Workbook
Name Roles: #REF!
Name Roles: #REF!

Sheet Filename
A1: RBR file name content | AM1: Only EE and LT file name content
A2: Project name | F2: _ | G2: Originator/ Supplier/ Contractor | H2: _ | I2: Volume_System/Zone | L2: _ | M2: Location | N2: _ | O2: Document type RBDTD-EE-DS3-DPS1_PLU_OP-058-ZZ_ZZZZ_IF_IS_VE_000001 | T2: _ | U2: Discipline code | AB2: _ | AC2: Project stage | AH2: _ | AI2: Number | AJ2: _ | AK2: Revision No. | AL2: _ | AM2: Drawing name | AN2: _ | AO2: Number of the buildings in the project | AP2: - | AQ2: Document's running number within the project
A3: EE file name relevant | C3: EE file name relevant | E3: EE file name relevant | O3: EE file name relevant | U3: EE file name relevant | AC3: EE file name relevant | AK3: EE file name relevant | AM3: EE file name relevant | AO3: LT file name relevant | AQ3: EE file name relevant
A4: LT file name relevant | C4: LT file name relevant | E4: LT file name relevant | O4: LT file name relevant | U4: LT file name relevant | AC4: LT file name relevant | AQ4: LT file name relevant
A5: PROJECT ID | B5: - | C5: SECTION ID | D5: - | E5: SUB-SECTION ID | G5: Abbreviation of the originator of the document Predefined list ORIGINATOR_SUPPLIER Provided by RB Rail AS | I5: VOLUME/SYSTEM | J5: - | K5: ZONE | M5: Code of the location. Predefined list LOCATION Provided by RB Rail AS | O5: Abbreviation of the document type. Predefined list DOCUMENT TYPE Provided by RB Rail AS | Q5: RBR document type | S5: EE document type | U5: RBR discipline | W5: RBR CODE | Y5: LOCAL CODE EHR | AA5: LOCAL CODE MNT | AC5: Stage Description | AE5: Stage Code RBR | AG5: Stage Code EE | AH5: _ | AI5: Unique ID number of each construction object 000001-999999 | AJ5: _ | AK5: Revision number 1-999 | AM5: Drawing name. No limitations. | AO5: Number of the buildings in the project. According to LST 1516:2015 | AQ5: Document's running number within the project According to LST 1516:2015 | AS5: LT RELEVANT | AZ5: EE and LT relevant
A6: Project name according to DTD TS Predefined list PROJECT ID Provided by RB Rail AS | C6: Section name according to DTD TS Predefined list SECTION ID Provided by RB Rail AS | E6: Sub-section name according to DTD TS Predefined list SUB-SECTION ID Provided by RB Rail AS | I6: Code of the volume/ system. Predefined list VOLUME_SYSTEM Provided by RB Rail AS | K6: Code of the zone. Predefined list ZONE Provided by RB Rail AS | Q6: RBR document type code Predefined list Provided by RB Rail AS | S6: EE document type code Predefined list Provided by RB Rail AS | U6: RBR discipline Predefined list Provided by RB Rail AS | W6: RBR discipline code Predefined list Provided by RB Rail AS | Y6: Discipline code according to local legislation Predefined list | AA6: Discipline code according to local legislation Predefined list | AC6: Abbreviation of the project stage. Predefined list PROJECT STAGE Provided by RB Rail AS | AE6: Abbreviation of the project stage. Predefined list PROJECT STAGE Provided by RB Rail AS | AG6: Abbreviation of the project stage. Predefined list PROJECT STAGE Provided by RB Rail AS | BA6: EE formatted
AY7: LT formatted | BA7: LT formatted
AS8: LT Project ID | AU8: LT Document type | AW8: LT Project Stage Code | AY8: Number of the building in the project | AZ8: Document's running number within the project | BC8: Preview of the EE EHR file name | BD8: Length of filename, charecters | BF8: Preview of the EE MNT file name | BG8: Length of filename, charecters | BI8: RBR file number | BJ8: Length of filename, charecters | BL8: RBR file number, with revision number (Only for IDOM) | BM8: Length of filename, charecters
A9: RBDTD-EE | B9: =IF(C9=0,"","-") -> - | C9: DS1 | D9: =IF(E9=0,"","-") -> - | E9: DPS1 | F9: =IF(G9=0,"","_") -> _ | G9: VER | H9: =IF(I9=0,"","_") -> _ | I9: CU102002 | J9: =IF(K9=0,"","-") -> - | K9: ZZ | L9: =IF(M9=0,"","_") -> _ | M9: ZZZZ | N9: =IF(O9=0,"","_") -> _ | O9: Survey | P9: =IF(Q9="","","-") -> - | Q9: =IF(O9="","",VLOOKUP(O9,'DOCUMENT TYPE'!$A$2:$D$805,2,)) -> SU | R9: =IF(S9="","","-") -> - | S9: =IF(O9="","",VLOOKUP(O9,'DOCUMENT TYPE'!$A$2:$D$805,3,)) -> 1 | T9: =IF(U9=0,"","_") -> _ | U9: Land Melioration | V9: =IF(W9="","","-") -> - | W9: =IF(U9="","",VLOOKUP(U9,'ACTIVITY & DISCIPLINE CODE'!$F$3:$I$1863,2,)) -> DR | X9: =IF(Y9="","","-") -> - | Y9: =IF(U9="","",VLOOKUP(U9,'ACTIVITY & DISCIPLINE CODE'!$F$3:$I$1863,3,)) -> VK | Z9: =IF(AA9="","","_") -> _ | AA9: =IF(U9="","",VLOOKUP(U9,'ACTIVITY & DISCIPLINE CODE'!$F$3:$I$1863,4,)) -> DR | AB9: =IF(AC9=0,"","_") -> _ | AC9: Detailed Technical Design | AD9: =IF(AE9="","","-") -> - | AE9: =IF(AC9="","",VLOOKUP(AC9,'PROJECT STAGE'!$A$2:$C$100,2,)) -> DTD | AF9: =IF(AG9="","","_") -> _ | AG9: =IF(AC9="","",VLOOKUP(AC9,'PROJECT STAGE'!$A$2:$C$100,3,)) -> TP | AH9: =IF(AI9="","","_") -> _ | AI9: 1 | AJ9: =IF(AK9="","","_") -> _ | AK9: 9 | AL9: =IF(AM9="","","_") -> _ | AM9: Notes_Drawing name | AN9: =IF(AO9=0,"","_") -> _ | AO9: 1 | AP9: =IF(AQ9="","","-") -> - | AQ9: 1 | AS9: =IF(A9="RBDTD-LT", "RBDTDLT","Not LT section__") -> Not LT section__ | AT9: =IF(AU9=0,"",".") | AU9: =IF(O9=0,"No input data",INDEX('DOCUMENT TYPE'!D:D,MATCH(Filename!O9,'DOCUMENT TYPE'!A:A,0))) -> 0 | AV9: =IF(AW9=0,"","-") -> - | AW9: =IF(AC9="PD","PP",IF(AC9="MD","TP",IF(AC9="DTD","DP","Check PROJECT STAGE"))) -> Check PROJECT STAGE | AX9: =IF(AY9>"0","-","") -> - | AY9: =IF(AO9=0,"",TEXT(AO9,"00")) -> 01 | AZ9: =IF(BA9>"0","-","") -> - | BA9: =IF(AQ9=0,"",TEXT(AQ9,"00")) -> 01 | BC9: =IF(Y9="","Missing input data",IF(Y9="-","Missing input data",_xlfn.TEXTJOIN(,,C9,E9,I9,AF9,AG9,X9,Y9,R9:S9,AP9,(TEXT(AQ9,"00")),AJ9,(TEXT(AK9,"v00")),AL9:AM9))) -> DS1DPS1CU102002_TP-VK-1-01_v09_Notes_Drawing name | BD9: =IF(Y9="","Missing input data",IF(Y9="-","Missing input data",LEN(BC9))) -> 49 | BF9: =IF(AA9="","Missing input data",IF(AA9="-","Missing input data",_xlfn.TEXTJOIN(,,A9:E9,AF9,AG9,P9,AA9,R9:S9,AP9,(TEXT(AQ9,"00")),AJ9,(TEXT(AK9,"v00")),AL9:AM9))) -> RBDTD-EE-DS1-DPS1_TP-DR-1-01_v09_Notes_Drawing name | BG9: =IF(AA9="","Missing input data",IF(AA9="-","Missing input data",LEN(BF9))) -> 51 | BI9: =IF(W9="","Missing input data",IF(W9="-","Missing input data",_xlfn.TEXTJOIN(,,A9:N9,Q9,T9,W9:Y9,AB9,AE9,AH9,(TEXT(AI9,"000000")),AL9:AM9))) -> RBDTD-EE-DS1-DPS1_VER_CU102002-ZZ_ZZZZ_SU_DR-VK_DTD_000001_Notes_Drawing name | BJ9: =IF(W9="","Missing input data",IF(W9="-","Missing input data",LEN(BI9))) -> 77 | BL9: =IF(W9="","Missing input data",IF(W9="-","Missing input data",_xlfn.TEXTJOIN(,,A9:N9,Q9,T9,W9:Y9,AB9,AE9,AH9,(TEXT(AI9,"000000")),AJ9,(TEXT(AK9,"000"))))) -> RBDTD-EE-DS1-DPS1_VER_CU102002-ZZ_ZZZZ_SU_DR-VK_DTD_000001_009 | BM9: =IF(W9="","Missing input data",IF(W9="-","Missing input data",LEN(BL9))) -> 62
B10: =IF(C10=0,"","-") | D10: =IF(E10=0,"","-") | F10: =IF(G10=0,"","_") | H10: =IF(I10=0,"","_") | J10: =IF(K10=0,"","-") | L10: =IF(M10=0,"","_") | N10: =IF(O10=0,"","_") | P10: =IF(Q10="","","-") | Q10: =IF(O10="","",VLOOKUP(O10,'DOCUMENT TYPE'!$A$2:$D$805,2,)) | R10: =IF(S10="","","-") | S10: =IF(O10="","",VLOOKUP(O10,'DOCUMENT TYPE'!$A$2:$D$805,3,)) | T10: =IF(U10=0,"","_") | V10: =IF(W10="","","-") | W10: =IF(U10="","",VLOOKUP(U10,'ACTIVITY & DISCIPLINE CODE'!$F$3:$I$1863,2,)) | X10: =IF(Y10="","","-") | Y10: =IF(U10="","",VLOOKUP(U10,'ACTIVITY & DISCIPLINE CODE'!$F$3:$I$1863,3,)) | Z10: =IF(AA10="","","_") | AA10: =IF(U10="","",VLOOKUP(U10,'ACTIVITY & DISCIPLINE CODE'!$F$3:$I$1863,4,)) | AB10: =IF(AC10=0,"","_") | AD10: =IF(AE10="","","-") | AE10: =IF(AC10="","",VLOOKUP(AC10,'PROJECT STAGE'!$A$2:$C$100,2,)) | AF10: =IF(AG10="","","_") | AG10: =IF(AC10="","",VLOOKUP(AC10,'PROJECT STAGE'!$A$2:$C$100,3,)) | AH10: =IF(AI10="","","_") | AJ10: =IF(AK10="","","_") | AL10: =IF(AM10="","","_") | AN10: =IF(AO10=0,"","_") -> _ | AO10: 2 | AP10: =IF(AQ10="","","-") | AS10: =IF(A10="RBDTD-LT", "RBDTDLT","Not LT section") -> Not LT section | AT10: =IF(AU10=0,"",".") -> . | AU10: =IF(O10=0,"No input data",INDEX('DOCUMENT TYPE'!D:D,MATCH(Filename!O10,'DOCUMENT TYPE'!A:A,0))) -> No input data | AV10: =IF(AW10=0,"","-") -> - | AW10: =IF(AC10="PD","PP",IF(AC10="MD","TP",IF(AC10="DTD","DP","Check PROJECT STAGE"))) -> Check PROJECT STAGE | AX10: =IF(AY10>"0","-","") -> - | AY10: =IF(AO10=0,"",TEXT(AO10,"00")) -> 02 | AZ10: =IF(BA10>"0","-","") | BA10: =IF(AQ10=0,"",TEXT(AQ10,"00")) | BC10: =IF(Y10="","Missing input data",IF(Y10="-","Missing input data",_xlfn.TEXTJOIN(,,A10:E10,AF10,AG10,P10,Y10,R10:S10,AP10,(TEXT(AQ10,"00")),AJ10,(TEXT(AK10,"v00")),AL10:AM10))) -> Missing input data | BD10: =IF(Y10="","Missing input data",IF(Y10="-","Missing input data",LEN(BC10))) -> Missing input data | BF10: =IF(AA10="","Missing input data",IF(AA10="-","Missing input data",_xlfn.TEXTJOIN(,,A10:E10,AF10,AG10,P10,AA10,R10:S10,AP10,(TEXT(AQ10,"00")),AJ10,(TEXT(AK10,"v00")),AL10:AM10))) -> Missing input data | BG10: =IF(AA10="","Missing input data",IF(AA10="-","Missing input data",LEN(BF10))) -> Missing input data | BI10: =IF(W10="","Missing input data",IF(W10="-","Missing input data",_xlfn.TEXTJOIN(,,A10:N10,Q10,T10,W10:Y10,AB10,AE10,AH10,(TEXT(AI10,"000000")),AL10:AM10))) -> Missing input data | BJ10: =IF(W10="","Missing input data",IF(W10="-","Missing input data",LEN(BI10))) -> Missing input data | BL10: =IF(W10="","Missing input data",IF(W10="-","Missing input data",_xlfn.TEXTJOIN(,,A10:N10,Q10,T10,W10:Y10,AB10,AE10,AH10,(TEXT(AI10,"000000")),AJ10,(TEXT(AK10,"000"))))) -> Missing input data | BM10: =IF(W10="","Missing input data",IF(W10="-","Missing input data",LEN(BL10))) -> Missing input data
B11: =IF(C11=0,"","-") | D11: =IF(E11=0,"","-") | F11: =IF(G11=0,"","_") | H11: =IF(I11=0,"","_") | J11: =IF(K11=0,"","-") | L11: =IF(M11=0,"","_") | N11: =IF(O11=0,"","_") | P11: =IF(Q11="","","-") | Q11: =IF(O11="","",VLOOKUP(O11,'DOCUMENT TYPE'!$A$2:$D$805,2,)) | R11: =IF(S11="","","-") | S11: =IF(O11="","",VLOOKUP(O11,'DOCUMENT TYPE'!$A$2:$D$805,3,)) | T11: =IF(U11=0,"","_") | V11: =IF(W11="","","-") | W11: =IF(U11="","",VLOOKUP(U11,'ACTIVITY & DISCIPLINE CODE'!$F$3:$I$1863,2,)) | X11: =IF(Y11="","","-") | Y11: =IF(U11="","",VLOOKUP(U11,'ACTIVITY & DISCIPLINE CODE'!$F$3:$I$1863,3,)) | Z11: =IF(AA11="","","_") | AA11: =IF(U11="","",VLOOKUP(U11,'ACTIVITY & DISCIPLINE CODE'!$F$3:$I$1863,4,)) | AB11: =IF(AC11=0,"","_") | AD11: =IF(AE11="","","-") | AE11: =IF(AC11="","",VLOOKUP(AC11,'PROJECT STAGE'!$A$2:$C$100,2,)) | AF11: =IF(AG11="","","_") | AG11: =IF(AC11="","",VLOOKUP(AC11,'PROJECT STAGE'!$A$2:$C$100,3,)) | AH11: =IF(AI11="","","_") | AJ11: =IF(AK11="","","_") | AL11: =IF(AM11="","","_") | AN11: =IF(AO11=0,"","_") | AP11: =IF(AQ11="","","-") | AS11: =IF(A11="RBDTD-LT", "RBDTDLT","Not LT section") -> Not LT section | AT11: =IF(AU11=0,"",".") -> . | AU11: =IF(O11=0,"No input data",INDEX('DOCUMENT TYPE'!D:D,MATCH(Filename!O11,'DOCUMENT TYPE'!A:A,0))) -> No input data | AV11: =IF(AW11=0,"","-") -> - | AW11: =IF(AC11="PD","PP",IF(AC11="MD","TP",IF(AC11="DTD","DP","Check PROJECT STAGE"))) -> Check PROJECT STAGE | AX11: =IF(AY11>"0","-","") | AY11: =IF(AO11=0,"",TEXT(AO11,"00")) | AZ11: =IF(BA11>"0","-","") | BA11: =IF(AQ11=0,"",TEXT(AQ11,"00")) | BC11: =IF(Y11="","Missing input data",IF(Y11="-","Missing input data",_xlfn.TEXTJOIN(,,A11:E11,AF11,AG11,P11,Y11,R11:S11,AP11,(TEXT(AQ11,"00")),AJ11,(TEXT(AK11,"v00")),AL11:AM11))) -> Missing input data | BD11: =IF(Y11="","Missing input data",IF(Y11="-","Missing input data",LEN(BC11))) -> Missing input data | BF11: =IF(AA11="","Missing input data",IF(AA11="-","Missing input data",_xlfn.TEXTJOIN(,,A11:E11,AF11,AG11,P11,AA11,R11:S11,AP11,(TEXT(AQ11,"00")),AJ11,(TEXT(AK11,"v00")),AL11:AM11))) -> Missing input data | BG11: =IF(AA11="","Missing input data",IF(AA11="-","Missing input data",LEN(BF11))) -> Missing input data | BI11: =IF(W11="","Missing input data",IF(W11="-","Missing input data",_xlfn.TEXTJOIN(,,A11:N11,Q11,T11,W11:Y11,AB11,AE11,AH11,(TEXT(AI11,"000000")),AL11:AM11))) -> Missing input data | BJ11: =IF(W11="","Missing input data",IF(W11="-","Missing input data",LEN(BI11))) -> Missing input data | BL11: =IF(W11="","Missing input data",IF(W11="-","Missing input data",_xlfn.TEXTJOIN(,,A11:N11,Q11,T11,W11:Y11,AB11,AE11,AH11,(TEXT(AI11,"000000")),AJ11,(TEXT(AK11,"000"))))) -> Missing input data | BM11: =IF(W11="","Missing input data",IF(W11="-","Missing input data",LEN(BL11))) -> Missing input data
B12: =IF(C12=0,"","-") | D12: =IF(E12=0,"","-") | F12: =IF(G12=0,"","_") | H12: =IF(I12=0,"","_") | J12: =IF(K12=0,"","-") | L12: =IF(M12=0,"","_") | N12: =IF(O12=0,"","_") | P12: =IF(Q12="","","-") | Q12: =IF(O12="","",VLOOKUP(O12,'DOCUMENT TYPE'!$A$2:$D$805,2,)) | R12: =IF(S12="","","-") | S12: =IF(O12="","",VLOOKUP(O12,'DOCUMENT TYPE'!$A$2:$D$805,3,)) | T12: =IF(U12=0,"","_") | V12: =IF(W12="","","-") | W12: =IF(U12="","",VLOOKUP(U12,'ACTIVITY & DISCIPLINE CODE'!$F$3:$I$1863,2,)) | X12: =IF(Y12="","","-") | Y12: =IF(U12="","",VLOOKUP(U12,'ACTIVITY & DISCIPLINE CODE'!$F$3:$I$1863,3,)) | Z12: =IF(AA12="","","_") | AA12: =IF(U12="","",VLOOKUP(U12,'ACTIVITY & DISCIPLINE CODE'!$F$3:$I$1863,4,)) | AB12: =IF(AC12=0,"","_") | AD12: =IF(AE12="","","-") | AE12: =IF(AC12="","",VLOOKUP(AC12,'PROJECT STAGE'!$A$2:$C$100,2,)) | AF12: =IF(AG12="","","_") | AG12: =IF(AC12="","",VLOOKUP(AC12,'PROJECT STAGE'!$A$2:$C$100,3,)) | AH12: =IF(AI12="","","_") | AJ12: =IF(AK12="","","_") | AL12: =IF(AM12="","","_") | AN12: =IF(AO12=0,"","_") | AP12: =IF(AQ12="","","-") | AS12: =IF(A12="RBDTD-LT", "RBDTDLT","Not LT section") -> Not LT section | AT12: =IF(AU12=0,"",".") -> . | AU12: =IF(O12=0,"No input data",INDEX('DOCUMENT TYPE'!D:D,MATCH(Filename!O12,'DOCUMENT TYPE'!A:A,0))) -> No input data | AV12: =IF(AW12=0,"","-") -> - | AW12: =IF(AC12="PD","PP",IF(AC12="MD","TP",IF(AC12="DTD","DP","Check PROJECT STAGE"))) -> Check PROJECT STAGE | AX12: =IF(AY12>"0","-","") | AY12: =IF(AO12=0,"",TEXT(AO12,"00")) | AZ12: =IF(BA12>"0","-","") | BA12: =IF(AQ12=0,"",TEXT(AQ12,"00")) | BC12: =IF(Y12="","Missing input data",IF(Y12="-","Missing input data",_xlfn.TEXTJOIN(,,A12:E12,AF12,AG12,P12,Y12,R12:S12,AP12,(TEXT(AQ12,"00")),AJ12,(TEXT(AK12,"v00")),AL12:AM12))) -> Missing input data | BD12: =IF(Y12="","Missing input data",IF(Y12="-","Missing input data",LEN(BC12))) -> Missing input data | BF12: =IF(AA12="","Missing input data",IF(AA12="-","Missing input data",_xlfn.TEXTJOIN(,,A12:E12,AF12,AG12,P12,AA12,R12:S12,AP12,(TEXT(AQ12,"00")),AJ12,(TEXT(AK12,"v00")),AL12:AM12))) -> Missing input data | BG12: =IF(AA12="","Missing input data",IF(AA12="-","Missing input data",LEN(BF12))) -> Missing input data | BI12: =IF(W12="","Missing input data",IF(W12="-","Missing input data",_xlfn.TEXTJOIN(,,A12:N12,Q12,T12,W12:Y12,AB12,AE12,AH12,(TEXT(AI12,"000000")),AL12:AM12))) -> Missing input data | BJ12: =IF(W12="","Missing input data",IF(W12="-","Missing input data",LEN(BI12))) -> Missing input data | BL12: =IF(W12="","Missing input data",IF(W12="-","Missing input data",_xlfn.TEXTJOIN(,,A12:N12,Q12,T12,W12:Y12,AB12,AE12,AH12,(TEXT(AI12,"000000")),AJ12,(TEXT(AK12,"000"))))) -> Missing input data | BM12: =IF(W12="","Missing input data",IF(W12="-","Missing input data",LEN(BL12))) -> Missing input data
B13: =IF(C13=0,"","-") | D13: =IF(E13=0,"","-") | F13: =IF(G13=0,"","_") | H13: =IF(I13=0,"","_") | J13: =IF(K13=0,"","-") | L13: =IF(M13=0,"","_") | N13: =IF(O13=0,"","_") | P13: =IF(Q13="","","-") | Q13: =IF(O13="","",VLOOKUP(O13,'DOCUMENT TYPE'!$A$2:$D$805,2,)) | R13: =IF(S13="","","-") | S13: =IF(O13="","",VLOOKUP(O13,'DOCUMENT TYPE'!$A$2:$D$805,3,)) | T13: =IF(U13=0,"","_") | V13: =IF(W13="","","-") | W13: =IF(U13="","",VLOOKUP(U13,'ACTIVITY & DISCIPLINE CODE'!$F$3:$I$1863,2,)) | X13: =IF(Y13="","","-") | Y13: =IF(U13="","",VLOOKUP(U13,'ACTIVITY & DISCIPLINE CODE'!$F$3:$I$1863,3,)) | Z13: =IF(AA13="","","_") | AA13: =IF(U13="","",VLOOKUP(U13,'ACTIVITY & DISCIPLINE CODE'!$F$3:$I$1863,4,)) | AB13: =IF(AC13=0,"","_") | AD13: =IF(AE13="","","-") | AE13: =IF(AC13="","",VLOOKUP(AC13,'PROJECT STAGE'!$A$2:$C$100,2,)) | AF13: =IF(AG13="","","_") | AG13: =IF(AC13="","",VLOOKUP(AC13,'PROJECT STAGE'!$A$2:$C$100,3,)) | AH13: =IF(AI13="","","_") | AJ13: =IF(AK13="","","_") | AL13: =IF(AM13="","","_") | AN13: =IF(AO13=0,"","_") | AP13: =IF(AQ13="","","-") | AS13: =IF(A13="RBDTD-LT", "RBDTDLT","Not LT section") -> Not LT section | AT13: =IF(AU13=0,"",".") -> . | AU13: =IF(O13=0,"No input data",INDEX('DOCUMENT TYPE'!D:D,MATCH(Filename!O13,'DOCUMENT TYPE'!A:A,0))) -> No input data | AV13: =IF(AW13=0,"","-") -> - | AW13: =IF(AC13="PD","PP",IF(AC13="MD","TP",IF(AC13="DTD","DP","Check PROJECT STAGE"))) -> Check PROJECT STAGE | AX13: =IF(AY13>"0","-","") | AY13: =IF(AO13=0,"",TEXT(AO13,"00")) | AZ13: =IF(BA13>"0","-","") | BA13: =IF(AQ13=0,"",TEXT(AQ13,"00")) | BC13: =IF(Y13="","Missing input data",IF(Y13="-","Missing input data",_xlfn.TEXTJOIN(,,A13:E13,AF13,AG13,P13,Y13,R13:S13,AP13,(TEXT(AQ13,"00")),AJ13,(TEXT(AK13,"v00")),AL13:AM13))) -> Missing input data | BD13: =IF(Y13="","Missing input data",IF(Y13="-","Missing input data",LEN(BC13))) -> Missing input data | BF13: =IF(AA13="","Missing input data",IF(AA13="-","Missing input data",_xlfn.TEXTJOIN(,,A13:E13,AF13,AG13,P13,AA13,R13:S13,AP13,(TEXT(AQ13,"00")),AJ13,(TEXT(AK13,"v00")),AL13:AM13))) -> Missing input data | BG13: =IF(AA13="","Missing input data",IF(AA13="-","Missing input data",LEN(BF13))) -> Missing input data | BI13: =IF(W13="","Missing input data",IF(W13="-","Missing input data",_xlfn.TEXTJOIN(,,A13:N13,Q13,T13,W13:Y13,AB13,AE13,AH13,(TEXT(AI13,"000000")),AL13:AM13))) -> Missing input data | BJ13: =IF(W13="","Missing input data",IF(W13="-","Missing input data",LEN(BI13))) -> Missing input data | BL13: =IF(W13="","Missing input data",IF(W13="-","Missing input data",_xlfn.TEXTJOIN(,,A13:N13,Q13,T13,W13:Y13,AB13,AE13,AH13,(TEXT(AI13,"000000")),AJ13,(TEXT(AK13,"000"))))) -> Missing input data | BM13: =IF(W13="","Missing input data",IF(W13="-","Missing input data",LEN(BL13))) -> Missing input data
B14: =IF(C14=0,"","-") | D14: =IF(E14=0,"","-") | F14: =IF(G14=0,"","_") | H14: =IF(I14=0,"","_") | J14: =IF(K14=0,"","-") | L14: =IF(M14=0,"","_") | N14: =IF(O14=0,"","_") | P14: =IF(Q14="","","-") | Q14: =IF(O14="","",VLOOKUP(O14,'DOCUMENT TYPE'!$A$2:$D$805,2,)) | R14: =IF(S14="","","-") | S14: =IF(O14="","",VLOOKUP(O14,'DOCUMENT TYPE'!$A$2:$D$805,3,)) | T14: =IF(U14=0,"","_") | V14: =IF(W14="","","-") | W14: =IF(U14="","",VLOOKUP(U14,'ACTIVITY & DISCIPLINE CODE'!$F$3:$I$1863,2,)) | X14: =IF(Y14="","","-") | Y14: =IF(U14="","",VLOOKUP(U14,'ACTIVITY & DISCIPLINE CODE'!$F$3:$I$1863,3,)) | Z14: =IF(AA14="","","_") | AA14: =IF(U14="","",VLOOKUP(U14,'ACTIVITY & DISCIPLINE CODE'!$F$3:$I$1863,4,)) | AB14: =IF(AC14=0,"","_") | AD14: =IF(AE14="","","-") | AE14: =IF(AC14="","",VLOOKUP(AC14,'PROJECT STAGE'!$A$2:$C$100,2,)) | AF14: =IF(AG14="","","_") | AG14: =IF(AC14="","",VLOOKUP(AC14,'PROJECT STAGE'!$A$2:$C$100,3,)) | AH14: =IF(AI14="","","_") | AJ14: =IF(AK14="","","_") | AL14: =IF(AM14="","","_") | AN14: =IF(AO14=0,"","_") | AP14: =IF(AQ14="","","-") | AS14: =IF(A14="RBDTD-LT", "RBDTDLT","Not LT section") -> Not LT section | AT14: =IF(AU14=0,"",".") -> . | AU14: =IF(O14=0,"No input data",INDEX('DOCUMENT TYPE'!D:D,MATCH(Filename!O14,'DOCUMENT TYPE'!A:A,0))) -> No input data | AV14: =IF(AW14=0,"","-") -> - | AW14: =IF(AC14="PD","PP",IF(AC14="MD","TP",IF(AC14="DTD","DP","Check PROJECT STAGE"))) -> Check PROJECT STAGE | AX14: =IF(AY14>"0","-","") | AY14: =IF(AO14=0,"",TEXT(AO14,"00")) | AZ14: =IF(BA14>"0","-","") | BA14: =IF(AQ14=0,"",TEXT(AQ14,"00")) | BC14: =IF(Y14="","Missing input data",IF(Y14="-","Missing input data",_xlfn.TEXTJOIN(,,A14:E14,AF14,AG14,P14,Y14,R14:S14,AP14,(TEXT(AQ14,"00")),AJ14,(TEXT(AK14,"v00")),AL14:AM14))) -> Missing input data | BD14: =IF(Y14="","Missing input data",IF(Y14="-","Missing input data",LEN(BC14))) -> Missing input data | BF14: =IF(AA14="","Missing input data",IF(AA14="-","Missing input data",_xlfn.TEXTJOIN(,,A14:E14,AF14,AG14,P14,AA14,R14:S14,AP14,(TEXT(AQ14,"00")),AJ14,(TEXT(AK14,"v00")),AL14:AM14))) -> Missing input data | BG14: =IF(AA14="","Missing input data",IF(AA14="-","Missing input data",LEN(BF14))) -> Missing input data | BI14: =IF(W14="","Missing input data",IF(W14="-","Missing input data",_xlfn.TEXTJOIN(,,A14:N14,Q14,T14,W14:Y14,AB14,AE14,AH14,(TEXT(AI14,"000000")),AL14:AM14))) -> Missing input data | BJ14: =IF(W14="","Missing input data",IF(W14="-","Missing input data",LEN(BI14))) -> Missing input data | BL14: =IF(W14="","Missing input data",IF(W14="-","Missing input data",_xlfn.TEXTJOIN(,,A14:N14,Q14,T14,W14:Y14,AB14,AE14,AH14,(TEXT(AI14,"000000")),AJ14,(TEXT(AK14,"000"))))) -> Missing input data | BM14: =IF(W14="","Missing input data",IF(W14="-","Missing input data",LEN(BL14))) -> Missing input data
B15: =IF(C15=0,"","-") | D15: =IF(E15=0,"","-") | F15: =IF(G15=0,"","_") | H15: =IF(I15=0,"","_") | J15: =IF(K15=0,"","-") | L15: =IF(M15=0,"","_") | N15: =IF(O15=0,"","_") | P15: =IF(Q15="","","-") | Q15: =IF(O15="","",VLOOKUP(O15,'DOCUMENT TYPE'!$A$2:$D$805,2,)) | R15: =IF(S15="","","-") | S15: =IF(O15="","",VLOOKUP(O15,'DOCUMENT TYPE'!$A$2:$D$805,3,)) | T15: =IF(U15=0,"","_") | V15: =IF(W15="","","-") | W15: =IF(U15="","",VLOOKUP(U15,'ACTIVITY & DISCIPLINE CODE'!$F$3:$I$1863,2,)) | X15: =IF(Y15="","","-") | Y15: =IF(U15="","",VLOOKUP(U15,'ACTIVITY & DISCIPLINE CODE'!$F$3:$I$1863,3,)) | Z15: =IF(AA15="","","_") | AA15: =IF(U15="","",VLOOKUP(U15,'ACTIVITY & DISCIPLINE CODE'!$F$3:$I$1863,4,)) | AB15: =IF(AC15=0,"","_") | AD15: =IF(AE15="","","-") | AE15: =IF(AC15="","",VLOOKUP(AC15,'PROJECT STAGE'!$A$2:$C$100,2,)) | AF15: =IF(AG15="","","_") | AG15: =IF(AC15="","",VLOOKUP(AC15,'PROJECT STAGE'!$A$2:$C$100,3,)) | AH15: =IF(AI15="","","_") | AJ15: =IF(AK15="","","_") | AL15: =IF(AM15="","","_") | AN15: =IF(AO15=0,"","_") | AP15: =IF(AQ15="","","-") | AS15: =IF(A15="RBDTD-LT", "RBDTDLT","Not LT section") -> Not LT section | AT15: =IF(AU15=0,"",".") -> . | AU15: =IF(O15=0,"No input data",INDEX('DOCUMENT TYPE'!D:D,MATCH(Filename!O15,'DOCUMENT TYPE'!A:A,0))) -> No input data | AV15: =IF(AW15=0,"","-") -> - | AW15: =IF(AC15="PD","PP",IF(AC15="MD","TP",IF(AC15="DTD","DP","Check PROJECT STAGE"))) -> Check PROJECT STAGE | AX15: =IF(AY15>"0","-","") | AY15: =IF(AO15=0,"",TEXT(AO15,"00")) | AZ15: =IF(BA15>"0","-","") | BA15: =IF(AQ15=0,"",TEXT(AQ15,"00")) | BC15: =IF(Y15="","Missing input data",IF(Y15="-","Missing input data",_xlfn.TEXTJOIN(,,A15:E15,AF15,AG15,P15,Y15,R15:S15,AP15,(TEXT(AQ15,"00")),AJ15,(TEXT(AK15,"v00")),AL15:AM15))) -> Missing input data | BD15: =IF(Y15="","Missing input data",IF(Y15="-","Missing input data",LEN(BC15))) -> Missing input data | BF15: =IF(AA15="","Missing input data",IF(AA15="-","Missing input data",_xlfn.TEXTJOIN(,,A15:E15,AF15,AG15,P15,AA15,R15:S15,AP15,(TEXT(AQ15,"00")),AJ15,(TEXT(AK15,"v00")),AL15:AM15))) -> Missing input data | BG15: =IF(AA15="","Missing input data",IF(AA15="-","Missing input data",LEN(BF15))) -> Missing input data | BI15: =IF(W15="","Missing input data",IF(W15="-","Missing input data",_xlfn.TEXTJOIN(,,A15:N15,Q15,T15,W15:Y15,AB15,AE15,AH15,(TEXT(AI15,"000000")),AL15:AM15))) -> Missing input data | BJ15: =IF(W15="","Missing input data",IF(W15="-","Missing input data",LEN(BI15))) -> Missing input data | BL15: =IF(W15="","Missing input data",IF(W15="-","Missing input data",_xlfn.TEXTJOIN(,,A15:N15,Q15,T15,W15:Y15,AB15,AE15,AH15,(TEXT(AI15,"000000")),AJ15,(TEXT(AK15,"000"))))) -> Missing input data | BM15: =IF(W15="","Missing input data",IF(W15="-","Missing input data",LEN(BL15))) -> Missing input data
B16: =IF(C16=0,"","-") | D16: =IF(E16=0,"","-") | F16: =IF(G16=0,"","_") | H16: =IF(I16=0,"","_") | J16: =IF(K16=0,"","-") | L16: =IF(M16=0,"","_") | N16: =IF(O16=0,"","_") | P16: =IF(Q16="","","-") | Q16: =IF(O16="","",VLOOKUP(O16,'DOCUMENT TYPE'!$A$2:$D$805,2,)) | R16: =IF(S16="","","-") | S16: =IF(O16="","",VLOOKUP(O16,'DOCUMENT TYPE'!$A$2:$D$805,3,)) | T16: =IF(U16=0,"","_") | V16: =IF(W16="","","-") | W16: =IF(U16="","",VLOOKUP(U16,'ACTIVITY & DISCIPLINE CODE'!$F$3:$I$1863,2,)) | X16: =IF(Y16="","","-") | Y16: =IF(U16="","",VLOOKUP(U16,'ACTIVITY & DISCIPLINE CODE'!$F$3:$I$1863,3,)) | Z16: =IF(AA16="","","_") | AA16: =IF(U16="","",VLOOKUP(U16,'ACTIVITY & DISCIPLINE CODE'!$F$3:$I$1863,4,)) | AB16: =IF(AC16=0,"","_") | AD16: =IF(AE16="","","-") | AE16: =IF(AC16="","",VLOOKUP(AC16,'PROJECT STAGE'!$A$2:$C$100,2,)) | AF16: =IF(AG16="","","_") | AG16: =IF(AC16="","",VLOOKUP(AC16,'PROJECT STAGE'!$A$2:$C$100,3,)) | AH16: =IF(AI16="","","_") | AJ16: =IF(AK16="","","_") | AL16: =IF(AM16="","","_") | AN16: =IF(AO16=0,"","_") | AP16: =IF(AQ16="","","-") | AS16: =IF(A16="RBDTD-LT", "RBDTDLT","Not LT section") -> Not LT section | AT16: =IF(AU16=0,"",".") -> . | AU16: =IF(O16=0,"No input data",INDEX('DOCUMENT TYPE'!D:D,MATCH(Filename!O16,'DOCUMENT TYPE'!A:A,0))) -> No input data | AV16: =IF(AW16=0,"","-") -> - | AW16: =IF(AC16="PD","PP",IF(AC16="MD","TP",IF(AC16="DTD","DP","Check PROJECT STAGE"))) -> Check PROJECT STAGE | AX16: =IF(AY16>"0","-","") | AY16: =IF(AO16=0,"",TEXT(AO16,"00")) | AZ16: =IF(BA16>"0","-","") | BA16: =IF(AQ16=0,"",TEXT(AQ16,"00")) | BC16: =IF(Y16="","Missing input data",IF(Y16="-","Missing input data",_xlfn.TEXTJOIN(,,A16:E16,AF16,AG16,P16,Y16,R16:S16,AP16,(TEXT(AQ16,"00")),AJ16,(TEXT(AK16,"v00")),AL16:AM16))) -> Missing input data | BD16: =IF(Y16="","Missing input data",IF(Y16="-","Missing input data",LEN(BC16))) -> Missing input data | BF16: =IF(AA16="","Missing input data",IF(AA16="-","Missing input data",_xlfn.TEXTJOIN(,,A16:E16,AF16,AG16,P16,AA16,R16:S16,AP16,(TEXT(AQ16,"00")),AJ16,(TEXT(AK16,"v00")),AL16:AM16))) -> Missing input data | BG16: =IF(AA16="","Missing input data",IF(AA16="-","Missing input data",LEN(BF16))) -> Missing input data | BI16: =IF(W16="","Missing input data",IF(W16="-","Missing input data",_xlfn.TEXTJOIN(,,A16:N16,Q16,T16,W16:Y16,AB16,AE16,AH16,(TEXT(AI16,"000000")),AL16:AM16))) -> Missing input data | BJ16: =IF(W16="","Missing input data",IF(W16="-","Missing input data",LEN(BI16))) -> Missing input data | BL16: =IF(W16="","Missing input data",IF(W16="-","Missing input data",_xlfn.TEXTJOIN(,,A16:N16,Q16,T16,W16:Y16,AB16,AE16,AH16,(TEXT(AI16,"000000")),AJ16,(TEXT(AK16,"000"))))) -> Missing input data | BM16: =IF(W16="","Missing input data",IF(W16="-","Missing input data",LEN(BL16))) -> Missing input data
B17: =IF(C17=0,"","-") | D17: =IF(E17=0,"","-") | F17: =IF(G17=0,"","_") | H17: =IF(I17=0,"","_") | J17: =IF(K17=0,"","-") | L17: =IF(M17=0,"","_") | N17: =IF(O17=0,"","_") | P17: =IF(Q17="","","-") | Q17: =IF(O17="","",VLOOKUP(O17,'DOCUMENT TYPE'!$A$2:$D$805,2,)) | R17: =IF(S17="","","-") | S17: =IF(O17="","",VLOOKUP(O17,'DOCUMENT TYPE'!$A$2:$D$805,3,)) | T17: =IF(U17=0,"","_") | V17: =IF(W17="","","-") | W17: =IF(U17="","",VLOOKUP(U17,'ACTIVITY & DISCIPLINE CODE'!$F$3:$I$1863,2,)) | X17: =IF(Y17="","","-") | Y17: =IF(U17="","",VLOOKUP(U17,'ACTIVITY & DISCIPLINE CODE'!$F$3:$I$1863,3,)) | Z17: =IF(AA17="","","_") | AA17: =IF(U17="","",VLOOKUP(U17,'ACTIVITY & DISCIPLINE CODE'!$F$3:$I$1863,4,)) | AB17: =IF(AC17=0,"","_") | AD17: =IF(AE17="","","-") | AE17: =IF(AC17="","",VLOOKUP(AC17,'PROJECT STAGE'!$A$2:$C$100,2,)) | AF17: =IF(AG17="","","_") | AG17: =IF(AC17="","",VLOOKUP(AC17,'PROJECT STAGE'!$A$2:$C$100,3,)) | AH17: =IF(AI17="","","_") | AJ17: =IF(AK17="","","_") | AL17: =IF(AM17="","","_") | AN17: =IF(AO17=0,"","_") | AP17: =IF(AQ17="","","-") | AS17: =IF(A17="RBDTD-LT", "RBDTDLT","Not LT section") -> Not LT section | AT17: =IF(AU17=0,"",".") -> . | AU17: =IF(O17=0,"No input data",INDEX('DOCUMENT TYPE'!D:D,MATCH(Filename!O17,'DOCUMENT TYPE'!A:A,0))) -> No input data | AV17: =IF(AW17=0,"","-") -> - | AW17: =IF(AC17="PD","PP",IF(AC17="MD","TP",IF(AC17="DTD","DP","Check PROJECT STAGE"))) -> Check PROJECT STAGE | AX17: =IF(AY17>"0","-","") | AY17: =IF(AO17=0,"",TEXT(AO17,"00")) | AZ17: =IF(BA17>"0","-","") | BA17: =IF(AQ17=0,"",TEXT(AQ17,"00")) | BC17: =IF(Y17="","Missing input data",IF(Y17="-","Missing input data",_xlfn.TEXTJOIN(,,A17:E17,AF17,AG17,P17,Y17,R17:S17,AP17,(TEXT(AQ17,"00")),AJ17,(TEXT(AK17,"v00")),AL17:AM17))) -> Missing input data | BD17: =IF(Y17="","Missing input data",IF(Y17="-","Missing input data",LEN(BC17))) -> Missing input data | BF17: =IF(AA17="","Missing input data",IF(AA17="-","Missing input data",_xlfn.TEXTJOIN(,,A17:E17,AF17,AG17,P17,AA17,R17:S17,AP17,(TEXT(AQ17,"00")),AJ17,(TEXT(AK17,"v00")),AL17:AM17))) -> Missing input data | BG17: =IF(AA17="","Missing input data",IF(AA17="-","Missing input data",LEN(BF17))) -> Missing input data | BI17: =IF(W17="","Missing input data",IF(W17="-","Missing input data",_xlfn.TEXTJOIN(,,A17:N17,Q17,T17,W17:Y17,AB17,AE17,AH17,(TEXT(AI17,"000000")),AL17:AM17))) -> Missing input data | BJ17: =IF(W17="","Missing input data",IF(W17="-","Missing input data",LEN(BI17))) -> Missing input data | BL17: =IF(W17="","Missing input data",IF(W17="-","Missing input data",_xlfn.TEXTJOIN(,,A17:N17,Q17,T17,W17:Y17,AB17,AE17,AH17,(TEXT(AI17,"000000")),AJ17,(TEXT(AK17,"000"))))) -> Missing input data | BM17: =IF(W17="","Missing input data",IF(W17="-","Missing input data",LEN(BL17))) -> Missing input data
B18: =IF(C18=0,"","-") | D18: =IF(E18=0,"","-") | F18: =IF(G18=0,"","_") | H18: =IF(I18=0,"","_") | J18: =IF(K18=0,"","-") | L18: =IF(M18=0,"","_") | N18: =IF(O18=0,"","_") | P18: =IF(Q18="","","-") | Q18: =IF(O18="","",VLOOKUP(O18,'DOCUMENT TYPE'!$A$2:$D$805,2,)) | R18: =IF(S18="","","-") | S18: =IF(O18="","",VLOOKUP(O18,'DOCUMENT TYPE'!$A$2:$D$805,3,)) | T18: =IF(U18=0,"","_") | V18: =IF(W18="","","-") | W18: =IF(U18="","",VLOOKUP(U18,'ACTIVITY & DISCIPLINE CODE'!$F$3:$I$1863,2,)) | X18: =IF(Y18="","","-") | Y18: =IF(U18="","",VLOOKUP(U18,'ACTIVITY & DISCIPLINE CODE'!$F$3:$I$1863,3,)) | Z18: =IF(AA18="","","_") | AA18: =IF(U18="","",VLOOKUP(U18,'ACTIVITY & DISCIPLINE CODE'!$F$3:$I$1863,4,)) | AB18: =IF(AC18=0,"","_") | AD18: =IF(AE18="","","-") | AE18: =IF(AC18="","",VLOOKUP(AC18,'PROJECT STAGE'!$A$2:$C$100,2,)) | AF18: =IF(AG18="","","_") | AG18: =IF(AC18="","",VLOOKUP(AC18,'PROJECT STAGE'!$A$2:$C$100,3,)) | AH18: =IF(AI18="","","_") | AJ18: =IF(AK18="","","_") | AL18: =IF(AM18="","","_") | AN18: =IF(AO18=0,"","_") | AP18: =IF(AQ18="","","-") | AS18: =IF(A18="RBDTD-LT", "RBDTDLT","Not LT section") -> Not LT section | AT18: =IF(AU18=0,"",".") -> . | AU18: =IF(O18=0,"No input data",INDEX('DOCUMENT TYPE'!D:D,MATCH(Filename!O18,'DOCUMENT TYPE'!A:A,0))) -> No input data | AV18: =IF(AW18=0,"","-") -> - | AW18: =IF(AC18="PD","PP",IF(AC18="MD","TP",IF(AC18="DTD","DP","Check PROJECT STAGE"))) -> Check PROJECT STAGE | AX18: =IF(AY18>"0","-","") | AY18: =IF(AO18=0,"",TEXT(AO18,"00")) | AZ18: =IF(BA18>"0","-","") | BA18: =IF(AQ18=0,"",TEXT(AQ18,"00")) | BC18: =IF(Y18="","Missing input data",IF(Y18="-","Missing input data",_xlfn.TEXTJOIN(,,A18:E18,AF18,AG18,P18,Y18,R18:S18,AP18,(TEXT(AQ18,"00")),AJ18,(TEXT(AK18,"v00")),AL18:AM18))) -> Missing input data | BD18: =IF(Y18="","Missing input data",IF(Y18="-","Missing input data",LEN(BC18))) -> Missing input data | BF18: =IF(AA18="","Missing input data",IF(AA18="-","Missing input data",_xlfn.TEXTJOIN(,,A18:E18,AF18,AG18,P18,AA18,R18:S18,AP18,(TEXT(AQ18,"00")),AJ18,(TEXT(AK18,"v00")),AL18:AM18))) -> Missing input data | BG18: =IF(AA18="","Missing input data",IF(AA18="-","Missing input data",LEN(BF18))) -> Missing input data | BI18: =IF(W18="","Missing input data",IF(W18="-","Missing input data",_xlfn.TEXTJOIN(,,A18:N18,Q18,T18,W18:Y18,AB18,AE18,AH18,(TEXT(AI18,"000000")),AL18:AM18))) -> Missing input data | BJ18: =IF(W18="","Missing input data",IF(W18="-","Missing input data",LEN(BI18))) -> Missing input data | BL18: =IF(W18="","Missing input data",IF(W18="-","Missing input data",_xlfn.TEXTJOIN(,,A18:N18,Q18,T18,W18:Y18,AB18,AE18,AH18,(TEXT(AI18,"000000")),AJ18,(TEXT(AK18,"000"))))) -> Missing input data | BM18: =IF(W18="","Missing input data",IF(W18="-","Missing input data",LEN(BL18))) -> Missing input data
B19: =IF(C19=0,"","-") | D19: =IF(E19=0,"","-") | F19: =IF(G19=0,"","_") | H19: =IF(I19=0,"","_") | J19: =IF(K19=0,"","-") | L19: =IF(M19=0,"","_") | N19: =IF(O19=0,"","_") | P19: =IF(Q19="","","-") | Q19: =IF(O19="","",VLOOKUP(O19,'DOCUMENT TYPE'!$A$2:$D$805,2,)) | R19: =IF(S19="","","-") | S19: =IF(O19="","",VLOOKUP(O19,'DOCUMENT TYPE'!$A$2:$D$805,3,)) | T19: =IF(U19=0,"","_") | V19: =IF(W19="","","-") | W19: =IF(U19="","",VLOOKUP(U19,'ACTIVITY & DISCIPLINE CODE'!$F$3:$I$1863,2,)) | X19: =IF(Y19="","","-") | Y19: =IF(U19="","",VLOOKUP(U19,'ACTIVITY & DISCIPLINE CODE'!$F$3:$I$1863,3,)) | Z19: =IF(AA19="","","_") | AA19: =IF(U19="","",VLOOKUP(U19,'ACTIVITY & DISCIPLINE CODE'!$F$3:$I$1863,4,)) | AB19: =IF(AC19=0,"","_") | AD19: =IF(AE19="","","-") | AE19: =IF(AC19="","",VLOOKUP(AC19,'PROJECT STAGE'!$A$2:$C$100,2,)) | AF19: =IF(AG19="","","_") | AG19: =IF(AC19="","",VLOOKUP(AC19,'PROJECT STAGE'!$A$2:$C$100,3,)) | AH19: =IF(AI19="","","_") | AJ19: =IF(AK19="","","_") | AL19: =IF(AM19="","","_") | AN19: =IF(AO19=0,"","_") | AP19: =IF(AQ19="","","-") | AS19: =IF(A19="RBDTD-LT", "RBDTDLT","Not LT section") -> Not LT section | AT19: =IF(AU19=0,"",".") -> . | AU19: =IF(O19=0,"No input data",INDEX('DOCUMENT TYPE'!D:D,MATCH(Filename!O19,'DOCUMENT TYPE'!A:A,0))) -> No input data | AV19: =IF(AW19=0,"","-") -> - | AW19: =IF(AC19="PD","PP",IF(AC19="MD","TP",IF(AC19="DTD","DP","Check PROJECT STAGE"))) -> Check PROJECT STAGE | AX19: =IF(AY19>"0","-","") | AY19: =IF(AO19=0,"",TEXT(AO19,"00")) | AZ19: =IF(BA19>"0","-","") | BA19: =IF(AQ19=0,"",TEXT(AQ19,"00")) | BC19: =IF(Y19="","Missing input data",IF(Y19="-","Missing input data",_xlfn.TEXTJOIN(,,A19:E19,AF19,AG19,P19,Y19,R19:S19,AP19,(TEXT(AQ19,"00")),AJ19,(TEXT(AK19,"v00")),AL19:AM19))) -> Missing input data | BD19: =IF(Y19="","Missing input data",IF(Y19="-","Missing input data",LEN(BC19))) -> Missing input data | BF19: =IF(AA19="","Missing input data",IF(AA19="-","Missing input data",_xlfn.TEXTJOIN(,,A19:E19,AF19,AG19,P19,AA19,R19:S19,AP19,(TEXT(AQ19,"00")),AJ19,(TEXT(AK19,"v00")),AL19:AM19))) -> Missing input data | BG19: =IF(AA19="","Missing input data",IF(AA19="-","Missing input data",LEN(BF19))) -> Missing input data | BI19: =IF(W19="","Missing input data",IF(W19="-","Missing input data",_xlfn.TEXTJOIN(,,A19:N19,Q19,T19,W19:Y19,AB19,AE19,AH19,(TEXT(AI19,"000000")),AL19:AM19))) -> Missing input data | BJ19: =IF(W19="","Missing input data",IF(W19="-","Missing input data",LEN(BI19))) -> Missing input data | BL19: =IF(W19="","Missing input data",IF(W19="-","Missing input data",_xlfn.TEXTJOIN(,,A19:N19,Q19,T19,W19:Y19,AB19,AE19,AH19,(TEXT(AI19,"000000")),AJ19,(TEXT(AK19,"000"))))) -> Missing input data | BM19: =IF(W19="","Missing input data",IF(W19="-","Missing input data",LEN(BL19))) -> Missing input data
B20: =IF(C20=0,"","-") | D20: =IF(E20=0,"","-") | F20: =IF(G20=0,"","_") | H20: =IF(I20=0,"","_") | J20: =IF(K20=0,"","-") | L20: =IF(M20=0,"","_") | N20: =IF(O20=0,"","_") | P20: =IF(Q20="","","-") | Q20: =IF(O20="","",VLOOKUP(O20,'DOCUMENT TYPE'!$A$2:$D$805,2,)) | R20: =IF(S20="","","-") | S20: =IF(O20="","",VLOOKUP(O20,'DOCUMENT TYPE'!$A$2:$D$805,3,)) | T20: =IF(U20=0,"","_") | V20: =IF(W20="","","-") | W20: =IF(U20="","",VLOOKUP(U20,'ACTIVITY & DISCIPLINE CODE'!$F$3:$I$1863,2,)) | X20: =IF(Y20="","","-") | Y20: =IF(U20="","",VLOOKUP(U20,'ACTIVITY & DISCIPLINE CODE'!$F$3:$I$1863,3,)) | Z20: =IF(AA20="","","_") | AA20: =IF(U20="","",VLOOKUP(U20,'ACTIVITY & DISCIPLINE CODE'!$F$3:$I$1863,4,)) | AB20: =IF(AC20=0,"","_") | AD20: =IF(AE20="","","-") | AE20: =IF(AC20="","",VLOOKUP(AC20,'PROJECT STAGE'!$A$2:$C$100,2,)) | AF20: =IF(AG20="","","_") | AG20: =IF(AC20="","",VLOOKUP(AC20,'PROJECT STAGE'!$A$2:$C$100,3,)) | AH20: =IF(AI20="","","_") | AJ20: =IF(AK20="","","_") | AL20: =IF(AM20="","","_") | AN20: =IF(AO20=0,"","_") | AP20: =IF(AQ20="","","-") | AS20: =IF(A20="RBDTD-LT", "RBDTDLT","Not LT section") -> Not LT section | AT20: =IF(AU20=0,"",".") -> . | AU20: =IF(O20=0,"No input data",INDEX('DOCUMENT TYPE'!D:D,MATCH(Filename!O20,'DOCUMENT TYPE'!A:A,0))) -> No input data | AV20: =IF(AW20=0,"","-") -> - | AW20: =IF(AC20="PD","PP",IF(AC20="MD","TP",IF(AC20="DTD","DP","Check PROJECT STAGE"))) -> Check PROJECT STAGE | AX20: =IF(AY20>"0","-","") | AY20: =IF(AO20=0,"",TEXT(AO20,"00")) | AZ20: =IF(BA20>"0","-","") | BA20: =IF(AQ20=0,"",TEXT(AQ20,"00")) | BC20: =IF(Y20="","Missing input data",IF(Y20="-","Missing input data",_xlfn.TEXTJOIN(,,A20:E20,AF20,AG20,P20,Y20,R20:S20,AP20,(TEXT(AQ20,"00")),AJ20,(TEXT(AK20,"v00")),AL20:AM20))) -> Missing input data | BD20: =IF(Y20="","Missing input data",IF(Y20="-","Missing input data",LEN(BC20))) -> Missing input data | BF20: =IF(AA20="","Missing input data",IF(AA20="-","Missing input data",_xlfn.TEXTJOIN(,,A20:E20,AF20,AG20,P20,AA20,R20:S20,AP20,(TEXT(AQ20,"00")),AJ20,(TEXT(AK20,"v00")),AL20:AM20))) -> Missing input data | BG20: =IF(AA20="","Missing input data",IF(AA20="-","Missing input data",LEN(BF20))) -> Missing input data | BI20: =IF(W20="","Missing input data",IF(W20="-","Missing input data",_xlfn.TEXTJOIN(,,A20:N20,Q20,T20,W20:Y20,AB20,AE20,AH20,(TEXT(AI20,"000000")),AL20:AM20))) -> Missing input data | BJ20: =IF(W20="","Missing input data",IF(W20="-","Missing input data",LEN(BI20))) -> Missing input data | BL20: =IF(W20="","Missing input data",IF(W20="-","Missing input data",_xlfn.TEXTJOIN(,,A20:N20,Q20,T20,W20:Y20,AB20,AE20,AH20,(TEXT(AI20,"000000")),AJ20,(TEXT(AK20,"000"))))) -> Missing input data | BM20: =IF(W20="","Missing input data",IF(W20="-","Missing input data",LEN(BL20))) -> Missing input data
B21: =IF(C21=0,"","-") | D21: =IF(E21=0,"","-") | F21: =IF(G21=0,"","_") | H21: =IF(I21=0,"","_") | J21: =IF(K21=0,"","-") | L21: =IF(M21=0,"","_") | N21: =IF(O21=0,"","_") | P21: =IF(Q21="","","-") | Q21: =IF(O21="","",VLOOKUP(O21,'DOCUMENT TYPE'!$A$2:$D$805,2,)) | R21: =IF(S21="","","-") | S21: =IF(O21="","",VLOOKUP(O21,'DOCUMENT TYPE'!$A$2:$D$805,3,)) | T21: =IF(U21=0,"","_") | V21: =IF(W21="","","-") | W21: =IF(U21="","",VLOOKUP(U21,'ACTIVITY & DISCIPLINE CODE'!$F$3:$I$1863,2,)) | X21: =IF(Y21="","","-") | Y21: =IF(U21="","",VLOOKUP(U21,'ACTIVITY & DISCIPLINE CODE'!$F$3:$I$1863,3,)) | Z21: =IF(AA21="","","_") | AA21: =IF(U21="","",VLOOKUP(U21,'ACTIVITY & DISCIPLINE CODE'!$F$3:$I$1863,4,)) | AB21: =IF(AC21=0,"","_") | AD21: =IF(AE21="","","-") | AE21: =IF(AC21="","",VLOOKUP(AC21,'PROJECT STAGE'!$A$2:$C$100,2,)) | AF21: =IF(AG21="","","_") | AG21: =IF(AC21="","",VLOOKUP(AC21,'PROJECT STAGE'!$A$2:$C$100,3,)) | AH21: =IF(AI21="","","_") | AJ21: =IF(AK21="","","_") | AL21: =IF(AM21="","","_") | AN21: =IF(AO21=0,"","_") | AP21: =IF(AQ21="","","-") | AS21: =IF(A21="RBDTD-LT", "RBDTDLT","Not LT section") -> Not LT section | AT21: =IF(AU21=0,"",".") -> . | AU21: =IF(O21=0,"No input data",INDEX('DOCUMENT TYPE'!D:D,MATCH(Filename!O21,'DOCUMENT TYPE'!A:A,0))) -> No input data | AV21: =IF(AW21=0,"","-") -> - | AW21: =IF(AC21="PD","PP",IF(AC21="MD","TP",IF(AC21="DTD","DP","Check PROJECT STAGE"))) -> Check PROJECT STAGE | AX21: =IF(AY21>"0","-","") | AY21: =IF(AO21=0,"",TEXT(AO21,"00")) | AZ21: =IF(BA21>"0","-","") | BA21: =IF(AQ21=0,"",TEXT(AQ21,"00")) | BC21: =IF(Y21="","Missing input data",IF(Y21="-","Missing input data",_xlfn.TEXTJOIN(,,A21:E21,AF21,AG21,P21,Y21,R21:S21,AP21,(TEXT(AQ21,"00")),AJ21,(TEXT(AK21,"v00")),AL21:AM21))) -> Missing input data | BD21: =IF(Y21="","Missing input data",IF(Y21="-","Missing input data",LEN(BC21))) -> Missing input data | BF21: =IF(AA21="","Missing input data",IF(AA21="-","Missing input data",_xlfn.TEXTJOIN(,,A21:E21,AF21,AG21,P21,AA21,R21:S21,AP21,(TEXT(AQ21,"00")),AJ21,(TEXT(AK21,"v00")),AL21:AM21))) -> Missing input data | BG21: =IF(AA21="","Missing input data",IF(AA21="-","Missing input data",LEN(BF21))) -> Missing input data | BI21: =IF(W21="","Missing input data",IF(W21="-","Missing input data",_xlfn.TEXTJOIN(,,A21:N21,Q21,T21,W21:Y21,AB21,AE21,AH21,(TEXT(AI21,"000000")),AL21:AM21))) -> Missing input data | BJ21: =IF(W21="","Missing input data",IF(W21="-","Missing input data",LEN(BI21))) -> Missing input data | BL21: =IF(W21="","Missing input data",IF(W21="-","Missing input data",_xlfn.TEXTJOIN(,,A21:N21,Q21,T21,W21:Y21,AB21,AE21,AH21,(TEXT(AI21,"000000")),AJ21,(TEXT(AK21,"000"))))) -> Missing input data | BM21: =IF(W21="","Missing input data",IF(W21="-","Missing input data",LEN(BL21))) -> Missing input data
B22: =IF(C22=0,"","-") | D22: =IF(E22=0,"","-") | F22: =IF(G22=0,"","_") | H22: =IF(I22=0,"","_") | J22: =IF(K22=0,"","-") | L22: =IF(M22=0,"","_") | N22: =IF(O22=0,"","_") | P22: =IF(Q22="","","-") | Q22: =IF(O22="","",VLOOKUP(O22,'DOCUMENT TYPE'!$A$2:$D$805,2,)) | R22: =IF(S22="","","-") | S22: =IF(O22="","",VLOOKUP(O22,'DOCUMENT TYPE'!$A$2:$D$805,3,)) | T22: =IF(U22=0,"","_") | V22: =IF(W22="","","-") | W22: =IF(U22="","",VLOOKUP(U22,'ACTIVITY & DISCIPLINE CODE'!$F$3:$I$1863,2,)) | X22: =IF(Y22="","","-") | Y22: =IF(U22="","",VLOOKUP(U22,'ACTIVITY & DISCIPLINE CODE'!$F$3:$I$1863,3,)) | Z22: =IF(AA22="","","_") | AA22: =IF(U22="","",VLOOKUP(U22,'ACTIVITY & DISCIPLINE CODE'!$F$3:$I$1863,4,)) | AB22: =IF(AC22=0,"","_") | AD22: =IF(AE22="","","-") | AE22: =IF(AC22="","",VLOOKUP(AC22,'PROJECT STAGE'!$A$2:$C$100,2,)) | AF22: =IF(AG22="","","_") | AG22: =IF(AC22="","",VLOOKUP(AC22,'PROJECT STAGE'!$A$2:$C$100,3,)) | AH22: =IF(AI22="","","_") | AJ22: =IF(AK22="","","_") | AL22: =IF(AM22="","","_") | AN22: =IF(AO22=0,"","_") | AP22: =IF(AQ22="","","-") | AS22: =IF(A22="RBDTD-LT", "RBDTDLT","Not LT section") -> Not LT section | AT22: =IF(AU22=0,"",".") -> . | AU22: =IF(O22=0,"No input data",INDEX('DOCUMENT TYPE'!D:D,MATCH(Filename!O22,'DOCUMENT TYPE'!A:A,0))) -> No input data | AV22: =IF(AW22=0,"","-") -> - | AW22: =IF(AC22="PD","PP",IF(AC22="MD","TP",IF(AC22="DTD","DP","Check PROJECT STAGE"))) -> Check PROJECT STAGE | AX22: =IF(AY22>"0","-","") | AY22: =IF(AO22=0,"",TEXT(AO22,"00")) | AZ22: =IF(BA22>"0","-","") | BA22: =IF(AQ22=0,"",TEXT(AQ22,"00")) | BC22: =IF(Y22="","Missing input data",IF(Y22="-","Missing input data",_xlfn.TEXTJOIN(,,A22:E22,AF22,AG22,P22,Y22,R22:S22,AP22,(TEXT(AQ22,"00")),AJ22,(TEXT(AK22,"v00")),AL22:AM22))) -> Missing input data | BD22: =IF(Y22="","Missing input data",IF(Y22="-","Missing input data",LEN(BC22))) -> Missing input data | BF22: =IF(AA22="","Missing input data",IF(AA22="-","Missing input data",_xlfn.TEXTJOIN(,,A22:E22,AF22,AG22,P22,AA22,R22:S22,AP22,(TEXT(AQ22,"00")),AJ22,(TEXT(AK22,"v00")),AL22:AM22))) -> Missing input data | BG22: =IF(AA22="","Missing input data",IF(AA22="-","Missing input data",LEN(BF22))) -> Missing input data | BI22: =IF(W22="","Missing input data",IF(W22="-","Missing input data",_xlfn.TEXTJOIN(,,A22:N22,Q22,T22,W22:Y22,AB22,AE22,AH22,(TEXT(AI22,"000000")),AL22:AM22))) -> Missing input data | BJ22: =IF(W22="","Missing input data",IF(W22="-","Missing input data",LEN(BI22))) -> Missing input data | BL22: =IF(W22="","Missing input data",IF(W22="-","Missing input data",_xlfn.TEXTJOIN(,,A22:N22,Q22,T22,W22:Y22,AB22,AE22,AH22,(TEXT(AI22,"000000")),AJ22,(TEXT(AK22,"000"))))) -> Missing input data | BM22: =IF(W22="","Missing input data",IF(W22="-","Missing input data",LEN(BL22))) -> Missing input data
... B1000: =IF(C1000=0,"","-") | D1000: =IF(E1000=0,"","-") | F1000: =IF(G1000=0,"","_") | H1000: =IF(I1000=0,"","_") | J1000: =IF(K1000=0,"","-") | L1000: =IF(M1000=0,"","_") | N1000: =IF(O1000=0,"","_") | P1000: =IF(Q1000="","","-") | Q1000: =IF(O1000="","",VLOOKUP(O1000,'DOCUMENT TYPE'!$A$2:$D$805,2,)) | R1000: =IF(S1000="","","-") | S1000: =IF(O1000="","",VLOOKUP(O1000,'DOCUMENT TYPE'!$A$2:$D$805,3,)) | T1000: =IF(U1000=0,"","_") | V1000: =IF(W1000="","","-") | W1000: =IF(U1000="","",VLOOKUP(U1000,'ACTIVITY & DISCIPLINE CODE'!$F$3:$I$1863,2,)) | X1000: =IF(Y1000="","","-") | Y1000: =IF(U1000="","",VLOOKUP(U1000,'ACTIVITY & DISCIPLINE CODE'!$F$3:$I$1863,3,)) | Z1000: =IF(AA1000="","","_") | AA1000: =IF(U1000="","",VLOOKUP(U1000,'ACTIVITY & DISCIPLINE CODE'!$F$3:$I$1863,4,)) | AB1000: =IF(AC1000=0,"","_") | AD1000: =IF(AE1000="","","-") | AE1000: =IF(AC1000="","",VLOOKUP(AC1000,'PROJECT STAGE'!$A$2:$C$100,2,)) | AF1000: =IF(AG1000="","","_") | AG1000: =IF(AC1000="","",VLOOKUP(AC1000,'PROJECT STAGE'!$A$2:$C$100,3,)) | AH1000: =IF(AI1000="","","_") | AJ1000: =IF(AK1000="","","_") | AL1000: =IF(AM1000="","","_") | AN1000: =IF(AO1000=0,"","_") | AP1000: =IF(AQ1000="","","-") | AS1000: =IF(A1000="RBDTD-LT", "RBDTDLT","Not LT section") -> Not LT section | AT1000: =IF(AU1000=0,"",".") -> . | AU1000: =IF(O1000=0,"No input data",INDEX('DOCUMENT TYPE'!D:D,MATCH(Filename!O1000,'DOCUMENT TYPE'!A:A,0))) -> No input data | AV1000: =IF(AW1000=0,"","-") -> - | AW1000: =IF(AC1000="PD","PP",IF(AC1000="MD","TP",IF(AC1000="DTD","DP","Check PROJECT STAGE"))) -> Check PROJECT STAGE | AX1000: =IF(AY1000>"0","-","") | AY1000: =IF(AO1000=0,"",TEXT(AO1000,"00")) | AZ1000: =IF(BA1000>"0","-","") | BA1000: =IF(AQ1000=0,"",TEXT(AQ1000,"00")) | BC1000: =IF(Y1000="","Missing input data",IF(Y1000="-","Missing input data",_xlfn.TEXTJOIN(,,A1000:E1000,AF1000,AG1000,P1000,Y1000,R1000:S1000,AP1000,(TEXT(AQ1000,"00")),AJ1000,(TEXT(AK1000,"v00")),AL1000:AM1000))) -> Missing input data | BD1000: =IF(Y1000="","Missing input data",IF(Y1000="-","Missing input data",LEN(BC1000))) -> Missing input data | BF1000: =IF(AA1000="","Missing input data",IF(AA1000="-","Missing input data",_xlfn.TEXTJOIN(,,A1000:E1000,AF1000,AG1000,P1000,AA1000,R1000:S1000,AP1000,(TEXT(AQ1000,"00")),AJ1000,(TEXT(AK1000,"v00")),AL1000:AM1000))) -> Missing input data | BG1000: =IF(AA1000="","Missing input data",IF(AA1000="-","Missing input data",LEN(BF1000))) -> Missing input data | BI1000: =IF(W1000="","Missing input data",IF(W1000="-","Missing input data",_xlfn.TEXTJOIN(,,A1000:N1000,Q1000,T1000,W1000:Y1000,AB1000,AE1000,AH1000,(TEXT(AI1000,"000000")),AL1000:AM1000))) -> Missing input data | BJ1000: =IF(W1000="","Missing input data",IF(W1000="-","Missing input data",LEN(BI1000))) -> Missing input data | BL1000: =IF(W1000="","Missing input data",IF(W1000="-","Missing input data",_xlfn.TEXTJOIN(,,A1000:N1000,Q1000,T1000,W1000:Y1000,AB1000,AE1000,AH1000,(TEXT(AI1000,"000000")),AJ1000,(TEXT(AK1000,"000"))))) -> Missing input data | BM1000: =IF(W1000="","Missing input data",IF(W1000="-","Missing input data",LEN(BL1000))) -> Missing input data
D1001: =IF(E1001=0,"","-")
D1002: =IF(E1002=0,"","-")
D1003: =IF(E1003=0,"","-")
D1004: =IF(E1004=0,"","-")
D1005: =IF(E1005=0,"","-")
D1006: =IF(E1006=0,"","-")
D1007: =IF(E1007=0,"","-")
D1008: =IF(E1008=0,"","-")
D1009: =IF(E1009=0,"","-")
D1010: =IF(E1010=0,"","-")
D1011: =IF(E1011=0,"","-")
D1012: =IF(E1012=0,"","-")
... D1292: =IF(E1292=0,"","-")

Sheet PROJECT ID
A1: CODE | B1: DESCTIPTION
A2: RBDTD-EE | B2: Design section in Estonia

Sheet SECTION ID
A1: CODE | B1: DESCTIPTION
A2: ZZ | B2: No section
A3: DS1 | B3: Design section No.1
A4: SS | B4: Signaling subsystem section
A5: ES | B5: Energy subsystem section
B6: To be continued if required. Any code and description shall be agreed with the Client.

Sheet SUB-SECTION ID
A1: CODE | B1: DESCTIPTION
A2: ZZ | B2: No sub-section
A3: DPS1 | B3: Design Priority section No.1
A4: DPS2 | B4: Design Priority section No.2
A5: DPS3 | B5: Design Priority section No.3
A6: DPS4 | B6: Design Priority section No.4
A7: DPS5 | B7: Design Priority section No.5
B8: To be continued if required. Any code and description shall be agreed with the Client.

Sheet ORIGINATOR_SUPPLIER
A1: CODE | B1: NAME
A2: AFR | B2: Afry
A3: ALL | B3: Allspark
A4: ARD | B4: Ardanuy
A5: ATE | B5: Atemo OÜ
A6: ENS | B6: Enersense AS
A7: GRK | B7: GRK infra AS
A8: HPT | B8: Hepta Group Energy OÜ
A9: INF | B9: INF INFRA OÜ
A10: KKP | B10: Keskkonnaprojekt AS
A11: KMG | B11: KMG Inseneriehituse AS
A12: KPR | B12: K-Projekt (ET)
... A31: YIT | B31: AS YIT Eesti
B32: To be continued if required. Any code and description shall be agreed with the Client.

Sheet VOLUME_SYSTEM
A1: IN FORCE CODE | B1: VE CODE | C1: MD CODE | D1: DTD | E1: RBR-Functional classification | F1: NAME / TYPE | G1: COUNTRY | H1: PD code | I1: PD Section | J1: Municipality | K1: WGS84 Long X Coordinate | L1: WGS84 Lat Y Coordinate | M1: Characteristics of Crossing / Road / Utility | N1: Affected party | O1: PD_km | P1: Type of data | Q1: Date | R1: Order | S1: Order with roads | T1: Archive | U1: New
A2: 000000 | B2: 000000 | C2: 000000 | F2: No Volume applicable | R2: 1 | S2: 1
A3: ZZZZZZ | B3: ZZZZZZ | C3: ZZZZZZ | F3: Multiple volumes applicable | R3: 2 | S3: 2
A4: OS1600 | B4: OS1600 | C4: OS1600 | E4: PP-FA-PTLO-00 | F4: Local Passenger Stop or Station | G4: EE | I4: 1 | K4: 59.179078 | L4: 24.770408 | M4: Kohila Local station | O4: 3+800 | P4: Facility/Station | R4: 3 | S4: 3
A5: OS160101 | C5: OS1601 | D5: OS160101 | E5: AR-BD-PLAT-TR | F5: Platform-Train Stn | G5: EE | I5: 1 | K5: 59.179182 | L5: 24.770511 | M5: Kohila Station Platform / Canopies and other structures on the platforms | O5: 3+800 | P5: Other | R5: 4 | S5: 4
A6: OS160102 | C6: OS1602 | D6: OS160102 | E6: AR-BD-PLAT-TR | F6: Platform-Train Stn | G6: EE | I6: 1 | K6: 59.179102 | L6: 24.770335 | M6: Kohila Station platform right | O6: 3+800 | P6: Other | R6: 5 | S6: 5
A7: OS160104 | D7: OS160104 | E7: CV-RO-ROAD-CA | F7: Road-Corridor Access | G7: EE | I7: 1 | K7: 59.180025 | L7: 24.769897 | M7: Evacuation path platform 1 | O7: 3+800 | P7: Road | R7: 6 | S7: 6 | T7: x
A8: OR160104 | D8: OR160104 | E8: CV-RO-ROAD-CA | F8: Road-Corridor Access | G8: EE | I8: 1 | K8: 59.180025 | L8: 24.769897 | M8: Evacuation path platform 1 | O8: 3+800 | P8: Road | Q8: 20.10.2025 | R8: 7 | S8: 7 | U8: new
A9: OS160105 | D9: OS160105 | E9: CV-RO-ROAD-CA | F9: Road-Corridor Access | G9: EE | I9: 1 | K9: 59.178213 | L9: 24.771468 | M9: Evacuation path platform 1 | O9: 3+800 | P9: Road | R9: 8 | S9: 8 | T9: x
A10: OR160105 | D10: OR160105 | E10: CV-RO-ROAD-CA | F10: Road-Corridor Access | G10: EE | I10: 1 | K10: 59.178213 | L10: 24.771468 | M10: Evacuation path platform 1 | O10: 3+800 | P10: Road | Q10: 20.10.2025 | R10: 9 | S10: 9 | U10: new
A11: OS160106 | D11: OS160106 | E11: CV-RO-ROAD-CA | F11: Road-Corridor Access | G11: EE | I11: 1 | K11: 59.179941 | L11: 24.769465 | M11: Evacuation path platform 2 | O11: 3+800 | P11: Road | R11: 10 | S11: 10 | T11: x
A12: OR160106 | D12: OR160106 | E12: CV-RO-ROAD-CA | F12: Road-Corridor Access | G12: EE | I12: 1 | K12: 59.179941 | L12: 24.769465 | M12: Evacuation path platform 2 | O12: 3+800 | P12: Road | Q12: 20.10.2025 | R12: 11 | S12: 11 | U12: new
A13: OS160107 | D13: OS160107 | E13: CV-RO-ROAD-CA | F13: Road-Corridor Access | G13: EE | I13: 1 | K13: 59.178128 | L13: 24.770966 | M13: Evacuation path platform 2 | O13: 3+800 | P13: Road | R13: 12 | S13: 12 | T13: x
A14: OR160107 | D14: OR160107 | E14: CV-RO-ROAD-CA | F14: Road-Corridor Access | G14: EE | I14: 1 | K14: 59.178128 | L14: 24.770966 | M14: Evacuation path platform 2 | O14: 3+800 | P14: Road | Q14: 20.10.2025 | R14: 13 | S14: 13 | U14: new
A15: OS160121 | C15: OS160121 | E15: CV-MS-INTF-EL | F15: Electricity Interface | G15: EE | I15: 1 | K15: 59.179077 | L15: 24.770409 | M15: Kohila Station Platform / Electricity, external( High-voltage) | O15: 3+800 | P15: Interface | R15: 14 | S15: 14
A16: OS160122 | C16: OS160122 | E16: CV-MS-INTF-00 | F16: Unidentified interface | G16: EE | I16: 1 | K16: 59.179077 | L16: 24.770409 | M16: Kohila Station Platform / Water and sewerage, external | O16: 3+800 | P16: Interface | R16: 15 | S16: 15
A17: OS160123 | D17: OS160123 | E17: CV-MS-INTF-EL | F17: Electricity Interface | G17: EE | I17: 1 | K17: 59.179224 | L17: 24.770614 | M17: Kohila Station Low-voltage( platforms and overpass)(low voltage) | O17: 3+800 | P17: Interface | R17: 16 | S17: 16
A18: OS160301 | C18: OS1603 | D18: OS160301 | E18: AR-BD-BLDG-SN | F18: Station Building | G18: EE | I18: 1 | K18: 59.179077 | L18: 24.770409 | M18: Kohila Local Station / Station Building (including utilities, art) excl. structural engineering design below platforms floor surface. Excl. canopies and other structures on the platforms | O18: 3+800 | P18: Other | R18: 17 | S18: 17 | T18: x
A19: OS1604 | C19: OS1604 | E19: AR-BD-BLDG-SN | F19: Station Building | G19: EE | I19: 1 | K19: 59.179077 | L19: 24.770409 | M19: 426 | O19: 3+800 | P19: Other | R19: 18 | S19: 18 | T19: x
A20: OS160401 | C20: OS160401 | E20: AR-BD-BLDG-SN | F20: Station Building | G20: EE | I20: 1 | K20: 59.179077 | L20: 24.770408 | M20: Kohila Local Station / Bus stop. Bike parking. Debris station. | O20: 3+800 | P20: Other | R20: 19 | S20: 19 | T20: x
A21: OS160402 | C21: OS160402 | E21: CV-BR-UPSS-RD | F21: Underpass-Road | G21: EE | I21: 1 | K21: 59.179077 | L21: 24.770409 | M21: Kohila Local Station / Structural Engineering design below platforms floor surface | O21: 3+800 | P21: Underpass | R21: 20 | S21: 20 | T21: x
A22: OS160403 | C22: OS160403 | E22: CV-BR-OPSS-PD | F22: Overpass-Pedestrian | G22: EE | I22: 1 | K22: 59.179077 | L22: 24.770409 | M22: Overpass Kohila Pedestrian crossing. Stairs from platform floor | O22: 3+800 | P22: Overpass | R22: 21 | S22: 21
A23: OS160411 | C23: OS160411 | E23: AR-UD-LSCP-00 | F23: Landscaping | G23: EE | I23: 1 | K23: 59.179077 | L23: 24.770409 | M23: Kohila Local Station infrastucture / Urban design | O23: 3+800 | P23: Other | R23: 22 | S23: 22 | T23: x
A24: OS160412 | C24: OS160412 | E24: CV-RO-ROAD-00 | F24: Road-Not specified | G24: EE | I24: 1 | K24: 59.179077 | L24: 24.770409 | M24: Kohila Local Station infrastucture / Outdoor area+ parking | O24: 3+800 | P24: Road | R24: 23 | S24: 23 | T24: x
A25: OS160413 | D25: OS160413 | E25: CV-RO-ROAD-SQ | F25: Square | G25: EE | I25: 1 | K25: 59.178787 | L25: 24.769951 | M25: Kohila outdoor area subsoil work | O25: 3+850 | P25: Road | Q25: 20.10.2025 | R25: 24 | S25: 24 | U25: new
A26: OS160421 | C26: OS160421 | E26: CV-MS-INTF-EL | F26: Electricity Interface | G26: EE | I26: 1 | K26: 59.179077 | L26: 24.770409 | M26: Kohila Local Station infrastucture / Electricity, external | O26: 3+800 | P26: Interface | R26: 25 | S26: 25 | T26: x
A27: OS160422 | C27: OS160422 | E27: CV-MS-INTF-EL | F27: Electricity Interface | G27: EE | I27: 1 | K27: 59.179077 | L27: 24.770409 | M27: Overpass Kohila. Pedestrian crossing / Electricity, external | O27: 3+800 | P27: Interface | R27: 26 | S27: 26 | T27: x
A28: OS160423 | C28: OS160423 | E28: CV-MS-INTF-00 | F28: Unidentified interface | G28: EE | I28: 1 | K28: 59.179077 | L28: 24.770409 | M28: Kohila Local Station infrastucture / Water and sewerage, external | O28: 3+800 | P28: Interface | R28: 27 | S28: 27 | T28: x
A29: OS160424 | C29: OS160424 | E29: CV-MS-INTF-00 | F29: Unidentified interface | G29: EE | I29: 1 | K29: 59.179077 | L29: 24.770409 | M29: Overpass Kohila. Pedestrian crossing / Water and sewerage, external | O29: 3+800 | P29: Interface | R29: 28 | S29: 28 | T29: x
A30: OS160425 | D30: OS160425 | E30: CV-MS-INTF-EL | F30: Electricity Interface | G30: EE | I30: 1 | K30: 59.178964 | L30: 24.769241 | M30: Kohila station Street lighting+electricity( Outdoor) | O30: 3+800 | P30: Interface | R30: 29 | S30: 29 | T30: x
A31: OS160426 | D31: OS160426 | E31: CV-MS-INTF-RW | F31: Temorary rainwater drainage pipeline | G31: EE | I31: 1 | K31: 59.178803 | L31: 24.769242 | M31: Kohila station temporary drainage of rainwater through an outdoor | O31: 3+800 | P31: Other | Q31: 13.05.2025 | R31: 30 | S31: 30
A32: RW1000 | C32: RW1000 | E32: TR-TR-TRAK-ML | F32: Track-Mainline | G32: EE | H32: ZZZZ | I32: 1 | K32: 59.173504 | L32: 24.774533 | M32: Railway Kohila | O32: 0+000 - 9+416 | P32: Track | R32: 31 | S32: 31
A33: RW100100 | C33: RW1000 | D33: RW100100 | E33: TR-TR-SUBS-00 | F33: Substructure | G33: EE | H33: ZZZZ | I33: 1 | K33: 59.171976 | L33: 24.783121 | M33: Railway Kohila substructure/Railway main line drainage | O33: 0+000 - 9+416 | P33: Substructure | R33: 32 | S33: 32
A34: RW100200 | C34: RW1000 | D34: RW100200 | E34: TR-TR-SUPS-00 | F34: Superstructure | G34: EE | H34: ZZZZ | I34: 1 | K34: 59.173033 | L34: 24.782909 | M34: Railway Kohila | O34: 0+000 - 9+416 | P34: Superstructure | R34: 33 | S34: 33
A35: RW100300 | C35: RW1000 | D35: RW100300 | E35: CV-MS-INTF-SG | F35: Signalling Interface | G35: EE | H35: ZZZZ | I35: 1 | K35: 59.172508 | L35: 24.782903 | M35: RW1300 CCS Cable channel | O35: 0+000 - 9+416 | P35: Interface | R35: 34 | S35: 34
A36: RW100600 | C36: RW1000 | D36: RW100600 | E36: CV-FN-FENC-00 | F36: Fence | G36: EE | H36: ZZZZ | I36: 1 | K36: 59.17234727 | L36: 24.776375137 | M36: Railway Kohila fences | O36: 0+000 - 9+416 | P36: Fence | R36: 35 | S36: 35
A37: RW100800 | C37: RW1000 | D37: RW100800 | E37: AR-UD-LSCP-00 | F37: Landscaping | G37: EE | I37: 1 | K37: 59.17296 | L37: 24.775718 | M37: Railway landscaping | O37: 0+000 - 9+416 | P37: Other | Q37: 08.05.2025 | R37: 36 | S37: 36
A38: OR1000 | D38: OR1000 | E38: CV-RO-ROAD-CM | F38: Road-Maintenance | G38: EE | H38: ZZZZ | I38: 1 | K38: 59.174 | L38: 24.783 | M38: Railway maintenance roads | O38: 0+000 - 9+416 | P38: Road | R38: 37 | S38: 37
A39: BR1210 | C39: BR1210 | E39: CV-BR-OPSS-RD | F39: Overpass-Road | G39: EE | H39: 07-BR10 | I39: 1 | K39: 59.200531 | L39: 24.752122 | M39: Tagadi road nr 3170198 | O39: 1+192 | P39: Overpass | R39: 38 | S39: 38
A40: OR1208 | C40: OR1208 | E40: CV-RO-ROAD-LO | F40: Road-Local | G40: EE | I40: 1 | K40: 59.199467 | L40: 24.752553 | M40: Kurtna road nr 3170009 | N40: BR1210 | O40: 1+192 | P40: Road | R40: 39 | S40: 39
A41: CU120810 | D41: CU120810 | E41: CV-DR-CULV-RD | F41: Culvert-Road | G41: EE | I41: 1 | K41: 59.200442 | L41: 24.751752 | M41: Culvert | N41: OR1208 | O41: 1+193 | P41: Culvert | R41: 40 | S41: 40
A42: OR120802 | D42: OR120802 | E42: CV-RO-ROAD-CA | F42: Road-Corridor Access | G42: EE | I42: 1 | K42: 59.196086 | L42: 24.7544 | M42: Road | N42: BR1210 | O42: 1+698 | P42: Road | R42: 41 | S42: 41
A43: OR120804 | D43: OR120804 | E43: CV-RO-ROAD-CM | F43: Road-Maintenance | G43: EE | I43: 1 | K43: 59.203972 | L43: 24.748691 | M43: Maintenance road | N43: RW1000 | O43: 0+762 | P43: Road | R43: 42 | S43: 42
A44: OR120806 | D44: OR120806 | E44: CV-RO-ROAD-CM | F44: Road-Maintenance | G44: EE | I44: 1 | K44: 59.195318 | L44: 24.755865 | M44: Maintenance road | N44: RW1000 | O44: 1+810 | P44: Road | R44: 43 | S44: 43
A45: OR120808 | D45: OR120808 | E45: CV-RO-ROAD-CA | F45: Road-Corridor Access | G45: EE | I45: 1 | K45: 59.190315 | L45: 24.757133 | M45: Road | N45: BR1610 | O45: 2+349 | P45: Road | R45: 44 | S45: 44
A46: OR120810 | D46: OR120810 | E46: CV-RO-ROAD-GP | F46: Green path | G46: EE | I46: 1 | K46: 59.20847 | L46: 24.744817 | M46: Green path | N46: RW1000 | O46: 0+000-0+465, Right | P46: Road | Q46: 22.05.2025 | R46: 45 | S46: 45
A47: OR1210 | C47: OR1210 | E47: CV-RO-ROAD-LO | F47: Road-Local | G47: EE | I47: 1 | K47: 59.200531 | L47: 24.752122 | M47: Tagadi road nr 3170198 | N47: BR1210 | O47: 1+192 | P47: Road | R47: 46 | S47: 46
A48: OR121001 | D48: OR121001 | E48: CV-RO-ROAD-CA | F48: Road-Corridor Access | G48: EE | I48: 1 | K48: 59.20125 | L48: 24.752602 | M48: Road | N48: BR1210/RW1000 | O48: 1+130 | P48: Road | R48: 47 | S48: 47
A49: OR121003 | D49: OR121003 | E49: CV-RO-ROAD-CA | F49: Road-Corridor Access | G49: EE | I49: 1 | K49: 59.20149 | L49: 24.755151 | M49: Road | N49: BR1210/RW1000 | O49: 1+163 | P49: Road | R49: 48 | S49: 48
A50: OR121005 | D50: OR121005 | E50: CV-RO-ROAD-CA | F50: Road-Corridor Access | G50: EE | I50: 1 | K50: 59.201014 | L50: 24.755411 | M50: Road | N50: BR1210/RW1000 | O50: 1+218 | P50: Road | R50: 49 | S50: 49
A51: OR121007 | D51: OR121007 | E51: CV-RO-ROAD-CM | F51: Road-Maintenance | G51: EE | I51: 1 | K51: 59.203353 | L51: 24.75011 | M51: Maintenance road | N51: RW1000 | O51: 0+858 | P51: Road | R51: 50 | S51: 50
A52: OR121009 | D52: OR121009 | E52: CV-RO-ROAD-CA | F52: Road-Corridor Access | G52: EE | I52: 1 | K52: 59.194428 | L52: 24.758185 | M52: Access road | O52: 1+954 | P52: Road | R52: 51 | S52: 51
A53: OR121011 | D53: OR121011 | E53: CV-RO-ROAD-CA | F53: Road-Corridor Access | G53: EE | I53: 1 | K53: 59.193229 | L53: 24.761992 | M53: Road | O53: 2+163 | P53: Road | R53: 52 | S53: 52
A54: OR121013 | D54: OR121013 | E54: CV-RO-ROAD-CA | F54: Road-Corridor Access | G54: EE | I54: 1 | K54: 59.196705 | L54: 24.756215 | M54: Road | N54: BR1210/RW1000 | O54: 1+676 | P54: Road | R54: 53 | S54: 53
A55: OR121015 | D55: OR121015 | E55: CV-RO-ROAD-CA | F55: Road-Corridor Access | G55: EE | I55: 1 | K55: 59.201704 | L55: 24.752587 | M55: Access road | N55: RW1000 | O55: 1+083 | P55: Road | R55: 54 | S55: 54
A56: ME1121 | D56: ME1121 | E56: CV-DR-LAME-00 | F56: Land Melioration | G56: EE | I56: 1 | K56: 59.198307 | L56: 24.753199 | M56: Land Melioration Tagadi | O56: 1+075-1+750 | P56: Other | R56: 55 | S56: 55 | T56: x
A57: CU120802 | D57: CU120802 | E57: CV-DR-CULV-00 | F57: Culvert-Drainage | G57: EE | I57: 1 | K57: 59.196537 | L57: 24.754738 | M57: Culvert | N57: ME1121 | O57: 1+659 | P57: Culvert | R57: 56 | S57: 56 | T57: x
A58: CU120804 | D58: CU120804 | E58: CV-DR-CULV-00 | F58: Culvert-Drainage | G58: EE | I58: 1 | K58: 59.196078 | L58: 24.754234 | M58: Culvert | N58: ME1121 | O58: 1+395 | P58: Culvert | R58: 57 | S58: 57 | T58: x
A59: CU120806 | D59: CU120806 | E59: CV-DR-CULV-00 | F59: Culvert-Drainage | G59: EE | I59: 1 | K59: 59.195713 | L59: 24.754828 | M59: Culvert | N59: ME1121 | O59: 1+746 | P59: Culvert | R59: 58 | S59: 58 | T59: x
A60: CU120808 | D60: CU120808 | E60: CV-DR-CULV-00 | F60: Culvert-Drainage | G60: EE | I60: 1 | K60: 59.195889 | L60: 24.754664 | M60: Culvert | N60: ME1121 | O60: 1+724 | P60: Culvert | R60: 59 | S60: 59 | T60: x
A61: CU121002 | D61: CU121002 | E61: CV-DR-CULV-00 | F61: Culvert-Drainage | G61: EE | I61: 1 | K61: 59.201019 | L61: 24.749249 | M61: Culvert | N61: ME1121 | O61: 1+076 | P61: Culvert | R61: 60 | S61: 60 | T61: x
A62: CU121009 | D62: CU121009 | E62: CV-DR-CULV-00 | F62: Culvert-Drainage | G62: EE | I62: 1 | K62: 59.201418 | L62: 24.752813 | M62: Culvert | N62: ME1121 | O62: 1+117 | P62: Culvert | R62: 61 | S62: 61 | T62: x
A63: CU121015 | D63: CU121015 | E63: CV-DR-CULV-00 | F63: Culvert-Drainage | G63: EE | I63: 1 | K63: 59.200959 | L63: 24.754037 | M63: Culvert | N63: ME1121 | O63: 1+192 | P63: Culvert | R63: 62 | S63: 62 | T63: x
A64: CU121017 | D64: CU121017 | E64: CV-DR-CULV-00 | F64: Culvert-Drainage | G64: EE | I64: 1 | K64: 59.200507 | L64: 24.754589 | M64: Culvert | N64: ME1121 | O64: 1+251 | P64: Culvert | R64: 63 | S64: 63 | T64: x
A65: CU121019 | D65: CU121019 | E65: CV-DR-CULV-00 | F65: Culvert-Drainage | G65: EE | I65: 1 | K65: 59.201468 | L65: 24.753076 | M65: Culvert | N65: ME1121 | O65: 1+118 | P65: Culvert | R65: 64 | S65: 64 | T65: x
A66: BR1215 | C66: BR1215 | E66: CV-BR-OPSS-RD | F66: Overpass-Road | G66: EE | H66: 07-BR09 | I66: 1 | K66: 59.178516 | L66: 24.773136 | M66: Urge road nr 3170011 | O66: 3+944 | P66: Overpass | R66: 65 | S66: 65
A67: OR1215 | C67: OR1215 | E67: CV-RO-ROAD-LO | F67: Road-Local | G67: EE | I67: 1 | K67: 59.178159 | L67: 24.771923 | M67: Urge road nr 3170011 | O67: 3+944 | P67: Road | R67: 66 | S67: 66
A68: OR121501 | D68: OR121501 | E68: CV-RO-ROAD-CM | F68: Road-Maintenance | G68: EE | I68: 1 | K68: 59.186723 | L68: 24.76445 | M68: Maintenance road | O68: 2+763 | P68: Road | R68: 67 | S68: 67
A69: OR121502 | D69: OR121502 | E69: CV-RO-ROAD-CM | F69: Road-Maintenance | G69: EE | I69: 1 | K69: 59.186536 | L69: 24.763615 | M69: Maintenance road | O69: 2+761 | P69: Road | R69: 68 | S69: 68
A70: OR121503 | D70: OR121503 | E70: CV-RO-ROAD-CA | F70: Road-Corridor Access | G70: EE | I70: 1 | K70: 59.183808 | L70: 24.767003 | M70: Access road | N70: BR1215 | O70: 3+235 | P70: Road | R70: 69 | S70: 69
A71: OR121504 | D71: OR121504 | E71: CV-RO-ROAD-CM | F71: Road-Maintenance | G71: EE | I71: 1 | K71: 59.183991 | L71: 24.765828 | M71: Maintenance road | N71: BR1215 | O71: 3+200 | P71: Road | R71: 70 | S71: 70
A72: OR121505 | C72: OR121505 | E72: CV-RO-ROAD-CM | F72: Road-Maintenance | G72: EE | I72: 1 | K72: 59.177215 | L72: 24.772831 | M72: Maintenance road | O72: 4+046 | P72: Road | R72: 71 | S72: 71
A73: OR121506 | C73: OR121506 | E73: CV-RO-ROAD-LO | F73: Road-Local | G73: EE | I73: 1 | K73: 59.177293 | L73: 24.768613 | M73: Local road | O73: 3+941 | P73: Road | R73: 72 | S73: 72
A74: OR121507 | D74: OR121507 | E74: CV-RO-ROAD-CA | F74: Road-Corridor Access | G74: EE | I74: 1 | K74: 59.183066 | L74: 24.767777 | M74: Access road | O74: 3+333 | P74: Road | R74: 73 | S74: 73
A75: OR121508 | C75: OR121508 | E75: CV-RO-ROAD-LO | F75: Road-Local | G75: EE | I75: 1 | K75: 59.177197 | L75: 24.771353 | M75: Local road | O75: 4+014 | P75: Road | R75: 74 | S75: 74
A76: OR121509 | C76: OR121509 | E76: CV-RO-ROAD-CA | F76: Road-Corridor Access | G76: EE | I76: 1 | K76: 59.179518 | L76: 24.774346 | M76: Access road | O76: 3+984 | P76: Road | R76: 75 | S76: 75
A77: OR121510 | C77: OR121510 | E77: CV-RO-ROAD-CA | F77: Road-Corridor Access | G77: EE | I77: 1 | K77: 59.176659 | L77: 24.766067 | M77: Tööstuse street | O77: 3+714 | P77: Road | R77: 76 | S77: 76
A78: OR121511 | C78: OR121511 | E78: CV-RO-ROAD-LO | F78: Road-Local | G78: EE | I78: 1 | K78: 59.1805 | L78: 24.777592 | M78: Local road | O78: 3+820 | P78: Road | R78: 77 | S78: 77
A79: OR121512 | C79: OR121512 | E79: CV-RO-ROAD-CA | F79: Road-Corridor Access | G79: EE | I79: 1 | K79: 59.175981 | L79: 24.768566 | M79: Access road | O79: 3+919 | P79: Road | R79: 78 | S79: 78
A80: OR121513 | C80: OR121513 | E80: CV-RO-ROAD-CA | F80: Road-Corridor Access | G80: EE | I80: 1 | K80: 59.180737 | L80: 24.782295 | M80: Access road | O80: 3+903 | P80: Road | R80: 79 | S80: 79
A81: OR121514 | C81: OR121514 | E81: CV-RO-ROAD-CA | F81: Road-Corridor Access | G81: EE | I81: 1 | K81: 59.174199 | L81: 24.768406 | M81: Access road | O81: 4+252 | P81: Road | R81: 80 | S81: 80
A82: OR121515 | C82: OR121515 | E82: CV-RO-ROAD-LO | F82: Road-Local | G82: EE | I82: 1 | K82: 59.180176 | L82: 24.778051 | M82: Local road | O82: 3+863 | P82: Road | R82: 81 | S82: 81
A83: OR121516 | C83: OR121516 | E83: CV-RO-ROAD-LO | F83: Road-Local | G83: EE | I83: 1 | K83: 59.17517 | L83: 24.767593 | M83: Road | O83: 3+919 | P83: Road | R83: 82 | S83: 82
A84: OR121517 | C84: OR121517 | E84: CV-RO-ROAD-CA | F84: Road-Corridor Access | G84: EE | I84: 1 | K84: 59.179551 | L84: 24.784312 | M84: Road | O84: 4+070 | P84: Road | R84: 83 | S84: 83
A85: OR121518 | C85: OR121518 | E85: CV-RO-ROAD-CA | F85: Road-Corridor Access | G85: EE | I85: 1 | K85: 59.17288 | L85: 24.767101 | M85: Kiriku off-road | O85: 4+357 | P85: Road | R85: 84 | S85: 84
A86: OR121519 | C86: OR121519 | E86: CV-RO-ROAD-CA | F86: Road-Corridor Access | G86: EE | I86: 1 | K86: 59.179482 | L86: 24.783829 | M86: 202 off-road | O86: 4+066 | P86: Road | R86: 85 | S86: 85
... A100: OR121533 | C100: OR121533 | E100: CV-RO-ROAD-CA | F100: Road-Corridor Access | G100: EE | I100: 1 | K100: 59.179589 | L100: 24.77679 | M100: Urgesauna off-road | O100: 3+894 | P100: Road | R100: 99 | S100: 99
A101: OR121534 | D101: OR121534 | E101: CV-RO-ROAD-CA | F101: Road-Corridor Access | G101: EE | I101: 1 | K101: 59.169352 | L101: 24.76366 | M101: Viljandi road off-road | O101: 4+800 | P101: Road | R101: 100 | S101: 100
A102: OR121535 | C102: OR121535 | E102: CV-RO-ROAD-LO | F102: Road-Local | G102: EE | I102: 1 | K102: 59.179834 | L102: 24.776617 | M102: Urge pedestrian | O102: 3+865 | P102: Road | R102: 101 | S102: 101
A103: OR121536 | D103: OR121536 | E103: CV-RO-ROAD-LO | F103: Road-Local | G103: EE | I103: 1 | K103: 59.173203 | L103: 24.76732 | M103: Urge pedestrian and cycling path | O103: 4+400 | P103: Road | R103: 102 | S103: 102
A104: OR121537 | C104: OR121537 | E104: CV-RO-ROAD-SR | F104: Road-Safety Ramp | G104: EE | I104: 1 | K104: 59.180478 | L104: 24.781635 | M104: Ramp 4 | O104: 3+914 | P104: Road | R104: 103 | S104: 103
A105: OR121538 | D105: OR121538 | E105: CV-RO-ROAD-CA | F105: Road-Corridor Access | G105: EE | I105: 1 | K105: 59.177648 | L105: 24.76901 | M105: Kohila road corridor access | O105: 3+920 | P105: Road | R105: 104 | S105: 104
A106: OR121539 | C106: OR121539 | E106: CV-RO-ROAD-00 | F106: Road-Not specified | G106: EE | I106: 1 | K106: 59.181398 | L106: 24.780844 | M106: Urge oversize | O106: 3+802 | P106: Road | R106: 105 | S106: 105
A107: OR121540 | D107: OR121540 | E107: CV-RO-ROAD-CA | F107: Road-Stn/Stop Access | G107: EE | I107: 1 | K107: 59.178036 | L107: 24.769941 | M107: Kohila station pedestrian and cycling path | O107: 3+895 | P107: Road | R107: 106 | S107: 106
A108: OR121541 | C108: OR121541 | E108: CV-RO-ROAD-CA | F108: Road-Corridor Access | G108: EE | I108: 1 | K108: 59.179046 | L108: 24.773053 | M108: Sõeru off-road | O108: 3+864 | P108: Road | R108: 107 | S108: 107
A109: OR121542 | D109: OR121542 | E109: CV-RO-ROAD-CA | F109: Road-Corridor Access | G109: EE | I109: 1 | K109: 59.180551 | L109: 24.768546 | M109: Access road | N109: OR121504 | O109: 3+585-3+700 | P109: Road | Q109: 02.06.2025 | R109: 108 | S109: 108
A110: OR121543 | D110: OR121543 | E110: CV-RO-ROAD-SA | F110: Road-Corridor Access | G110: EE | I110: 1 | K110: 59.173362 | L110: 24.775583 | M110: Urge-Uuspere corridor access | O110: 4+500 | P110: Road | R110: 109 | S110: 109
A111: OR121545 | D111: OR121545 | E111: CV-RO-ROAD-CA | F111: Road-Corridor Access | G111: EE | I111: 1 | K111: 59.184316 | L111: 24.766661 | M111: Access road | N111: OR121503 | O111: 3+050-3+650 | P111: Road | Q111: 02.06.2025 | R111: 110 | S111: 110
A112: OR121546 | D112: OR121546 | E112: CV-RO-ROAD-CA | F112: Road-Corridor Access | G112: EE | I112: 1 | K112: 59.179601 | L112: 24769445 | M112: Maintenance road off-road | N112: OR121542 | O112: 3+730 | P112: Road | Q112: 19.09.2025 | R112: 111 | S112: 111
A113: OR121547 | D113: OR121547 | E113: CV-RO-ROAD-CA | F113: Road-Corridor Access | G113: EE | I113: 1 | K113: 59.18038 | L113: 24.77001 | M113: Off-Road | O113: 3+660 | P113: Road | Q113: 04.07.2025 | R113: 112 | S113: 112
...

Sheet ZONE
A1: CODE | B1: NAME
A2: ZZ | B2: Whole Zone
A3: 00 | B3: No Zone applicable
A4: SB | B4: Substructure | C4: Not in use
A5: SP | B5: Superstructure | C5: Not in use
A6: EN | B6: Entrances | C6: Not in use
A7: AG | B7: Above Ground | C7: Not in use
B8: To be continued if required. Any code and description shall be agreed with the Client.

Sheet LOCATION
A1: CODE | B1: CHAINAGE KM
A2: 0000 | B2: No location applicable
A3: ZZZZ | B3: Multiple Locations applicable | F3: NOTES:
A4: 0001 | B4: 0 | C4: - | D4: =B5 -> 1000 | F4: Chainage and codes are relative for each desing priority section (DPS) starting from 0+000
A5: 0002 | B5: =B4+1000 -> 1000 | C5: =C4 -> - | D5: =B6 -> 2000 | F5: Absolute chainage shall be introduced after all design sections are finalized in MD stage
A6: 0003 | B6: =B5+1000 -> 2000 | C6: =C5 -> - | D6: =B7 -> 3000
A7: 0004 | B7: =B6+1000 -> 3000 | C7: =C6 -> - | D7: =B8 -> 4000
A8: 0005 | B8: =B7+1000 -> 4000 | C8: =C7 -> - | D8: =B9 -> 5000
A9: 0006 | B9: =B8+1000 -> 5000 | C9: =C8 -> - | D9: =B10 -> 6000
A10: 0007 | B10: =B9+1000 -> 6000 | C10: =C9 -> - | D10: =B11 -> 7000
A11: 0008 | B11: =B10+1000 -> 7000 | C11: =C10 -> - | D11: =B12 -> 8000
A12: 0009 | B12: =B11+1000 -> 8000 | C12: =C11 -> - | D12: =B13 -> 9000
A13: 0010 | B13: =B12+1000 -> 9000 | C13: =C12 -> - | D13: =B14 -> 10000
A14: 0011 | B14: =B13+1000 -> 10000 | C14: =C13 -> - | D14: =B15 -> 11000
A15: 0012 | B15: =B14+1000 -> 11000 | C15: =C14 -> - | D15: =B16 -> 12000
A16: 0013 | B16: =B15+1000 -> 12000 | C16: =C15 -> - | D16: =B17 -> 13000
A17: 0014 | B17: =B16+1000 -> 13000 | C17: =C16 -> - | D17: =B18 -> 14000
... A22: 0019 | B22: =B21+1000 -> 18000 | C22: =C21 -> - | D22: =B23 -> 19000
A23: 0020 | B23: =B22+1000 -> 19000 | C23: =C22 -> -
B24: To be continued if required. Any code and description shall be agreed with the Client.

Sheet ACTIVITY & DISCIPLINE CODE
B1: Folder number | C1: Activity/Discipline code description | D1: Volsys. Code | E1: Folder number | F1: Activity/Discipline description RBR | G1: Activity/Discipline code | J1: Activity/Discipline description EHR | K1: Activity/Discipline description MNT | L1: Rev date | M1: Rev by
G2: RBR | H2: EHR | I2: MNT
A3: Overall (0-OV) | B3: 000 | C3: Model | E3: 01 | F3: landXML | G3: MO | H3: AA | I3: -
E4: 02 | F4: IFC | G4: MO | H4: AA | I4: -
E5: 03 | F5: RVT | G5: MO | H5: AA | I5: -
E6: 04 | F6: NWD | G6: MO | H6: AA | I6: -
E7: ... | F7: ... | G7: MO | H7: AA | I7: -
B8: 001 | C8: Minutes of Meeting | F8: Minutes of Meeting | G8: MOM | H8: AA | I8: -
B9: 002 | C9: General | D9: VOLSYS. CODE | E9: 01 | F9: General | G9: GE | H9: AA | I9: - | J9: Üldosa | K9: Üldosa
E10: 02 | F10: Conditions for Design | G10: GE | H10: AA | I10: PT | J10: Üldosa | K10: projekteerimistingimused
E11: 03 | F11: Terms of Reference | G11: GE | H11: AA | I11: LY | J11: Üldosa | K11: lähteülesanne
E12: 04 | F12: Technical Conditions | G12: GE | H12: AA | I12: TT | J12: Üldosa | K12: tehnilised tingimused
E13: 05 | F13: Initial Data | G13: GE | H13: AA | I13: AD | J13: Üldosa | K13: lähteandmed
E14: 06 | F14: Approvals | G14: GE | H14: AA | I14: KK | J14: Üldosa | K14: kooskõlastused
E15: 07 | F15: Road Safety Audit | G15: GE | H15: AA | I15: LA | J15: Üldosa | K15: liiklusohutuse audit
E16: 08 | F16: Appraisal | G16: GE | H16: AA | I16: EK | J16: Üldosa | K16: ekspertiis
E17: 09 | F17: Agreement with landowners | G17: GE | H17: AA | I17: MO | J17: Üldosa | K17: kokkulepped maaomanikega
E18: 10 | F18: Building Permit | G18: GE | H18: AA | I18: BP | J18: Üldosa | K18: ehitusluba
E19: 11 | F19: Road pavement calculation | G19: GE | H19: AA | I19: KA | J19: Üldosa | K19: kattendiarvutus
E20: 12 | F20: Cost List | G20: GE | H20: AA | I20: CL | J20: Üldosa | K20: kululoend
E21: 13 | F21: Application for Funding | G21: GE | H21: AA | I21: RK | J21: Üldosa | K21: rahastustaotlus
E22: 14 | F22: Land allocation Plan | G22: GE | H22: AA | I22: KY | J22: Üldosa | K22: ümberkruntimiskava (krundijaotuskava)
E23: 15 | F23: General technical solutions | G23: GE | H23: AA | I23: KY | J23: Üldosa
B24: 003 | C24: Investigations, Surveys and Studies | E24: 01 | F24: Geological Investigations | G24: IS | H24: AA | I24: GL | J24: Üldosa | K24: geoloogiline uuring
E25: 02 | F25: Traffic Survey | G25: IS | H25: AA | I25: LU | J25: Üldosa | K25: liiklusuuring
E26: 03 | F26: Flora/Fauna Survey | G26: IS | H26: AA | I26: FU | J26: Üldosa | K26: taimsetiku/loomastiku uuring
E27: 04 | F27: Archeological Survey | G27: IS | H27: AA | I27: AU | J27: Üldosa | K27: arheoloogiline uuring
E28: 05 | F28: Topographic Survey | G28: IS | H28: AA | I28: GD | J28: Üldosa | K28: topogeodeesia
E29: 06 | F29: Noise Survey | G29: IS | H29: AA | I29: MU | J29: Üldosa | K29: müra uuring
E30: 07 | F30: Enviormental screening | G30: IS | H30: AA | I30: KE | J30: Üldosa | K30: keskkonnamõju eelhinnang
E31: 08 | F31: EIA | G31: IS | H31: AA | I31: KH | J31: Üldosa | K31: keskkonnamõju hinnang (KMH või KSH)
E32: 09 | F32: Feasibilty study | G32: IS | H32: AA | I32: TU | J32: Üldosa | K32: teostatavusuuring
E33: 10 | F33: Other | G33: IS | H33: AA | I33: ZZ | J33: Üldosa | K33: muu
B34: 004 | C34: Demolition | E34: 01 | F34: Architecture, Building structures & Service (Demolition) | G34: DE | H34: AA | I34: - | J34: Üldosa
E35: 02 | F35: Civil & Structures (Demolition) | G35: DE | H35: AA | I35: - | J35: Üldosa
E36: 03 | F36: Electrical (Demolition) | G36: DE | H36: AA | I36: - | J36: Üldosa
E37: 04 | F37: Fleet (Demolition) | G37: DE | H37: AA | I37: - | J37: Üldosa
E38: 05 | F38: Property (Demolition) | G38: DE | H38: AA | I38: - | J38: Üldosa
E39: 06 | F39: Signalling & Control Systems (Demolition) | G39: DE | H39: AA | I39: - | J39: Üldosa
E40: 07 | F40: Information Technology & Telecommunications System (Demolition) | G40: DE | H40: AA | I40: - | J40: Üldosa
E41: 08 | F41: Track (Demolition) | G41: DE | H41: AA | I41: - | J41: Üldosa
E42: 09 | F42: Fire safety systems (Demolition) | G42: DE | H42: AA | I42: - | J42: Üldosa
E43: 10 | F43: General demolition design (Demolition) | G43: DE | H43: AA | I43: - | J43: Üldosa
E44: 11 | F44: Other (Demolition) | G44: DE | H44: AA | I44: - | J44: Üldosa
B45: 005 | C45: Construction documentation | E45: 1 | F45: AsBuiltDoc | G45: GE | H45: AA | I45: - | J45: Üldosa | K45: Tööde aktid, Teostusmõõdistused, protokollid, katsetused
E46: 2 | F46: Maintenance Sheet | G46: GE | H46: AA | I46: - | J46: Üldosa | K46: Hooldusjuhend
E47: 3 | F47: Manufacturer Sheet | G47: GE | H47: AA | I47: - | J47: Üldosa | K47: Tooteleht, paigaldusjuhend
E48: 4 | F48: Delivery note | G48: GE | H48: AA | I48: - | J48: Üldosa | K48: Saatelehed
E49: 5 | F49: Site Diary | G49: GE | H49: AA | I49: - | J49: Üldosa | K49: Ehitustööde päevik
E50: 6 | F50: Photos | G50: GE | H50: AA | I50: - | J50: Üldosa | K50: Üldfotod
E51: 7 | F51: Personnel | G51: GE | H51: AA | I51: - | J51: Üldosa | K51: Personal ja nende nõuded
E52: 8 | F52: Quality management | G52: GE | H52: AA | I52: - | J52: Üldosa | K52: Keskkonnakavad, kvaliteedi tagamiseplaanid
E53: 9 | H53: - | I53: -
E54: 10 | H54: - | I54: -
E55: 11 | H55: - | I55: -
A56: Architecture, Building structures & Services (1-AR) | B56: 101 | C56: Master Plan | D56: VOLSYS. CODE | F56: Position Plan | G56: MP | H56: AS | I56: - | J56: Asendiplaan
B57: 102 | C57: Urban Design & Landscaping | E57: 01 | F57: Landscaping | G57: UD | H57: MA | I57: MA | J57: Maastik | K57: Maastik
E58: 02 | F58: Paving | G58: UD | H58: MA | I58: - | J58: Maastik | K58: Maastik
B59: 103 | C59: Car Parks | E59: 01 | F59: Car Park-At Grade Commuter | G59: PK | H59: TL | I59: TL | K59: Tee
E60: 02 | F60: Car Park-Multi Storey Commuter | G60: PK | H60: TL | I60: TL | K60: Tee
E61: 03 | F61: Kiss and Ride Bay | G61: PK | H61: TL | I61: TL | K61: Tee
E62: 04 | F62: Taxi Rank | G62: PK | H62: TL | I62: TL | K62: Tee
B63: 104 | C63: Architecture | F63: Architecture | G63: AR | H63: AR | I63: - | J63: Arhitektuur
B64: 105 | C64: Interior Architecture | E64: 01 | F64: Office Equipment | G64: IA | H64: SA | I64: - | J64: Sisearhitektuur
E65: 02 | F65: Furniture & Fixtures | G65: IA | H65: SA | I65: - | J65: Sisearhitektuur
B66: 106 | C66: Art | E66: 01 | F66: Paintings | G66: OA | H66: AR | I66: - | J66: Kunst
E67: 02 | F67: Sculptures | G67: OA | H67: AR | I67: - | J67: Kunst
B68: 107 | C68: Structural | E68: 01 | F68: Construction Structures | G68: STR | H68: EK | I68: - | J68: Konstruktsioon
E69: 02 | F69: Access Platform | G69: STR | H69: EK | I69: - | J69: Konstruktsioon
E70: 03 | F70: Access Ramp | G70: STR | H70: EK | I70: - | J70: Konstruktsioon
E71: 04 | F71: Building-Permanent | G71: STR | H71: EK | I71: - | J71: Konstruktsioon
E72: 05 | F72: Platform | G72: STR | H72: EK | I72: - | J72: Konstruktsioon
B73: 108 | C73: Acoustics | F73: Acoustics | G73: AC | H73: AK | I73: - | J73: Akustika
B74: 109 | C74: Mechanical Systems (HVAC) | F74: Mechanical Systems (HVAC) | G74: ME | H74: KV | J74: Küte, ventilatsioon ja jahutus
B75: 110 | C75: Heating and Cooling Engineering and Networks (HECL) | E75: 01 | F75: Heating Engineering and Networks | G75: HE | H75: SV | I75: TV | J75: Soojusvarustus
E76: 02 | F76: Cooling Engineering and Networks | G76: CL | H76: KVJ | J76: Jahutusvarustus | L76: 45706 | M76: Taavo Tinno (EHR tähis)
B77: 111 | C77: Water Supply and Sewerage, external | F77: Water Supply and Sewerage, external | G77: WE | H77: VKV | I77: TV | J77: Veevarustuse ja kanalisatsiooni välisosa | K77: Tehnovõrgud
B78: 112 | C78: Water Supply and Sewerage, interior | F78: Water Supply and Sewerage, interior | G78: IW | H78: VKS | I78: - | J78: Veevarustuse ja kanalisatsiooni siseosa
B79: 113 | C79: Gas supply, external network | F79: Gas supply, external network | G79: EG | H79: GVV | I79: TV | J79: Gaasivarustuse välisvõrk | K79: Tehnovõrgud | L79: 45706 | M79: Taavo Tinno (EHR tähis)
B80: 114 | C80: Gas supply, internal network | F80: Gas supply, internal network | G80: IG | H80: GVS | I80: - | J80: Gaasivarustuse siseosa | L80: 45706 | M80: Taavo Tinno (EHR tähis)
B81: 115 | C81: Technology Part | E81: 01 | F81: Compressed Air Systems | G81: TP | H81: TE | I81: - | J81: Tehnoloogia
E82: 02 | F82: Other systems | G82: TP | H82: TE | I82: TV | J82: Tehnoloogia | K82: Tehnovõrgud
E83: 03 | F83: Fuel & Oil Systems | G83: TP | H83: TE | I83: TV | J83: Tehnoloogia | K83: Tehnovõrgud
E84: 04 | F84: Door locking systems | G84: TP | H84: TE | I84: TV | J84: Tehnoloogia
B85: 116 | C85: Vertical Transportation Systems | E85: 01 | F85: Escalator | G85: VT | H85: TE | I85: - | J85: Tehnoloogia
E86: 02 | F86: Lift | G86: VT | H86: TE | I86: - | J86: Tehnoloogia
B87: 117 | C87: Energy | F87: Energy Efficency | G87: EN | H87: EE | I87: - | J87: Energiamärgis
A88: Civil & Structures (2-CV) | B88: 201 | C88: Roads | D88: VOLSYS. CODE | F88: Road | G88: RO | H88: TL | I88: TL | J88: Teed ja liikluskorraldus (va. raudteed, veetranspordirajatised ja sillad-viaduktid) | K88: Tee
B89: 202 | C89: Bridges | E89: 01 | F89: Overpass | G89: BR | H89: TS | I89: TS | J89: Sillad, viaduktid, estakaadid ja tunnelid | K89: Konstruktsioonid
E90: 02 | F90: Bridge-Road | G90: BR | H90: TS | I90: TS | J90: Sillad, viaduktid, estakaadid ja tunnelid | K90: Konstruktsioonid
E91: 03 | F91: Bridge-Railway | G91: BR | H91: TS | I91: TS | J91: Sillad, viaduktid, estakaadid ja tunnelid | K91: Konstruktsioonid
E92: 04 | F92: Underpass | G92: BR | H92: TS | I92: TS | J92: Sillad, viaduktid, estakaadid ja tunnelid | K92: Konstruktsioonid
E93: 05 | F93: Viaduct-Road | G93: BR | H93: TS | I93: TS | J93: Sillad, viaduktid, estakaadid ja tunnelid | K93: Konstruktsioonid
B94: 203 | C94: Tunnels | F94: Tunnel | G94: TU | H94: TS | I94: MR | J94: Sillad, viaduktid, estakaadid ja tunnelid | K94: Muud rajatised
B95: 204 | C95: Retaining Wall | F95: Retaining Wall | G95: RS | H95: TS | I95: TS | J95: Sillad, viaduktid, estakaadid ja tunnelid | K95: Konstruktsioonid
B96: 205 | C96: Earthworks & Geotech | E96: 01 | F96: Earthworks-Cutting | G96: EW | H96: TS | I96: MR | J96: Sillad, viaduktid, estakaadid ja tunnelid | K96: Muud rajatised
E97: 02 | F97: Earthworks-Embankment | G97: EW | H97: TS | I97: MR | J97: Sillad, viaduktid, estakaadid ja tunnelid | K97: Muud rajatised
B98: 206 | C98: Misc Structures | F98: Fauna Crossing | G98: MS | H98: TS | I98: MR | J98: Sillad, viaduktid, estakaadid ja tunnelid | K98: Muud rajatised
B99: 207 | C99: Overhead & Gantry Structures | F99: Overhead Loading Structure | G99: OS | H99: TS | I99: MR | J99: Sillad, viaduktid, estakaadid ja tunnelid | K99: Muud rajatised
B100: 208 | C100: Tower Structures | E100: 01 | F100: Communications Tower | G100: TW | H100: TS | I100: MR | J100: Sillad, viaduktid, estakaadid ja tunnelid | K100: Muud rajatised
...

Sheet DOCUMENT TYPE
A1: DOCUMENT TYPE DESCRIPTION | B1: RBR CODE | C1: EE file name relevant | D1: LT file name relevant
A2: Animation File | B2: AF | C2: 9 | F2: FOR INFORMATION
A3: Application | B3: AP | C3: 9 | G3: EE document types
A4: BIM model native format | B4: BM | C4: 9 | F4: 0 | G4: Ülddokumendid (tiitelleht, sisukord, dokumentide nimekiri jms) | H4: General documents (title page, table of contents, list of documents, etc.)
A5: Bill of Quantity (general) | B5: BQ | C5: 8 | D5: SŽ | F5: 1 | G5: Lähtedokumendid (projekteerimistingimused, tehnilised tingimused jms) | H5: Reference documents (design specifications, technical conditions, etc.)
A6: Bill of Quantity for Eqiupment (Placement of equipment) | B6: BQ | C6: 8 | D6: IŽ | F6: 2 | G6: Kooskõlastused (kooskõlastuste koondtabel, kooskõlastuslehed jms | H6: Coordinations (summary table of coordination, coordination letters, etc.)
A7: Bill of Quantity for Construction Products | B7: BQ | C7: 8 | D7: SPŽ | F7: 3 | G7: Seletuskirjad | H7: Explanatory notes
A8: Bill of Quantity for Construction works | B8: BQ | C8: 8 | D8: SDŽ | F8: 4 | G8: Asendiplaani joonised (välisosa plaanijoonised) | H8: Drawings of the position plan (external plane layouts)
A9: BIM element/object | B9: BE | C9: 9 | F9: 5 | G9: Ehitise üldised plaanijoonised (horisontaalsed üldjoonised, sh üldskeemid) | H9: General layout of the building (horizontal general drawings, including general layouts)
A10: Calculations (general) | B10: CA | C10: 9 | D10: S | F10: 6 | G10: Ehitise üldised vaated, lõiked, pikiprofiilid (vertikaalsed üldjoonised) | H10: General views, cuts, longitudinal profiles of the building (vertical drawings)
A11: Engineering calculations | B11: CA | C11: 9 | D11: IS | F11: 7 | G11: Muud joonised (sõlmed, detailid jms) | H11: Other drawings (nodes, details, etc.)
A12: Economic calculations | B12: CA | C12: 9 | D12: ES | F12: 8 | G12: Spetsifikatsioonid, mahtude loetelud jms | H12: Specifications, volumes, etc.
A13: Clash detection model native file | B13: CC | C13: 9 | F13: 9 | G13: Lisad (kõik muud lisatavad dokumendid) | H13: Extras (all other documents to be added)
A14: Contract | B14: CD | C14: 1
A15: Comment | B15: CE | C15: 9
A16: Change Request Notice | B16: CH | C16: 9 | G16: LT document types
A17: Point Cloud model | B17: CL | C17: 9 | F17: AR | G17: Aiškinamasis raštas | H17: Explanatory note
A18: Combined Model | B18: CM | C18: 9 | F18: BAR | G18: Bendrasis aiškinamasis raštas | H18: General explanatory note
A19: Consent | B19: CN | C19: 0 | F19: B | G19: Brėžiniai | H19: Drawings
A20: Correspondence | B20: CO | C20: 0 | F20: S… | G20: Skaičiavimai (skaičiavimų rezultatai) | H20: Calculations (results of calculations)
A21: Cost Plan | B21: CP | C21: 8 | F21: IS | G21: Inžineriniai skaičiavimai | H21: Engineering calculations
A22: Cost estimation calculations | B22: CE | C22: 8 | D22: KS | F22: KS | G22: Kainos skaičiavimas | H22: Cost estimation
A23: Clash Report | B23: CR | C23: 9 | F23: ES | G23: Ekonominiai skaičiavimai | H23: Economic calculations
A24: Calculation Sheet | B24: CS | C24: 9 | D24: S, IS, KS, ES | F24: TS | G24: Techninės specifikacijos | H24: Technical specifications
A25: Certificate | B25: CT | C25: 9 | F25: BTS | G25: Bendroji techninė specifikacija | H25: General technical specification
A26: Asset Data Dictionary | B26: AD | C26: 9 | F26: Ž… | G26: Žiniaraštis | H26: Bill of ….
A27: Asset Data Dictionary Defi Documents (AD4s) | B27: DA | C27: 9 | F27: PSŽ | G27: Projekto sudėties žiniaraštis | H27: Project Composition Sheet
A28: Database | B28: DB | C28: 9 | F28: BSŽ | G28: Bylos (segtuvų) sudėties žiniaraštis | H28: File (binder) composition chart
A29: Data Drop from BIM Model | B29: DD | C29: 9 | F29: SDŽ | G29: Sustambintų darbų žiniaraštis
A30: Drawings of the position plan (external plane layouts), Site plan drawings | B30: D1 | C30: 4 | D30: B | F30: ŠŽ… | G30: Sąnaudų kiekių žiniaraštis (statybos produktu, įrenginių ir statybos darbų) | H30: BoQ (construction products, equipment and construction works)
A31: General layout of the building (horizontal general drawings, including general layouts), GA drawings | B31: D2 | C31: 5 | D31: B | F31: IŽ | G31: Įrenginių žiniaraštis | H31: Bill of eqiupment (Placement of equipment)
A32: General views, cuts, longitudinal profiles of the building (vertical drawings) | B32: D3 | C32: 6 | D32: B | F32: SPŽ | G32: Statybos produktų žiniaraštis | H32: Construction Products Sheet
A33: Other drawings (nodes, details, etc.) | B33: D4 | C33: 7 | D33: B | F33: SDŽ | G33: Statybos darbų žiniaraštis | H33: Construction works sheet
A34: Detailed equipment or space data | B34: DS | C34: 7
A35: Existing Information | B35: EI | C35: 1
A36: Financial Document | B36: FD | C36: 0
A37: Forms | B37: FM | C37: 0
A38: File Note | B38: FN | C38: 0
A39: Ground Investigation | B39: GI | C39: 1
A40: GIS dataset | B40: GS | C40: 1
A41: Health and Safety | B41: HS | C41: 0
A42: Information Exchange File | B42: IE | C42: 9
A43: BIM Model IFC format | B43: IF | C43: 9
A44: Image | B44: IM | C44: 9
A45: Invoice | B45: IN | C45: 0
... A70: Report | B70: RP | C70: 0
A71: Explanatory reports | B71: RP | C71: 3 | F71: 44375 | G71: Added (Eike Alunurm; RBE)
A72: Schedule of Accommodation | B72: SA | C72: 9
A73: Schedules | B73: SH | C73: 9
A74: Sketch | B74: SK | C74: 7
A75: Snagging List | B75: SN | C75: 0
A76: Specification | B76: SP | C76: 8 | D76: BTS
A77: Specification | B77: SP | C77: 8 | D77: TS
A78: Standard | B78: ST | C78: 1
A79: Survey | B79: SU | C79: 1
A80: Template | B80: TE | C80: 1
A81: Terms of reference | B81: TO | C81: 1 | F81: 27.08.2021 | G81: Changed number (Eike Alunurm; RBE)
A82: Technical Query | B82: TQ | C82: 0
A83: Transmittal | B83: TR | C83: 0
A84: Visualisation | B84: VS | C84: 9
A85: Other Document Type | B85: XX | C85: 9
A86: Coordinations | B86: CO | C86: 2 | F86: 44375 | G86: Added (Eike Alunurm; RBE)
A87: To be continued if required. Any code and description shall be agreed with the Client.

Sheet PROJECT STAGE
A2: STAGE DESCRIPTION | B2: RBR CODE | C2: EE CODE | D2: Staadium
A3: Site Investigations | B3: SI | C3: UP | D3: Uuringud
A4: Value Engineering | B4: VE | C4: VE | D4: Väärtuspõhine alternatiivide võrdlus
A5: Preliminary design | B5: PD | C5: EP | D5: Eelprojekt
A6: Master Design | B6: MD | C6: PP | D6: Põhiprojekt
A7: Detailed Technical Design | B7: DTD | C7: TP | D7: Tööprojekt
A8: Construction | B8: CO | C8: TEP | D8: Teostusprojekt
A9: Operation | B9: OP | C9: OP | D9: Opereerimine
A10: Demolition | B10: DE | C10: LP | D10: Lammutusprojekt
A12: Techinis darbu projektas - LST 1516:2015 | B12: TDP
A13: Būvprojekts minimālā sastāvā - LBN 202-15 | B13: MBP
B14: To be continued if required. Any code and description shall be agreed with the Client.

Sheet ASSET CLASSIFICATION
A1: ASSET CLASSIFICATION | M1: v.2020-03-17 | N1: All updates and modifications should be agreed with BIM Team
O2: Object Description Translation
A3: Discipline | B3: Discipline description | C3: Asset Class | D3: Asset Class description | E3: Function | F3: Asset Function description | G3: Type | H3: Asset Type description | I3: ISO 12006 mapping | J3: Category | K3: Capitalise | L3: Asset Class (Financial) | M3: RBR-Functional classification | N3: Object description | O3: Estonian | P3: Latvian | Q3: Lithuanian | R3: Aux | S3: Calculated for AM comparison | T3: v202002 | U3: RB team | V3: RB when added | W3: comments
A4: AR | B4: Architecture & Services | C4: BD | D4: Buildings & Access | E4: APLT | F4: Access Platform | G4: EW | H4: Elevated Work | I4: Entity | J4: Non Linear | K4: Yes | L4: Buildings | M4: =A4&"-"&R4 -> AR-BD-APLT-EW | N4: Fxd Elev Work Plat | R4: =C4& "-" &E4 & IF(G4<>"","-" &G4,"-00") -> BD-APLT-EW | S4: =C4& "-" &E4 & IF(G4<>"","-" &G4,"") -> BD-APLT-EW | T4: =VLOOKUP(S4,'[1]Asset Classifications'!$M$12:$M$1690,1,FALSE) -> BD-APLT-EW | V4: from_v202002
A5: AR | B5: Architecture & Services | C5: BD | D5: Buildings & Access | E5: APLT | F5: Access Platform | G5: YD | H5: Yard | I5: Entity | J5: Non Linear | K5: Yes | L5: Buildings | M5: =A5&"-"&R5 -> AR-BD-APLT-YD | N5: Fxd Yard Access Plat | R5: =C5& "-" &E5 & IF(G5<>"","-" &G5,"-00") -> BD-APLT-YD | S5: =C5& "-" &E5 & IF(G5<>"","-" &G5,"") -> BD-APLT-YD | T5: =VLOOKUP(S5,'[1]Asset Classifications'!$M$12:$M$1690,1,FALSE) -> BD-APLT-YD | V5: from_v202002
A6: AR | B6: Architecture & Services | C6: BD | D6: Buildings & Access | E6: ARMP | F6: Access Ramp | I6: Entity | J6: Non Linear | K6: Yes | L6: Buildings | M6: =A6&"-"&R6 -> AR-BD-ARMP-00 | N6: Access Ramp | R6: =C6& "-" &E6 & IF(G6<>"","-" &G6,"-00") -> BD-ARMP-00 | S6: =C6& "-" &E6 & IF(G6<>"","-" &G6,"") -> BD-ARMP | T6: =VLOOKUP(S6,'[1]Asset Classifications'!$M$12:$M$1690,1,FALSE) -> BD-ARMP
A7: AR | B7: Architecture & Services | C7: BD | D7: Buildings & Access | E7: BKES | F7: Bicycle Shed | I7: Entity | J7: Non Linear | K7: Yes | L7: Buildings | M7: =A7&"-"&R7 -> AR-BD-BKES-00 | N7: Bicycle Shed | R7: =C7& "-" &E7 & IF(G7<>"","-" &G7,"-00") -> BD-BKES-00 | S7: =C7& "-" &E7 & IF(G7<>"","-" &G7,"") -> BD-BKES | T7: =VLOOKUP(S7,'[1]Asset Classifications'!$M$12:$M$1690,1,FALSE) -> BD-BKES
A8: AR | B8: Architecture & Services | C8: BD | D8: Buildings & Access | E8: BLDG | F8: Building-Permanent | G8: AM | H8: Amenities | I8: Entity | J8: Non Linear | K8: Yes | L8: Buildings | M8: =A8&"-"&R8 -> AR-BD-BLDG-AM | N8: Amenities Building | R8: =C8& "-" &E8 & IF(G8<>"","-" &G8,"-00") -> BD-BLDG-AM | S8: =C8& "-" &E8 & IF(G8<>"","-" &G8,"") -> BD-BLDG-AM | T8: =VLOOKUP(S8,'[1]Asset Classifications'!$M$12:$M$1690,1,FALSE) -> BD-BLDG-AM
A9: AR | B9: Architecture & Services | C9: BD | D9: Buildings & Access | E9: BLDG | F9: Building-Permanent | G9: CO | H9: Communications | I9: Entity | J9: Non Linear | K9: Yes | L9: Buildings | M9: =A9&"-"&R9 -> AR-BD-BLDG-CO | N9: Communications Building | R9: =C9& "-" &E9 & IF(G9<>"","-" &G9,"-00") -> BD-BLDG-CO | S9: =C9& "-" &E9 & IF(G9<>"","-" &G9,"") -> BD-BLDG-CO | T9: =VLOOKUP(S9,'[1]Asset Classifications'!$M$12:$M$1690,1,FALSE) -> BD-BLDG-CO
A10: AR | B10: Architecture & Services | C10: BD | D10: Buildings & Access | E10: BLDG | F10: Building-Permanent | G10: DP | H10: Depot | I10: Entity | J10: Non Linear | K10: Yes | L10: Buildings | M10: =A10&"-"&R10 -> AR-BD-BLDG-DP | N10: Depot Building | R10: =C10& "-" &E10 & IF(G10<>"","-" &G10,"-00") -> BD-BLDG-DP | S10: =C10& "-" &E10 & IF(G10<>"","-" &G10,"") -> BD-BLDG-DP | T10: =VLOOKUP(S10,'[1]Asset Classifications'!$M$12:$M$1690,1,FALSE) -> BD-BLDG-DP | U10: Ops
A11: AR | B11: Architecture & Services | C11: BD | D11: Buildings & Access | E11: BLDG | F11: Building-Permanent | G11: FD | H11: Fuel Shed | I11: Entity | J11: Non Linear | K11: Yes | L11: Buildings | M11: =A11&"-"&R11 -> AR-BD-BLDG-FD | N11: Fuel Shed Building | R11: =C11& "-" &E11 & IF(G11<>"","-" &G11,"-00") -> BD-BLDG-FD | S11: =C11& "-" &E11 & IF(G11<>"","-" &G11,"") -> BD-BLDG-FD | T11: =VLOOKUP(S11,'[1]Asset Classifications'!$M$12:$M$1690,1,FALSE) -> BD-BLDG-FD
A12: AR | B12: Architecture & Services | C12: BD | D12: Buildings & Access | E12: BLDG | F12: Building-Permanent | G12: GA | H12: Garage | I12: Entity | J12: Non Linear | K12: Yes | L12: Buildings | M12: =A12&"-"&R12 -> AR-BD-BLDG-GA | N12: Garage Building | R12: =C12& "-" &E12 & IF(G12<>"","-" &G12,"-00") -> BD-BLDG-GA | S12: =C12& "-" &E12 & IF(G12<>"","-" &G12,"") -> BD-BLDG-GA | T12: =VLOOKUP(S12,'[1]Asset Classifications'!$M$12:$M$1690,1,FALSE) -> BD-BLDG-GA
A13: AR | B13: Architecture & Services | C13: BD | D13: Buildings & Access | E13: BLDG | F13: Building-Permanent | G13: LA | H13: Laboratory | I13: Entity | J13: Non Linear | K13: Yes | L13: Buildings | M13: =A13&"-"&R13 -> AR-BD-BLDG-LA | N13: Laboratory Building | R13: =C13& "-" &E13 & IF(G13<>"","-" &G13,"-00") -> BD-BLDG-LA | S13: =C13& "-" &E13 & IF(G13<>"","-" &G13,"") -> BD-BLDG-LA | T13: =VLOOKUP(S13,'[1]Asset Classifications'!$M$12:$M$1690,1,FALSE) -> BD-BLDG-LA
A14: AR | B14: Architecture & Services | C14: BD | D14: Buildings & Access | E14: BLDG | F14: Building-Permanent | G14: OF | H14: Office/Admin | I14: Entity | J14: Non Linear | K14: Yes | L14: Buildings | M14: =A14&"-"&R14 -> AR-BD-BLDG-OF | N14: Office/Admin Bldg | R14: =C14& "-" &E14 & IF(G14<>"","-" &G14,"-00") -> BD-BLDG-OF | S14: =C14& "-" &E14 & IF(G14<>"","-" &G14,"") -> BD-BLDG-OF | T14: =VLOOKUP(S14,'[1]Asset Classifications'!$M$12:$M$1690,1,FALSE) -> BD-BLDG-OF
A15: AR | B15: Architecture & Services | C15: BD | D15: Buildings & Access | E15: BLDG | F15: Building-Permanent | G15: OP | H15: Operations | I15: Entity | J15: Non Linear | K15: Yes | L15: Buildings | M15: =A15&"-"&R15 -> AR-BD-BLDG-OP | N15: Operations Building | R15: =C15& "-" &E15 & IF(G15<>"","-" &G15,"-00") -> BD-BLDG-OP | S15: =C15& "-" &E15 & IF(G15<>"","-" &G15,"") -> BD-BLDG-OP | T15: =VLOOKUP(S15,'[1]Asset Classifications'!$M$12:$M$1690,1,FALSE) -> BD-BLDG-OP
A16: AR | B16: Architecture & Services | C16: BD | D16: Buildings & Access | E16: BLDG | F16: Building-Permanent | G16: RE | H16: Retail | I16: Entity | J16: Non Linear | K16: Yes | L16: Buildings | M16: =A16&"-"&R16 -> AR-BD-BLDG-RE | N16: Retail Building | R16: =C16& "-" &E16 & IF(G16<>"","-" &G16,"-00") -> BD-BLDG-RE | S16: =C16& "-" &E16 & IF(G16<>"","-" &G16,"") -> BD-BLDG-RE | T16: =VLOOKUP(S16,'[1]Asset Classifications'!$M$12:$M$1690,1,FALSE) -> BD-BLDG-RE
A17: AR | B17: Architecture & Services | C17: BD | D17: Buildings & Access | E17: BLDG | F17: Building-Permanent | G17: RS | H17: Residential | I17: Entity | J17: Non Linear | K17: Yes | L17: Buildings | M17: =A17&"-"&R17 -> AR-BD-BLDG-RS | N17: Residential Building | R17: =C17& "-" &E17 & IF(G17<>"","-" &G17,"-00") -> BD-BLDG-RS | S17: =C17& "-" &E17 & IF(G17<>"","-" &G17,"") -> BD-BLDG-RS | T17: =VLOOKUP(S17,'[1]Asset Classifications'!$M$12:$M$1690,1,FALSE) -> BD-BLDG-RS
A18: AR | B18: Architecture & Services | C18: BD | D18: Buildings & Access | E18: BLDG | F18: Building-Permanent | G18: SB | H18: Signal Box | I18: Entity | J18: Non Linear | K18: Yes | L18: Buildings | M18: =A18&"-"&R18 -> AR-BD-BLDG-SB | N18: Signal Box Building | R18: =C18& "-" &E18 & IF(G18<>"","-" &G18,"-00") -> BD-BLDG-SB | S18: =C18& "-" &E18 & IF(G18<>"","-" &G18,"") -> BD-BLDG-SB | T18: =VLOOKUP(S18,'[1]Asset Classifications'!$M$12:$M$1690,1,FALSE) -> BD-BLDG-SB
A19: AR | B19: Architecture & Services | C19: BD | D19: Buildings & Access | E19: BLDG | F19: Building-Permanent | G19: SD | H19: Storage Shed | I19: Entity | J19: Non Linear | K19: Yes | L19: Buildings | M19: =A19&"-"&R19 -> AR-BD-BLDG-SD | N19: Storage Shed Bldg | R19: =C19& "-" &E19 & IF(G19<>"","-" &G19,"-00") -> BD-BLDG-SD | S19: =C19& "-" &E19 & IF(G19<>"","-" &G19,"") -> BD-BLDG-SD | T19: =VLOOKUP(S19,'[1]Asset Classifications'!$M$12:$M$1690,1,FALSE) -> BD-BLDG-SD
A20: AR | B20: Architecture & Services | C20: BD | D20: Buildings & Access | E20: BLDG | F20: Building-Permanent | G20: SH | H20: Section Hut | I20: Entity | J20: Non Linear | K20: Yes | L20: Buildings | M20: =A20&"-"&R20 -> AR-BD-BLDG-SH | N20: Section Hut Building | R20: =C20& "-" &E20 & IF(G20<>"","-" &G20,"-00") -> BD-BLDG-SH | S20: =C20& "-" &E20 & IF(G20<>"","-" &G20,"") -> BD-BLDG-SH | T20: =VLOOKUP(S20,'[1]Asset Classifications'!$M$12:$M$1690,1,FALSE) -> BD-BLDG-SH
A21: AR | B21: Architecture & Services | C21: BD | D21: Buildings & Access | E21: BLDG | F21: Building-Permanent | G21: SN | H21: Station | I21: Entity | J21: Non Linear | K21: Yes | L21: Buildings | M21: =A21&"-"&R21 -> AR-BD-BLDG-SN | N21: Station Building | R21: =C21& "-" &E21 & IF(G21<>"","-" &G21,"-00") -> BD-BLDG-SN | S21: =C21& "-" &E21 & IF(G21<>"","-" &G21,"") -> BD-BLDG-SN | T21: =VLOOKUP(S21,'[1]Asset Classifications'!$M$12:$M$1690,1,FALSE) -> BD-BLDG-SN | U21: Ops
A22: AR | B22: Architecture & Services | C22: BD | D22: Buildings & Access | E22: BLDG | F22: Building-Permanent | G22: SS | H22: Substation | I22: Entity | J22: Non Linear | K22: Yes | L22: Buildings | M22: =A22&"-"&R22 -> AR-BD-BLDG-SS | N22: Substation Building | R22: =C22& "-" &E22 & IF(G22<>"","-" &G22,"-00") -> BD-BLDG-SS | S22: =C22& "-" &E22 & IF(G22<>"","-" &G22,"") -> BD-BLDG-SS | T22: =VLOOKUP(S22,'[1]Asset Classifications'!$M$12:$M$1690,1,FALSE) -> BD-BLDG-SS
A23: AR | B23: Architecture & Services | C23: BD | D23: Buildings & Access | E23: BLDG | F23: Building-Permanent | G23: SV | H23: Services | I23: Entity | J23: Non Linear | K23: Yes | L23: Buildings | M23: =A23&"-"&R23 -> AR-BD-BLDG-SV | N23: Services Building | R23: =C23& "-" &E23 & IF(G23<>"","-" &G23,"-00") -> BD-BLDG-SV | S23: =C23& "-" &E23 & IF(G23<>"","-" &G23,"") -> BD-BLDG-SV | T23: =VLOOKUP(S23,'[1]Asset Classifications'!$M$12:$M$1690,1,FALSE) -> BD-BLDG-SV | U23: Ops
A24: AR | B24: Architecture & Services | C24: BD | D24: Buildings & Access | E24: BLDG | F24: Building-Permanent | G24: TR | H24: Training | I24: Entity | J24: Non Linear | K24: Yes | L24: Buildings | M24: =A24&"-"&R24 -> AR-BD-BLDG-TR | N24: Training Building | R24: =C24& "-" &E24 & IF(G24<>"","-" &G24,"-00") -> BD-BLDG-TR | S24: =C24& "-" &E24 & IF(G24<>"","-" &G24,"") -> BD-BLDG-TR | T24: =VLOOKUP(S24,'[1]Asset Classifications'!$M$12:$M$1690,1,FALSE) -> BD-BLDG-TR
A25: AR | B25: Architecture & Services | C25: BD | D25: Buildings & Access | E25: BLDG | F25: Building-Permanent | G25: TS | H25: Tunnel Services | I25: Entity | J25: Non Linear | K25: Yes | L25: Infrastructure | M25: =A25&"-"&R25 -> AR-BD-BLDG-TS | N25: Tunnel Services Bldg | R25: =C25& "-" &E25 & IF(G25<>"","-" &G25,"-00") -> BD-BLDG-TS | S25: =C25& "-" &E25 & IF(G25<>"","-" &G25,"") -> BD-BLDG-TS | T25: =VLOOKUP(S25,'[1]Asset Classifications'!$M$12:$M$1690,1,FALSE) -> BD-BLDG-TS
A26: AR | B26: Architecture & Services | C26: BD | D26: Buildings & Access | E26: BLDG | F26: Building-Permanent | G26: WA | H26: Wash/Presentation | I26: Entity | J26: Non Linear | K26: Yes | L26: Buildings | M26: =A26&"-"&R26 -> AR-BD-BLDG-WA | N26: Wash/Presentatn Bldg | R26: =C26& "-" &E26 & IF(G26<>"","-" &G26,"-00") -> BD-BLDG-WA | S26: =C26& "-" &E26 & IF(G26<>"","-" &G26,"") -> BD-BLDG-WA | T26: =VLOOKUP(S26,'[1]Asset Classifications'!$M$12:$M$1690,1,FALSE) -> BD-BLDG-WA
A27: AR | B27: Architecture & Services | C27: BD | D27: Buildings & Access | E27: BLDG | F27: Building-Permanent | G27: WH | H27: Warehouse | I27: Entity | J27: Non Linear | K27: Yes | L27: Buildings | M27: =A27&"-"&R27 -> AR-BD-BLDG-WH | N27: Warehouse Building | R27: =C27& "-" &E27 & IF(G27<>"","-" &G27,"-00") -> BD-BLDG-WH | S27: =C27& "-" &E27 & IF(G27<>"","-" &G27,"") -> BD-BLDG-WH | T27: =VLOOKUP(S27,'[1]Asset Classifications'!$M$12:$M$1690,1,FALSE) -> BD-BLDG-WH
A28: AR | B28: Architecture & Services | C28: BD | D28: Buildings & Access | E28: BLDG | F28: Building-Permanent | G28: WO | H28: Workshop | I28: Entity | J28: Non Linear | K28: Yes | L28: Buildings | M28: =A28&"-"&R28 -> AR-BD-BLDG-WO | N28: Workshop Building | R28: =C28& "-" &E28 & IF(G28<>"","-" &G28,"-00") -> BD-BLDG-WO | S28: =C28& "-" &E28 & IF(G28<>"","-" &G28,"") -> BD-BLDG-WO | T28: =VLOOKUP(S28,'[1]Asset Classifications'!$M$12:$M$1690,1,FALSE) -> BD-BLDG-WO
A29: AR | B29: Architecture & Services | C29: BD | D29: Buildings & Access | E29: BLDP | F29: Building-Portable | I29: Entity | J29: Non Linear | K29: Yes | L29: Buildings | M29: =A29&"-"&R29 -> AR-BD-BLDP-00 | N29: Portable Building | R29: =C29& "-" &E29 & IF(G29<>"","-" &G29,"-00") -> BD-BLDP-00 | S29: =C29& "-" &E29 & IF(G29<>"","-" &G29,"") -> BD-BLDP | T29: =VLOOKUP(S29,'[1]Asset Classifications'!$M$12:$M$1690,1,FALSE) -> BD-BLDP
A30: AR | B30: Architecture & Services | C30: BD | D30: Buildings & Access | E30: BRMP | F30: Boat Ramp | I30: Entity | J30: Non Linear | K30: Yes | L30: Buildings | M30: =A30&"-"&R30 -> AR-BD-BRMP-00 | N30: Boat Ramp | R30: =C30& "-" &E30 & IF(G30<>"","-" &G30,"-00") -> BD-BRMP-00 | S30: =C30& "-" &E30 & IF(G30<>"","-" &G30,"") -> BD-BRMP | T30: =VLOOKUP(S30,'[1]Asset Classifications'!$M$12:$M$1690,1,FALSE) -> #N/A
A31: AR | B31: Architecture & Services | C31: BD | D31: Buildings & Access | E31: CNPY | F31: Canopy | G31: BI | H31: Bicycle | I31: Entity | J31: Non Linear | K31: Yes | L31: Buildings | M31: =A31&"-"&R31 -> AR-BD-CNPY-BI | N31: Canopy-Bicycle | R31: =C31& "-" &E31 & IF(G31<>"","-" &G31,"-00") -> BD-CNPY-BI | S31: =C31& "-" &E31 & IF(G31<>"","-" &G31,"") -> BD-CNPY-BI | T31: =VLOOKUP(S31,'[1]Asset Classifications'!$M$12:$M$1690,1,FALSE) -> BD-CNPY-BI | V31: from_v202002
A32: AR | B32: Architecture & Services | C32: BD | D32: Buildings & Access | E32: CNPY | F32: Canopy | G32: BU | H32: Bus Stop | I32: Entity | J32: Non Linear | K32: Yes | L32: Buildings | M32: =A32&"-"&R32 -> AR-BD-CNPY-BU | N32: Canopy-Bus Stop | R32: =C32& "-" &E32 & IF(G32<>"","-" &G32,"-00") -> BD-CNPY-BU | S32: =C32& "-" &E32 & IF(G32<>"","-" &G32,"") -> BD-CNPY-BU | T32: =VLOOKUP(S32,'[1]Asset Classifications'!$M$12:$M$1690,1,FALSE) -> BD-CNPY-BU
A33: AR | B33: Architecture & Services | C33: BD | D33: Buildings & Access | E33: CNPY | F33: Canopy | G33: DP | H33: Depot | I33: Entity | J33: Non Linear | K33: Yes | L33: Buildings | M33: =A33&"-"&R33 -> AR-BD-CNPY-DP | N33: Canopy-Depot | R33: =C33& "-" &E33 & IF(G33<>"","-" &G33,"-00") -> BD-CNPY-DP | S33: =C33& "-" &E33 & IF(G33<>"","-" &G33,"") -> BD-CNPY-DP | T33: =VLOOKUP(S33,'[1]Asset Classifications'!$M$12:$M$1690,1,FALSE) -> BD-CNPY-DP
A34: AR | B34: Architecture & Services | C34: BD | D34: Buildings & Access | E34: CNPY | F34: Canopy | G34: KR | H34: Kiss and Ride Bay | I34: Entity | J34: Non Linear | K34: Yes | L34: Buildings | M34: =A34&"-"&R34 -> AR-BD-CNPY-KR | N34: Canopy-Kiss and Ride | R34: =C34& "-" &E34 & IF(G34<>"","-" &G34,"-00") -> BD-CNPY-KR | S34: =C34& "-" &E34 & IF(G34<>"","-" &G34,"") -> BD-CNPY-KR | T34: =VLOOKUP(S34,'[1]Asset Classifications'!$M$12:$M$1690,1,FALSE) -> BD-CNPY-KR | V34: from_v202002
A35: AR | B35: Architecture & Services | C35: BD | D35: Buildings & Access | E35: CNPY | F35: Canopy | G35: LR | H35: Tram Stop | I35: Entity | J35: Non Linear | K35: Yes | L35: Buildings | M35: =A35&"-"&R35 -> AR-BD-CNPY-LR | N35: Canopy-Tram Stop | R35: =C35& "-" &E35 & IF(G35<>"","-" &G35,"-00") -> BD-CNPY-LR | S35: =C35& "-" &E35 & IF(G35<>"","-" &G35,"") -> BD-CNPY-LR | T35: =VLOOKUP(S35,'[1]Asset Classifications'!$M$12:$M$1690,1,FALSE) -> BD-CNPY-LR
A36: AR | B36: Architecture & Services | C36: BD | D36: Buildings & Access | E36: CNPY | F36: Canopy | G36: TA | H36: Taxi Rank | I36: Entity | J36: Non Linear | K36: Yes | L36: Buildings | M36: =A36&"-"&R36 -> AR-BD-CNPY-TA | N36: Canopy-Taxi Rank | R36: =C36& "-" &E36 & IF(G36<>"","-" &G36,"-00") -> BD-CNPY-TA | S36: =C36& "-" &E36 & IF(G36<>"","-" &G36,"") -> BD-CNPY-TA | T36: =VLOOKUP(S36,'[1]Asset Classifications'!$M$12:$M$1690,1,FALSE) -> BD-CNPY-TA | V36: from_v202002
A37: AR | B37: Architecture & Services | C37: BD | D37: Buildings & Access | E37: CNPY | F37: Canopy | G37: TR | H37: Train Station | I37: Entity | J37: Non Linear | K37: Yes | L37: Buildings | M37: =A37&"-"&R37 -> AR-BD-CNPY-TR | N37: Canopy-Train Station | R37: =C37& "-" &E37 & IF(G37<>"","-" &G37,"-00") -> BD-CNPY-TR | S37: =C37& "-" &E37 & IF(G37<>"","-" &G37,"") -> BD-CNPY-TR | T37: =VLOOKUP(S37,'[1]Asset Classifications'!$M$12:$M$1690,1,FALSE) -> BD-CNPY-TR
A38: AR | B38: Architecture & Services | C38: BD | D38: Buildings & Access | E38: CNPY | F38: Canopy | G38: WH | H38: Wharf | I38: Entity | J38: Non Linear | K38: Yes | L38: Buildings | M38: =A38&"-"&R38 -> AR-BD-CNPY-WH | N38: Canopy-Wharf | R38: =C38& "-" &E38 & IF(G38<>"","-" &G38,"-00") -> BD-CNPY-WH | S38: =C38& "-" &E38 & IF(G38<>"","-" &G38,"") -> BD-CNPY-WH | T38: =VLOOKUP(S38,'[1]Asset Classifications'!$M$12:$M$1690,1,FALSE) -> BD-CNPY-WH
A39: AR | B39: Architecture & Services | C39: BD | D39: Buildings & Access | E39: CONC | F39: Concourse | I39: Entity | J39: Non Linear | K39: Yes | L39: Buildings | M39: =A39&"-"&R39 -> AR-BD-CONC-00 | N39: Concourse | R39: =C39& "-" &E39 & IF(G39<>"","-" &G39,"-00") -> BD-CONC-00 | S39: =C39& "-" &E39 & IF(G39<>"","-" &G39,"") -> BD-CONC | T39: =VLOOKUP(S39,'[1]Asset Classifications'!$M$12:$M$1690,1,FALSE) -> BD-CONC
A40: AR | B40: Architecture & Services | C40: BD | D40: Buildings & Access | E40: DOOR | F40: Door | G40: HB | H40: Hinged bi-fold | I40: Product | J40: Non Linear | K40: Yes | L40: Buildings | M40: =A40&"-"&R40 -> AR-BD-DOOR-HB | N40: Door-Hinged bi-fold | R40: =C40& "-" &E40 & IF(G40<>"","-" &G40,"-00") -> BD-DOOR-HB | S40: =C40& "-" &E40 & IF(G40<>"","-" &G40,"") -> BD-DOOR-HB | T40: =VLOOKUP(S40,'[1]Asset Classifications'!$M$12:$M$1690,1,FALSE) -> BD-DOOR-HB | V40: from_v202002
A41: AR | B41: Architecture & Services | C41: BD | D41: Buildings & Access | E41: DOOR | F41: Door | G41: HS | H41: Hinged single | I41: Product | J41: Non Linear | K41: Yes | L41: Buildings | M41: =A41&"-"&R41 -> AR-BD-DOOR-HS | N41: Door-Hinged single | R41: =C41& "-" &E41 & IF(G41<>"","-" &G41,"-00") -> BD-DOOR-HS | S41: =C41& "-" &E41 & IF(G41<>"","-" &G41,"") -> BD-DOOR-HS | T41: =VLOOKUP(S41,'[1]Asset Classifications'!$M$12:$M$1690,1,FALSE) -> BD-DOOR-HS | V41: from_v202002
A42: AR | B42: Architecture & Services | C42: BD | D42: Buildings & Access | E42: DOOR | F42: Door | G42: PS | H42: Panel Section | I42: Product | J42: Non Linear | K42: Yes | L42: Buildings | M42: =A42&"-"&R42 -> AR-BD-DOOR-PS | N42: Door-Panel Section | R42: =C42& "-" &E42 & IF(G42<>"","-" &G42,"-00") -> BD-DOOR-PS | S42: =C42& "-" &E42 & IF(G42<>"","-" &G42,"") -> BD-DOOR-PS | T42: =VLOOKUP(S42,'[1]Asset Classifications'!$M$12:$M$1690,1,FALSE) -> BD-DOOR-PS | V42: from_v202002
A43: AR | B43: Architecture & Services | C43: BD | D43: Buildings & Access | E43: DOOR | F43: Door | G43: RO | H43: Rollup | I43: Product | J43: Non Linear | K43: Yes | L43: Buildings | M43: =A43&"-"&R43 -> AR-BD-DOOR-RO | N43: Door-Rollup | R43: =C43& "-" &E43 & IF(G43<>"","-" &G43,"-00") -> BD-DOOR-RO | S43: =C43& "-" &E43 & IF(G43<>"","-" &G43,"") -> BD-DOOR-RO | T43: =VLOOKUP(S43,'[1]Asset Classifications'!$M$12:$M$1690,1,FALSE) -> BD-DOOR-RO | V43: from_v202002
A44: AR | B44: Architecture & Services | C44: BD | D44: Buildings & Access | E44: DOOR | F44: Door | G44: SL | H44: Sliding | I44: Product | J44: Non Linear | K44: Yes | L44: Buildings | M44: =A44&"-"&R44 -> AR-BD-DOOR-SL | N44: Door-Sliding | R44: =C44& "-" &E44 & IF(G44<>"","-" &G44,"-00") -> BD-DOOR-SL | S44: =C44& "-" &E44 & IF(G44<>"","-" &G44,"") -> BD-DOOR-SL | T44: =VLOOKUP(S44,'[1]Asset Classifications'!$M$12:$M$1690,1,FALSE) -> BD-DOOR-SL | V44: from_v202002
A45: AR | B45: Architecture & Services | C45: BD | D45: Buildings & Access | E45: DOOR | F45: Door | G45: TC | H45: Tilt-up canopy | I45: Product | J45: Non Linear | K45: Yes | L45: Buildings | M45: =A45&"-"&R45 -> AR-BD-DOOR-TC | N45: Door-Tilt-up canopy | R45: =C45& "-" &E45 & IF(G45<>"","-" &G45,"-00") -> BD-DOOR-TC | S45: =C45& "-" &E45 & IF(G45<>"","-" &G45,"") -> BD-DOOR-TC | T45: =VLOOKUP(S45,'[1]Asset Classifications'!$M$12:$M$1690,1,FALSE) -> BD-DOOR-TC | V45: from_v202002
A46: AR | B46: Architecture & Services | C46: BD | D46: Buildings & Access | E46: DOOR | F46: Door | G46: TR | H46: Tilt-up retractable | I46: Product | J46: Non Linear | K46: Yes | L46: Buildings | M46: =A46&"-"&R46 -> AR-BD-DOOR-TR | N46: Door-Tilt-up retract | R46: =C46& "-" &E46 & IF(G46<>"","-" &G46,"-00") -> BD-DOOR-TR | S46: =C46& "-" &E46 & IF(G46<>"","-" &G46,"") -> BD-DOOR-TR | T46: =VLOOKUP(S46,'[1]Asset Classifications'!$M$12:$M$1690,1,FALSE) -> BD-DOOR-TR | V46: from_v202002
A47: AR | B47: Architecture & Services | C47: BD | D47: Buildings & Access | E47: EXPB | F47: Expandable Barrier | I47: Product | J47: Non Linear | K47: Yes | L47: Plant & Equipment | M47: =A47&"-"&R47 -> AR-BD-EXPB-00 | N47: Expandable Barrier | R47: =C47& "-" &E47 & IF(G47<>"","-" &G47,"-00") -> BD-EXPB-00 | S47: =C47& "-" &E47 & IF(G47<>"","-" &G47,"") -> BD-EXPB | T47: =VLOOKUP(S47,'[1]Asset Classifications'!$M$12:$M$1690,1,FALSE) -> BD-EXPB | V47: from_v202002
A48: AR | B48: Architecture & Services | C48: BD | D48: Buildings & Access | E48: GWAY | F48: Gangway | I48: Entity | J48: Non Linear | K48: Yes | L48: Buildings | M48: =A48&"-"&R48 -> AR-BD-GWAY-00 | N48: Gangway | R48: =C48& "-" &E48 & IF(G48<>"","-" &G48,"-00") -> BD-GWAY-00 | S48: =C48& "-" &E48 & IF(G48<>"","-" &G48,"") -> BD-GWAY | T48: =VLOOKUP(S48,'[1]Asset Classifications'!$M$12:$M$1690,1,FALSE) -> BD-GWAY
A49: AR | B49: Architecture & Services | C49: BD | D49: Buildings & Access | E49: HSRE | F49: Height Safety Restraint | I49: Product | J49: Non Linear | K49: Yes | L49: Buildings | M49: =A49&"-"&R49 -> AR-BD-HSRE-00 | N49: Hgt Safety Restraint | R49: =C49& "-" &E49 & IF(G49<>"","-" &G49,"-00") -> BD-HSRE-00 | S49: =C49& "-" &E49 & IF(G49<>"","-" &G49,"") -> BD-HSRE | T49: =VLOOKUP(S49,'[1]Asset Classifications'!$M$12:$M$1690,1,FALSE) -> BD-HSRE | V49: from_v202002
A50: AR | B50: Architecture & Services | C50: BD | D50: Buildings & Access | E50: HSTD | F50: Hardstand | I50: Entity | J50: Non Linear | K50: Yes | L50: Buildings | M50: =A50&"-"&R50 -> AR-BD-HSTD-00 | N50: Hardstand | R50: =C50& "-" &E50 & IF(G50<>"","-" &G50,"-00") -> BD-HSTD-00 | S50: =C50& "-" &E50 & IF(G50<>"","-" &G50,"") -> BD-HSTD | T50: =VLOOKUP(S50,'[1]Asset Classifications'!$M$12:$M$1690,1,FALSE) -> #N/A
A51: AR | B51: Architecture & Services | C51: BD | D51: Buildings & Access | E51: ISCA | F51: Integrated Services Cabinet | I51: Product | J51: Non Linear | K51: Yes | L51: Buildings | M51: =A51&"-"&R51 -> AR-BD-ISCA-00 | N51: Int Services Cabinet | R51: =C51& "-" &E51 & IF(G51<>"","-" &G51,"-00") -> BD-ISCA-00 | S51: =C51& "-" &E51 & IF(G51<>"","-" &G51,"") -> BD-ISCA | T51: =VLOOKUP(S51,'[1]Asset Classifications'!$M$12:$M$1690,1,FALSE) -> BD-ISCA | V51: from_v202002
A52: AR | B52: Architecture & Services | C52: BD | D52: Buildings & Access | E52: JETY | F52: Jetty | I52: Entity | J52: Non Linear | K52: Yes | L52: Buildings | M52: =A52&"-"&R52 -> AR-BD-JETY-00 | N52: Jetty | R52: =C52& "-" &E52 & IF(G52<>"","-" &G52,"-00") -> BD-JETY-00 | S52: =C52& "-" &E52 & IF(G52<>"","-" &G52,"") -> BD-JETY | T52: =VLOOKUP(S52,'[1]Asset Classifications'!$M$12:$M$1690,1,FALSE) -> BD-JETY
A53: AR | B53: Architecture & Services | C53: BD | D53: Buildings & Access | E53: LADR | F53: Ladder | I53: Product | J53: Non Linear | K53: Yes | L53: Buildings | M53: =A53&"-"&R53 -> AR-BD-LADR-00 | N53: Ladder | R53: =C53& "-" &E53 & IF(G53<>"","-" &G53,"-00") -> BD-LADR-00 | S53: =C53& "-" &E53 & IF(G53<>"","-" &G53,"") -> BD-LADR | T53: =VLOOKUP(S53,'[1]Asset Classifications'!$M$12:$M$1690,1,FALSE) -> BD-LADR
A54: AR | B54: Architecture & Services | C54: BD | D54: Buildings & Access | E54: LFTT | F54: Lift Tower | I54: Entity | J54: Non Linear | K54: Yes | L54: Buildings | M54: =A54&"-"&R54 -> AR-BD-LFTT-00 | N54: Lift Tower | R54: =C54& "-" &E54 & IF(G54<>"","-" &G54,"-00") -> BD-LFTT-00 | S54: =C54& "-" &E54 & IF(G54<>"","-" &G54,"") -> BD-LFTT | T54: =VLOOKUP(S54,'[1]Asset Classifications'!$M$12:$M$1690,1,FALSE) -> BD-LFTT
A55: AR | B55: Architecture & Services | C55: BD | D55: Buildings & Access | E55: PIER | F55: Pier | I55: Entity | J55: Non Linear | K55: Yes | L55: Buildings | M55: =A55&"-"&R55 -> AR-BD-PIER-00 | N55: Pier | R55: =C55& "-" &E55 & IF(G55<>"","-" &G55,"-00") -> BD-PIER-00 | S55: =C55& "-" &E55 & IF(G55<>"","-" &G55,"") -> BD-PIER | T55: =VLOOKUP(S55,'[1]Asset Classifications'!$M$12:$M$1690,1,FALSE) -> BD-PIER
A56: AR | B56: Architecture & Services | C56: BD | D56: Buildings & Access | E56: PLAT | F56: Platform | G56: LR | H56: Tram Stop | I56: Entity | J56: Linear | K56: Yes | L56: Buildings | M56: =A56&"-"&R56 -> AR-BD-PLAT-LR | N56: Platform-Tram Stop | R56: =C56& "-" &E56 & IF(G56<>"","-" &G56,"-00") -> BD-PLAT-LR | S56: =C56& "-" &E56 & IF(G56<>"","-" &G56,"") -> BD-PLAT-LR | T56: =VLOOKUP(S56,'[1]Asset Classifications'!$M$12:$M$1690,1,FALSE) -> BD-PLAT-LR
A57: AR | B57: Architecture & Services | C57: BD | D57: Buildings & Access | E57: PLAT | F57: Platform | G57: TR | H57: Train Station | I57: Entity | J57: Linear | K57: Yes | L57: Buildings | M57: =A57&"-"&R57 -> AR-BD-PLAT-TR | N57: Platform-Train Stn | R57: =C57& "-" &E57 & IF(G57<>"","-" &G57,"-00") -> BD-PLAT-TR | S57: =C57& "-" &E57 & IF(G57<>"","-" &G57,"") -> BD-PLAT-TR | T57: =VLOOKUP(S57,'[1]Asset Classifications'!$M$12:$M$1690,1,FALSE) -> BD-PLAT-TR
A58: AR | B58: Architecture & Services | C58: BD | D58: Buildings & Access | E58: PLTH | F58: Plinth | I58: Entity | J58: Non Linear | K58: Yes | L58: Buildings | M58: =A58&"-"&R58 -> AR-BD-PLTH-00 | N58: Plinth | R58: =C58& "-" &E58 & IF(G58<>"","-" &G58,"-00") -> BD-PLTH-00 | S58: =C58& "-" &E58 & IF(G58<>"","-" &G58,"") -> BD-PLTH | T58: =VLOOKUP(S58,'[1]Asset Classifications'!$M$12:$M$1690,1,FALSE) -> #N/A
A59: AR | B59: Architecture & Services | C59: BD | D59: Buildings & Access | E59: PONT | F59: Pontoon | I59: Entity | J59: Non Linear | K59: Yes | L59: Buildings | M59: =A59&"-"&R59 -> AR-BD-PONT-00 | N59: Pontoon | R59: =C59& "-" &E59 & IF(G59<>"","-" &G59,"-00") -> BD-PONT-00 | S59: =C59& "-" &E59 & IF(G59<>"","-" &G59,"") -> BD-PONT | T59: =VLOOKUP(S59,'[1]Asset Classifications'!$M$12:$M$1690,1,FALSE) -> BD-PONT
A60: AR | B60: Architecture & Services | C60: BD | D60: Buildings & Access | E60: STRS | F60: Stairs | G60: AC | H60: Access | I60: Entity | J60: Non Linear | K60: Yes | L60: Buildings | M60: =A60&"-"&R60 -> AR-BD-STRS-AC | N60: Stairs-Bldg Access | R60: =C60& "-" &E60 & IF(G60<>"","-" &G60,"-00") -> BD-STRS-AC | S60: =C60& "-" &E60 & IF(G60<>"","-" &G60,"") -> BD-STRS-AC | T60: =VLOOKUP(S60,'[1]Asset Classifications'!$M$12:$M$1690,1,FALSE) -> BD-STRS-AC
A61: AR | B61: Architecture & Services | C61: BD | D61: Buildings & Access | E61: STRS | F61: Stairs | G61: FI | H61: Fire | I61: Entity | J61: Non Linear | K61: Yes | L61: Buildings | M61: =A61&"-"&R61 -> AR-BD-STRS-FI | N61: Stairs-Fire | R61: =C61& "-" &E61 & IF(G61<>"","-" &G61,"-00") -> BD-STRS-FI | S61: =C61& "-" &E61 & IF(G61<>"","-" &G61,"") -> BD-STRS-FI | T61: =VLOOKUP(S61,'[1]Asset Classifications'!$M$12:$M$1690,1,FALSE) -> BD-STRS-FI
A62: AR | B62: Architecture & Services | C62: BD | D62: Buildings & Access | E62: STRS | F62: Stairs | G62: TP | H62: Track to Platform | I62: Product | J62: Non Linear | K62: Yes | L62: Plant & Equipment | M62: =A62&"-"&R62 -> AR-BD-STRS-TP | N62: Stairs-Trk to Platfm | R62: =C62& "-" &E62 & IF(G62<>"","-" &G62,"-00") -> BD-STRS-TP | S62: =C62& "-" &E62 & IF(G62<>"","-" &G62,"") -> BD-STRS-TP | T62: =VLOOKUP(S62,'[1]Asset Classifications'!$M$12:$M$1690,1,FALSE) -> BD-STRS-TP
A63: AR | B63: Architecture & Services | C63: BD | D63: Buildings & Access | E63: STRS | F63: Stairs | G63: TT | H63: Train to Track | I63: Product | J63: Non Linear | K63: Yes | L63: Plant & Equipment | M63: =A63&"-"&R63 -> AR-BD-STRS-TT | N63: Stairs-Train to Trk | R63: =C63& "-" &E63 & IF(G63<>"","-" &G63,"-00") -> BD-STRS-TT | S63: =C63& "-" &E63 & IF(G63<>"","-" &G63,"") -> BD-STRS-TT | T63: =VLOOKUP(S63,'[1]Asset Classifications'!$M$12:$M$1690,1,FALSE) -> BD-STRS-TT
A64: AR | B64: Architecture & Services | C64: BD | D64: Buildings & Access | E64: SUTE | F64: Suite | I64: Space | J64: Non Linear | K64: No | M64: =A64&"-"&R64 -> AR-BD-SUTE-00 | N64: Suite | R64: =C64& "-" &E64 & IF(G64<>"","-" &G64,"-00") -> BD-SUTE-00 | S64: =C64& "-" &E64 & IF(G64<>"","-" &G64,"") -> BD-SUTE | T64: =VLOOKUP(S64,'[1]Asset Classifications'!$M$12:$M$1690,1,FALSE) -> BD-SUTE | V64: from_v202002
A65: AR | B65: Architecture & Services | C65: BD | D65: Buildings & Access | E65: WALK | F65: Walkway | I65: Entity | J65: Non Linear | K65: Yes | L65: Buildings | M65: =A65&"-"&R65 -> AR-BD-WALK-00 | N65: Walkway-Bldg Access | R65: =C65& "-" &E65 & IF(G65<>"","-" &G65,"-00") -> BD-WALK-00 | S65: =C65& "-" &E65 & IF(G65<>"","-" &G65,"") -> BD-WALK | T65: =VLOOKUP(S65,'[1]Asset Classifications'!$M$12:$M$1690,1,FALSE) -> BD-WALK
A66: AR | B66: Architecture & Services | C66: CA | D66: Compressed Air Systems | E66: AIRD | F66: Air Dryer | I66: Product | J66: Non Linear | K66: No, with parent system | M66: =A66&"-"&R66 -> AR-CA-AIRD-00 | N66: Air Sup-Air Dryer | R66: =C66& "-" &E66 & IF(G66<>"","-" &G66,"-00") -> CA-AIRD-00 | S66: =C66& "-" &E66 & IF(G66<>"","-" &G66,"") -> CA-AIRD | T66: =VLOOKUP(S66,'[1]Asset Classifications'!$M$12:$M$1690,1,FALSE) -> CA-AIRD
A67: AR | B67: Architecture & Services | C67: CA | D67: Compressed Air Systems | E67: AIRM | F67: Air Main | I67: Product | J67: Linear | K67: No, with parent system | M67: =A67&"-"&R67 -> AR-CA-AIRM-00 | N67: Air Sup-Main | R67: =C67& "-" &E67 & IF(G67<>"","-" &G67,"-00") -> CA-AIRM-00 | S67: =C67& "-" &E67 & IF(G67<>"","-" &G67,"") -> CA-AIRM | T67: =VLOOKUP(S67,'[1]Asset Classifications'!$M$12:$M$1690,1,FALSE) -> CA-AIRM
A68: AR | B68: Architecture & Services | C68: CA | D68: Compressed Air Systems | E68: AIRR | F68: Air Receiver | I68: Product | J68: Non Linear | K68: No, with parent system | M68: =A68&"-"&R68 -> AR-CA-AIRR-00 | N68: Air Sup-Air Receiver | R68: =C68& "-" &E68 & IF(G68<>"","-" &G68,"-00") -> CA-AIRR-00 | S68: =C68& "-" &E68 & IF(G68<>"","-" &G68,"") -> CA-AIRR | T68: =VLOOKUP(S68,'[1]Asset Classifications'!$M$12:$M$1690,1,FALSE) -> CA-AIRR
A69: AR | B69: Architecture & Services | C69: CA | D69: Compressed Air Systems | E69: AIRS | F69: Air Supply System | G69: DP | H69: Depot | I69: System | J69: Non Linear | K69: Yes, each system | L69: Buildings | M69: =A69&"-"&R69 -> AR-CA-AIRS-DP | N69: Air Supply Sys-Depot | R69: =C69& "-" &E69 & IF(G69<>"","-" &G69,"-00") -> CA-AIRS-DP | S69: =C69& "-" &E69 & IF(G69<>"","-" &G69,"") -> CA-AIRS-DP | T69: =VLOOKUP(S69,'[1]Asset Classifications'!$M$12:$M$1690,1,FALSE) -> CA-AIRS-DP
A70: AR | B70: Architecture & Services | C70: CA | D70: Compressed Air Systems | E70: AIRS | F70: Air Supply System | G70: SI | H70: Signalling | I70: System | J70: Non Linear | K70: Yes, each system | L70: Infrastructure | M70: =A70&"-"&R70 -> AR-CA-AIRS-SI | N70: Air Supply Sys-Signl | R70: =C70& "-" &E70 & IF(G70<>"","-" &G70,"-00") -> CA-AIRS-SI | S70: =C70& "-" &E70 & IF(G70<>"","-" &G70,"") -> CA-AIRS-SI | T70: =VLOOKUP(S70,'[1]Asset Classifications'!$M$12:$M$1690,1,FALSE) -> CA-AIRS-SI
A71: AR | B71: Architecture & Services | C71: CA | D71: Compressed Air Systems | E71: AIRS | F71: Air Supply System | G71: SS | H71: Substation | I71: System | J71: Non Linear | K71: Yes, each system | L71: Infrastructure | M71: =A71&"-"&R71 -> AR-CA-AIRS-SS | N71: Air Supply Sys-Subs | R71: =C71& "-" &E71 & IF(G71<>"","-" &G71,"-00") -> CA-AIRS-SS | S71: =C71& "-" &E71 & IF(G71<>"","-" &G71,"") -> CA-AIRS-SS | T71: =VLOOKUP(S71,'[1]Asset Classifications'!$M$12:$M$1690,1,FALSE) -> CA-AIRS-SS
A72: AR | B72: Architecture & Services | C72: CA | D72: Compressed Air Systems | E72: AUTO | F72: Auto Drain | I72: Product | J72: Non Linear | K72: No, with parent system | M72: =A72&"-"&R72 -> AR-CA-AUTO-00 | N72: Air Sup-Auto Drain | R72: =C72& "-" &E72 & IF(G72<>"","-" &G72,"-00") -> CA-AUTO-00 | S72: =C72& "-" &E72 & IF(G72<>"","-" &G72,"") -> CA-AUTO | T72: =VLOOKUP(S72,'[1]Asset Classifications'!$M$12:$M$1690,1,FALSE) -> CA-AUTO
A73: AR | B73: Architecture & Services | C73: CA | D73: Compressed Air Systems | E73: COMP | F73: Compressor | I73: Product | J73: Non Linear | K73: No, with parent system | M73: =A73&"-"&R73 -> AR-CA-COMP-00 | N73: Compressor (Fxd) | R73: =C73& "-" &E73 & IF(G73<>"","-" &G73,"-00") -> CA-COMP-00 | S73: =C73& "-" &E73 & IF(G73<>"","-" &G73,"") -> CA-COMP | T73: =VLOOKUP(S73,'[1]Asset Classifications'!$M$12:$M$1690,1,FALSE) -> CA-COMP
A74: AR | B74: Architecture & Services | C74: CA | D74: Compressed Air Systems | E74: EXPJ | F74: Expansion Joint | I74: Product | J74: Non Linear | K74: No, with parent system | M74: =A74&"-"&R74 -> AR-CA-EXPJ-00 | N74: Air Sup-Expansn Jnt | R74: =C74& "-" &E74 & IF(G74<>"","-" &G74,"-00") -> CA-EXPJ-00 | S74: =C74& "-" &E74 & IF(G74<>"","-" &G74,"") -> CA-EXPJ | T74: =VLOOKUP(S74,'[1]Asset Classifications'!$M$12:$M$1690,1,FALSE) -> CA-EXPJ
A75: AR | B75: Architecture & Services | C75: CA | D75: Compressed Air Systems | E75: MANI | F75: Air Manifold | I75: Product | J75: Non Linear | K75: No, with parent system | M75: =A75&"-"&R75 -> AR-CA-MANI-00 | N75: Air Sup-Air Manifold | R75: =C75& "-" &E75 & IF(G75<>"","-" &G75,"-00") -> CA-MANI-00 | S75: =C75& "-" &E75 & IF(G75<>"","-" &G75,"") -> CA-MANI | T75: =VLOOKUP(S75,'[1]Asset Classifications'!$M$12:$M$1690,1,FALSE) -> CA-MANI
A76: AR | B76: Architecture & Services | C76: CA | D76: Compressed Air Systems | E76: PRTX | F76: Pressure Transmitter | I76: Product | J76: Non Linear | K76: No, with parent system | M76: =A76&"-"&R76 -> AR-CA-PRTX-00 | N76: Air Sup-Pressure Tx | R76: =C76& "-" &E76 & IF(G76<>"","-" &G76,"-00") -> CA-PRTX-00 | S76: =C76& "-" &E76 & IF(G76<>"","-" &G76,"") -> CA-PRTX | T76: =VLOOKUP(S76,'[1]Asset Classifications'!$M$12:$M$1690,1,FALSE) -> CA-PRTX
A77: AR | B77: Architecture & Services | C77: ES | D77: LV Reticulation & Lighting Systems | E77: ATSW | F77: Automatic Transfer Switch | I77: Product | J77: Non Linear | K77: No, with parent system | M77: =A77&"-"&R77 -> AR-ES-ATSW-00 | N77: Auto Transfer Switch | R77: =C77& "-" &E77 & IF(G77<>"","-" &G77,"-00") -> ES-ATSW-00 | S77: =C77& "-" &E77 & IF(G77<>"","-" &G77,"") -> ES-ATSW | T77: =VLOOKUP(S77,'[1]Asset Classifications'!$M$12:$M$1690,1,FALSE) -> ES-ATSW
A78: AR | B78: Architecture & Services | C78: ES | D78: LV Reticulation & Lighting Systems | E78: BATT | F78: Battery | I78: Product | J78: Non Linear | K78: No, with parent system | M78: =A78&"-"&R78 -> AR-ES-BATT-00 | N78: LV BU Battery | R78: =C78& "-" &E78 & IF(G78<>"","-" &G78,"-00") -> ES-BATT-00 | S78: =C78& "-" &E78 & IF(G78<>"","-" &G78,"") -> ES-BATT | T78: =VLOOKUP(S78,'[1]Asset Classifications'!$M$12:$M$1690,1,FALSE) -> ES-BATT
A79: AR | B79: Architecture & Services | C79: ES | D79: LV Reticulation & Lighting Systems | E79: CHGO | F79: Changeover Panel | I79: Product | J79: Non Linear | K79: No, with parent system | M79: =A79&"-"&R79 -> AR-ES-CHGO-00 | N79: LV Changeover Panel | R79: =C79& "-" &E79 & IF(G79<>"","-" &G79,"-00") -> ES-CHGO-00 | S79: =C79& "-" &E79 & IF(G79<>"","-" &G79,"") -> ES-CHGO | T79: =VLOOKUP(S79,'[1]Asset Classifications'!$M$12:$M$1690,1,FALSE) -> ES-CHGO | V79: from_v202002
A80: AR | B80: Architecture & Services | C80: ES | D80: LV Reticulation & Lighting Systems | E80: DBRD | F80: Distribution Board | G80: EM | H80: Emergency | I80: Product | J80: Non Linear | K80: No, with parent system | M80: =A80&"-"&R80 -> AR-ES-DBRD-EM | N80: Elec DB-Emergency | R80: =C80& "-" &E80 & IF(G80<>"","-" &G80,"-00") -> ES-DBRD-EM | S80: =C80& "-" &E80 & IF(G80<>"","-" &G80,"") -> ES-DBRD-EM | T80: =VLOOKUP(S80,'[1]Asset Classifications'!$M$12:$M$1690,1,FALSE) -> ES-DBRD-EM | V80: from_v202002
A81: AR | B81: Architecture & Services | C81: ES | D81: LV Reticulation & Lighting Systems | E81: DBRD | F81: Distribution Board | G81: ES | H81: Essential | I81: Product | J81: Non Linear | K81: No, with parent system | M81: =A81&"-"&R81 -> AR-ES-DBRD-ES | N81: Elec DB-Essential | R81: =C81& "-" &E81 & IF(G81<>"","-" &G81,"-00") -> ES-DBRD-ES | S81: =C81& "-" &E81 & IF(G81<>"","-" &G81,"") -> ES-DBRD-ES | T81: =VLOOKUP(S81,'[1]Asset Classifications'!$M$12:$M$1690,1,FALSE) -> ES-DBRD-ES | V81: from_v202002
A82: AR | B82: Architecture & Services | C82: ES | D82: LV Reticulation & Lighting Systems | E82: DBRD | F82: Distribution Board | G82: LS | H82: Life Safety | I82: Product | J82: Non Linear | K82: No, with parent system | M82: =A82&"-"&R82 -> AR-ES-DBRD-LS | N82: Elec DB-Life Safety | R82: =C82& "-" &E82 & IF(G82<>"","-" &G82,"-00") -> ES-DBRD-LS | S82: =C82& "-" &E82 & IF(G82<>"","-" &G82,"") -> ES-DBRD-LS | T82: =VLOOKUP(S82,'[1]Asset Classifications'!$M$12:$M$1690,1,FALSE) -> ES-DBRD-LS | V82: from_v202002
A83: AR | B83: Architecture & Services | C83: ES | D83: LV Reticulation & Lighting Systems | E83: DBRD | F83: Distribution Board | G83: MN | H83: Main | I83: Product | J83: Non Linear | K83: No, with parent system | M83: =A83&"-"&R83 -> AR-ES-DBRD-MN | N83: Fclty Elec DB-Main | R83: =C83& "-" &E83 & IF(G83<>"","-" &G83,"-00") -> ES-DBRD-MN | S83: =C83& "-" &E83 & IF(G83<>"","-" &G83,"") -> ES-DBRD-MN | T83: =VLOOKUP(S83,'[1]Asset Classifications'!$M$12:$M$1690,1,FALSE) -> #N/A
A84: AR | B84: Architecture & Services | C84: ES | D84: LV Reticulation & Lighting Systems | E84: DBRD | F84: Distribution Board | G84: NO | H84: Normal | I84: Product | J84: Non Linear | K84: No, with parent system | M84: =A84&"-"&R84 -> AR-ES-DBRD-NO | N84: Elec DB-Normal | R84: =C84& "-" &E84 & IF(G84<>"","-" &G84,"-00") -> ES-DBRD-NO | S84: =C84& "-" &E84 & IF(G84<>"","-" &G84,"") -> ES-DBRD-NO | T84: =VLOOKUP(S84,'[1]Asset Classifications'!$M$12:$M$1690,1,FALSE) -> ES-DBRD-NO | V84: from_v202002
A85: AR | B85: Architecture & Services | C85: ES | D85: LV Reticulation & Lighting Systems | E85: DBRD | F85: Distribution Board | G85: SU | H85: Sub | I85: Product | J85: Non Linear | K85: No, with parent system | M85: =A85&"-"&R85 -> AR-ES-DBRD-SU | N85: Fclty Elec DB-Sub | R85: =C85& "-" &E85 & IF(G85<>"","-" &G85,"-00") -> ES-DBRD-SU | S85: =C85& "-" &E85 & IF(G85<>"","-" &G85,"") -> ES-DBRD-SU | T85: =VLOOKUP(S85,'[1]Asset Classifications'!$M$12:$M$1690,1,FALSE) -> #N/A
A86: AR | B86: Architecture & Services | C86: ES | D86: LV Reticulation & Lighting Systems | E86: DBRD | F86: Distribution Board | G86: UP | H86: UPS | I86: Product | J86: Non Linear | K86: No, with parent system | M86: =A86&"-"&R86 -> AR-ES-DBRD-UP | N86: Elec DB-UPS | R86: =C86& "-" &E86 & IF(G86<>"","-" &G86,"-00") -> ES-DBRD-UP | S86: =C86& "-" &E86 & IF(G86<>"","-" &G86,"") -> ES-DBRD-UP | T86: =VLOOKUP(S86,'[1]Asset Classifications'!$M$12:$M$1690,1,FALSE) -> ES-DBRD-UP | V86: from_v202002
A87: AR | B87: Architecture & Services | C87: ES | D87: LV Reticulation & Lighting Systems | E87: ELEC | F87: LV Reticulation System | G87: BD | H87: Building | I87: System | J87: Non Linear | K87: Yes, each system | L87: Buildings | M87: =A87&"-"&R87 -> AR-ES-ELEC-BD | N87: LV Reticulation-Bldg | R87: =C87& "-" &E87 & IF(G87<>"","-" &G87,"-00") -> ES-ELEC-BD | S87: =C87& "-" &E87 & IF(G87<>"","-" &G87,"") -> ES-ELEC-BD | T87: =VLOOKUP(S87,'[1]Asset Classifications'!$M$12:$M$1690,1,FALSE) -> ES-ELEC-BD
A88: AR | B88: Architecture & Services | C88: ES | D88: LV Reticulation & Lighting Systems | E88: ELEC | F88: LV Reticulation System | G88: TU | H88: Tunnel | I88: System | J88: Non Linear | K88: Yes, each system | L88: Infrastructure | M88: =A88&"-"&R88 -> AR-ES-ELEC-TU | N88: LV Reticulation-Tunl | R88: =C88& "-" &E88 & IF(G88<>"","-" &G88,"-00") -> ES-ELEC-TU | S88: =C88& "-" &E88 & IF(G88<>"","-" &G88,"") -> ES-ELEC-TU | T88: =VLOOKUP(S88,'[1]Asset Classifications'!$M$12:$M$1690,1,FALSE) -> ES-ELEC-TU
A89: AR | B89: Architecture & Services | C89: ES | D89: LV Reticulation & Lighting Systems | E89: ERTH | F89: Earthing | I89: Product | J89: Non Linear | K89: No, with parent system | M89: =A89&"-"&R89 -> AR-ES-ERTH-00 | N89: Fclty Earthing | R89: =C89& "-" &E89 & IF(G89<>"","-" &G89,"-00") -> ES-ERTH-00 | S89: =C89& "-" &E89 & IF(G89<>"","-" &G89,"") -> ES-ERTH | T89: =VLOOKUP(S89,'[1]Asset Classifications'!$M$12:$M$1690,1,FALSE) -> ES-ERTH
A90: AR | B90: Architecture & Services | C90: ES | D90: LV Reticulation & Lighting Systems | E90: GENC | F90: Generator Connection | I90: Product | J90: Non Linear | K90: No, with parent system | M90: =A90&"-"&R90 -> AR-ES-GENC-00 | N90: LV BU Generator Conn | R90: =C90& "-" &E90 & IF(G90<>"","-" &G90,"-00") -> ES-GENC-00 | S90: =C90& "-" &E90 & IF(G90<>"","-" &G90,"") -> ES-GENC | T90: =VLOOKUP(S90,'[1]Asset Classifications'!$M$12:$M$1690,1,FALSE) -> ES-GENC | V90: from_v202002
A91: AR | B91: Architecture & Services | C91: ES | D91: LV Reticulation & Lighting Systems | E91: GENR | F91: Generator | I91: Product | J91: Non Linear | K91: No, with parent system | M91: =A91&"-"&R91 -> AR-ES-GENR-00 | N91: LV BU Generator | R91: =C91& "-" &E91 & IF(G91<>"","-" &G91,"-00") -> ES-GENR-00 | S91: =C91& "-" &E91 & IF(G91<>"","-" &G91,"") -> ES-GENR | T91: =VLOOKUP(S91,'[1]Asset Classifications'!$M$12:$M$1690,1,FALSE) -> ES-GENR
A92: AR | B92: Architecture & Services | C92: ES | D92: LV Reticulation & Lighting Systems | E92: GESB | F92: Generator Switch Board | I92: Product | J92: Non Linear | K92: No, with parent system | M92: =A92&"-"&R92 -> AR-ES-GESB-00 | N92: LV BU Generator SWBD | R92: =C92& "-" &E92 & IF(G92<>"","-" &G92,"-00") -> ES-GESB-00 | S92: =C92& "-" &E92 & IF(G92<>"","-" &G92,"") -> ES-GESB | T92: =VLOOKUP(S92,'[1]Asset Classifications'!$M$12:$M$1690,1,FALSE) -> ES-GESB | V92: from_v202002
A93: AR | B93: Architecture & Services | C93: ES | D93: LV Reticulation & Lighting Systems | E93: HFLT | F93: Harmonic Filter | I93: Product | J93: Non Linear | K93: No, with parent system | M93: =A93&"-"&R93 -> AR-ES-HFLT-00 | N93: LV Harmonic Filter | R93: =C93& "-" &E93 & IF(G93<>"","-" &G93,"-00") -> ES-HFLT-00 | S93: =C93& "-" &E93 & IF(G93<>"","-" &G93,"") -> ES-HFLT | T93: =VLOOKUP(S93,'[1]Asset Classifications'!$M$12:$M$1690,1,FALSE) -> ES-HFLT | V93: from_v202002
A94: AR | B94: Architecture & Services | C94: ES | D94: LV Reticulation & Lighting Systems | E94: HSSB | F94: Hydraulic Services Switch Board | I94: Product | J94: Non Linear | K94: No, with parent system | M94: =A94&"-"&R94 -> AR-ES-HSSB-00 | N94: Hydr Services SWBD | R94: =C94& "-" &E94 & IF(G94<>"","-" &G94,"-00") -> ES-HSSB-00 | S94: =C94& "-" &E94 & IF(G94<>"","-" &G94,"") -> ES-HSSB | T94: =VLOOKUP(S94,'[1]Asset Classifications'!$M$12:$M$1690,1,FALSE) -> ES-HSSB | V94: from_v202002
A95: AR | B95: Architecture & Services | C95: ES | D95: LV Reticulation & Lighting Systems | E95: INVR | F95: Inverter | I95: Product | J95: Non Linear | K95: No, with parent system | M95: =A95&"-"&R95 -> AR-ES-INVR-00 | N95: Inverter | R95: =C95& "-" &E95 & IF(G95<>"","-" &G95,"-00") -> ES-INVR-00 | S95: =C95& "-" &E95 & IF(G95<>"","-" &G95,"") -> ES-INVR | T95: =VLOOKUP(S95,'[1]Asset Classifications'!$M$12:$M$1690,1,FALSE) -> ES-INVR | V95: from_v202002
A96: AR | B96: Architecture & Services | C96: ES | D96: LV Reticulation & Lighting Systems | E96: LCMU | F96: Lighting Control Modular Unit | I96: Product | J96: Non Linear | K96: No, with parent system | M96: =A96&"-"&R96 -> AR-ES-LCMU-00 | N96: Lighting Control Un | R96: =C96& "-" &E96 & IF(G96<>"","-" &G96,"-00") -> ES-LCMU-00 | S96: =C96& "-" &E96 & IF(G96<>"","-" &G96,"") -> ES-LCMU | T96: =VLOOKUP(S96,'[1]Asset Classifications'!$M$12:$M$1690,1,FALSE) -> ES-LCMU | V96: from_v202002
A97: AR | B97: Architecture & Services | C97: ES | D97: LV Reticulation & Lighting Systems | E97: LGTF | F97: LV Lighting System | G97: BE | H97: Building-Emergency | I97: System | J97: Non Linear | K97: Yes, each system | L97: Buildings | M97: =A97&"-"&R97 -> AR-ES-LGTF-BE | N97: LV Light-Bldg Emer | R97: =C97& "-" &E97 & IF(G97<>"","-" &G97,"-00") -> ES-LGTF-BE | S97: =C97& "-" &E97 & IF(G97<>"","-" &G97,"") -> ES-LGTF-BE | T97: =VLOOKUP(S97,'[1]Asset Classifications'!$M$12:$M$1690,1,FALSE) -> ES-LGTF-BE
A98: AR | B98: Architecture & Services | C98: ES | D98: LV Reticulation & Lighting Systems | E98: LGTF | F98: LV Lighting System | G98: BG | H98: Building-General | I98: System | J98: Non Linear | K98: Yes, each system | L98: Buildings | M98: =A98&"-"&R98 -> AR-ES-LGTF-BG | N98: LV Light-Bldg Gen | R98: =C98& "-" &E98 & IF(G98<>"","-" &G98,"-00") -> ES-LGTF-BG | S98: =C98& "-" &E98 & IF(G98<>"","-" &G98,"") -> ES-LGTF-BG | T98: =VLOOKUP(S98,'[1]Asset Classifications'!$M$12:$M$1690,1,FALSE) -> ES-LGTF-BG
A99: AR | B99: Architecture & Services | C99: ES | D99: LV Reticulation & Lighting Systems | E99: LGTF | F99: LV Lighting System | G99: TE | H99: Tunnel-Emergency | I99: System | J99: Non Linear | K99: Yes, each system | L99: Infrastructure | M99: =A99&"-"&R99 -> AR-ES-LGTF-TE | N99: LV Light-Tunnel Emer | R99: =C99& "-" &E99 & IF(G99<>"","-" &G99,"-00") -> ES-LGTF-TE | S99: =C99& "-" &E99 & IF(G99<>"","-" &G99,"") -> ES-LGTF-TE | T99: =VLOOKUP(S99,'[1]Asset Classifications'!$M$12:$M$1690,1,FALSE) -> ES-LGTF-TE
A100: AR | B100: Architecture & Services | C100: ES | D100: LV Reticulation & Lighting Systems | E100: LGTF | F100: LV Lighting System | G100: TG | H100: Tunnel-General | I100: System | J100: Non Linear | K100: Yes, each system | L100: Infrastructure | M100: =A100&"-"&R100 -> AR-ES-LGTF-TG | N100: LV Light-Tunnel Gen | R100: =C100& "-" &E100 & IF(G100<>"","-" &G100,"-00") -> ES-LGTF-TG | S100: =C100& "-" &E100 & IF(G100<>"","-" &G100,"") -> ES-LGTF-TG | T100: =VLOOKUP(S100,'[1]Asset Classifications'!$M$12:$M$1690,1,FALSE) -> ES-LGTF-TG
...
