Workbook
Name Roles: #REF!
Name Roles: #REF!

Sheet Filename
A1: RBR file name content | AM1: Only EE and LT file name content
A2: Project name | F2: _ | G2: Originator/ Supplier/ Contractor | H2: _ | I2: Volume_System/Zone | L2: _ | M2: Location | N2: _ | O2: Document type | T2: _ | U2: Discipline code | AB2: _ | AC2: Project stage | AH2: _ | AI2: Number | AJ2: _ | AK2: Revision No. | AL2: _ | AM2: Drawing name | AN2: _ | AO2: Number of the buildings in the project | AP2: - | AQ2: Document's running number within the project
A3: EE file name relevant | C3: EE file name relevant | E3: EE file name relevant | O3: EE file name relevant | U3: EE file name relevant | AC3: EE file name relevant | AK3: EE file name relevant | AM3: EE file name relevant | AO3: LT file name relevant | AQ3: EE file name relevant
A4: LT file name relevant | C4: LT file name relevant | E4: LT file name relevant | O4: LT file name relevant | U4: LT file name relevant | AC4: LT file name relevant | AQ4: LT file name relevant
A5: PROJECT ID | B5: - | C5: SECTION ID | D5: - | E5: SUB-SECTION ID | G5: Abbreviation of the originator of the document Predefined list ORIGINATOR_SUPPLIER Provided by RB Rail AS | I5: VOLUME/SYSTEM | J5: - | K5: ZONE | M5: Code of the location. Predefined list LOCATION Provided by RB Rail AS | O5: Abbreviation of the document type. Predefined list DOCUMENT TYPE Provided by RB Rail AS | Q5: RBR document type | S5: EE document type | U5: RBR discipline | W5: RBR CODE | Y5: LOCAL CODE EHR | AA5: LOCAL CODE MNT | AC5: Stage Description | AE5: Stage Code RBR | AG5: Stage Code EE | AH5: _ | AI5: Unique ID number of each construction object 000001-999999 | AJ5: _ | AK5: Revision number 1-999 | AM5: Drawing name. No limitations. | AO5: Number of the buildings in the project. According to LST 1516:2015 | AQ5: Document's running number within the project According to LST 1516:2015 | AS5: LT RELEVANT | AZ5: EE and LT relevant
A6: Project name according to DTD TS Predefined list PROJECT ID Provided by RB Rail AS | C6: Section name according to DTD TS Predefined list SECTION ID Provided by RB Rail AS | E6: Sub-section name according to DTD TS Predefined list SUB-SECTION ID Provided by RB Rail AS | I6: Code of the volume/ system. Predefined list VOLUME_SYSTEM Provided by RB Rail AS | K6: Code of the zone. Predefined list ZONE Provided by RB Rail AS | Q6: RBR document type code Predefined list Provided by RB Rail AS | S6: EE document type code Predefined list Provided by RB Rail AS | U6: RBR discipline Predefined list Provided by RB Rail AS | W6: RBR discipline code Predefined list Provided by RB Rail AS | Y6: Discipline code according to local legislation Predefined list | AA6: Discipline code according to local legislation Predefined list | AC6: Abbreviation of the project stage. Predefined list PROJECT STAGE Provided by RB Rail AS | AE6: Abbreviation of the project stage. Predefined list PROJECT STAGE Provided by RB Rail AS | AG6: Abbreviation of the project stage. Predefined list PROJECT STAGE Provided by RB Rail AS | BA6: EE formatted
AY7: LT formatted | BA7: LT formatted
AS8: LT Project ID | AU8: LT Document type | AW8: LT Project Stage Code | AY8: Number of the building in the project | AZ8: Document's running number within the project | BC8: Preview of the EE EHR file name | BD8: Length of filename, charecters | BF8: Preview of the EE MNT file name | BG8: Length of filename, charecters | BI8: RBR file number | BJ8: Length of filename, charecters | BL8: RBR file number, with revision number (Only for IDOM) | BM8: Length of filename, charecters
A9: RBDTD-EE | B9: =IF(C9=0,"","-") -> - | C9: DS2 | D9: =IF(E9=0,"","-") -> - | E9: DPS1 | F9: =IF(G9=0,"","_") -> _ | G9: ATE | H9: =IF(I9=0,"","_") -> _ | I9: OS020001 | J9: =IF(K9=0,"","-") -> - | K9: ZZ | L9: =IF(M9=0,"","_") -> _ | M9: ZZZZ | N9: =IF(O9=0,"","_") -> _ | O9: Drawings of the position plan (external plane layouts), Site plan drawings | P9: =IF(Q9="","","-") -> - | Q9: =IF(O9="","",VLOOKUP(O9,'DOCUMENT TYPE'!$A$2:$D$805,2,)) -> D1 | R9: =IF(S9="","","-") -> - | S9: =IF(O9="","",VLOOKUP(O9,'DOCUMENT TYPE'!$A$2:$D$805,3,)) -> 4 | T9: =IF(U9=0,"","_") -> _ | U9: Bridge-Road | V9: =IF(W9="","","-") -> - | W9: =IF(U9="","",VLOOKUP(U9,'ACTIVITY & DISCIPLINE CODE'!$F$3:$I$1862,2,)) -> BR | X9: =IF(Y9="","","-") -> - | Y9: =IF(U9="","",VLOOKUP(U9,'ACTIVITY & DISCIPLINE CODE'!$F$3:$I$1862,3,)) -> TS | Z9: =IF(AA9="","","_") -> _ | AA9: =IF(U9="","",VLOOKUP(U9,'ACTIVITY & DISCIPLINE CODE'!$F$3:$I$1862,4,)) -> TS | AB9: =IF(AC9=0,"","_") -> _ | AC9: Construction | AD9: =IF(AE9="","","-") -> - | AE9: =IF(AC9="","",VLOOKUP(AC9,'PROJECT STAGE'!$A$2:$C$100,2,)) -> CO | AF9: =IF(AG9="","","_") -> _ | AG9: =IF(AC9="","",VLOOKUP(AC9,'PROJECT STAGE'!$A$2:$C$100,3,)) -> TJ | AH9: =IF(AI9="","","_") -> _ | AI9: 901 | AJ9: =IF(AK9="","","_") -> _ | AK9: 9 | AL9: =IF(AM9="","","_") -> _ | AM9: Notes-or-Drawing name | AN9: =IF(AO9=0,"","_") -> _ | AO9: 1 | AP9: =IF(AQ9="","","-") -> - | AQ9: 1 | AS9: =IF(A9="RBDTD-LT", "RBDTDLT","Not LT section__") -> Not LT section__ | AT9: =IF(AU9=0,"",".") -> . | AU9: =IF(O9=0,"No input data",INDEX('DOCUMENT TYPE'!D:D,MATCH(Filename!O9,'DOCUMENT TYPE'!A:A,0))) -> B | AV9: =IF(AW9=0,"","-") -> - | AW9: =IF(AC9="PD","PP",IF(AC9="MD","TP",IF(AC9="DTD","DP","Check PROJECT STAGE"))) -> Check PROJECT STAGE | AX9: =IF(AY9>"0","-","") -> - | AY9: =IF(AO9=0,"",TEXT(AO9,"00")) -> 01 | AZ9: =IF(BA9>"0","-","") -> - | BA9: =IF(AQ9=0,"",TEXT(AQ9,"00")) -> 01 | BC9: =IF(Y9="","Missing input data",IF(Y9="-","Missing input data",_xlfn.TEXTJOIN(,,C9,E9,I9,AF9,AG9,X9,Y9,R9:S9,AP9,(TEXT(AQ9,"00")),AJ9,(TEXT(AK9,"v00")),AL9:AM9))) -> DS2DPS1OS020001_TJ-TS-4-01_v09_Notes-or-Drawing name | BD9: =IF(Y9="","Missing input data",IF(Y9="-","Missing input data",LEN(BC9))) -> 52 | BF9: =IF(AA9="","Missing input data",IF(AA9="-","Missing input data",_xlfn.TEXTJOIN(,,C9,E9,I9,AF9,AG9,Z9,AA9,R9:S9,AP9,(TEXT(AQ9,"00")),AJ9,(TEXT(AK9,"v00")),AL9:AM9))) -> DS2DPS1OS020001_TJ_TS-4-01_v09_Notes-or-Drawing name | BG9: =IF(AA9="","Missing input data",IF(AA9="-","Missing input data",LEN(BF9))) -> 52 | BI9: =IF(W9="","Missing input data",IF(W9="-","Missing input data",_xlfn.TEXTJOIN(,,A9:N9,Q9,T9,W9,V9,Y9,AB9,AE9,AH9,(TEXT(AI9,"000000")),AL9:AM9))) -> RBDTD-EE-DS2-DPS1_ATE_OS020001-ZZ_ZZZZ_D1_BR-TS_CO_000901_Notes-or-Drawing name | BJ9: =IF(W9="","Missing input data",IF(W9="-","Missing input data",LEN(BI9))) -> 79 | BL9: =IF(W9="","Missing input data",IF(W9="-","Missing input data",_xlfn.TEXTJOIN(,,A9:N9,Q9,T9,W9,V9,Y9,AB9,AE9,AH9,(TEXT(AI9,"000000")),AJ9,(TEXT(AK9,"000"))))) -> RBDTD-EE-DS2-DPS1_ATE_OS020001-ZZ_ZZZZ_D1_BR-TS_CO_000901_009 | BM9: =IF(W9="","Missing input data",IF(W9="-","Missing input data",LEN(BL9))) -> 61
B10: =IF(C10=0,"","-") | D10: =IF(E10=0,"","-") | F10: =IF(G10=0,"","_") | H10: =IF(I10=0,"","_") | J10: =IF(K10=0,"","-") | L10: =IF(M10=0,"","_") | N10: =IF(O10=0,"","_") | P10: =IF(Q10="","","-") | Q10: =IF(O10="","",VLOOKUP(O10,'DOCUMENT TYPE'!$A$2:$D$805,2,)) | R10: =IF(S10="","","-") | S10: =IF(O10="","",VLOOKUP(O10,'DOCUMENT TYPE'!$A$2:$D$805,3,)) | T10: =IF(U10=0,"","_") | V10: =IF(W10="","","-") | W10: =IF(U10="","",VLOOKUP(U10,'ACTIVITY & DISCIPLINE CODE'!$F$3:$I$1862,2,)) | X10: =IF(Y10="","","-") | Y10: =IF(U10="","",VLOOKUP(U10,'ACTIVITY & DISCIPLINE CODE'!$F$3:$I$1862,3,)) | Z10: =IF(AA10="","","_") | AA10: =IF(U10="","",VLOOKUP(U10,'[1]ACTIVITY & DISCIPLINE CODE'!$F$3:$I$1850,4,)) | AB10: =IF(AC10=0,"","_") | AD10: =IF(AE10="","","-") | AE10: =IF(AC10="","",VLOOKUP(AC10,'PROJECT STAGE'!$A$2:$C$100,2,)) | AF10: =IF(AG10="","","_") | AG10: =IF(AC10="","",VLOOKUP(AC10,'PROJECT STAGE'!$A$2:$C$100,3,)) | AH10: =IF(AI10="","","_") | AJ10: =IF(AK10="","","_") | AL10: =IF(AM10="","","_") | AN10: =IF(AO10=0,"","_") -> _ | AO10: 2 | AP10: =IF(AQ10="","","-") | AS10: =IF(A10="RBDTD-LT", "RBDTDLT","Not LT section") -> Not LT section | AT10: =IF(AU10=0,"",".") -> . | AU10: =IF(O10=0,"No input data",INDEX('DOCUMENT TYPE'!D:D,MATCH(Filename!O10,'DOCUMENT TYPE'!A:A,0))) -> No input data | AV10: =IF(AW10=0,"","-") -> - | AW10: =IF(AC10="PD","PP",IF(AC10="MD","TP",IF(AC10="DTD","DP","Check PROJECT STAGE"))) -> Check PROJECT STAGE | AX10: =IF(AY10>"0","-","") -> - | AY10: =IF(AO10=0,"",TEXT(AO10,"00")) -> 02 | AZ10: =IF(BA10>"0","-","") | BA10: =IF(AQ10=0,"",TEXT(AQ10,"00")) | BC10: =IF(Y10="","Missing input data",IF(Y10="-","Missing input data",_xlfn.TEXTJOIN(,,C10,E10,I10,AF10,AG10,X10,Y10,R10:S10,AP10,(TEXT(AQ10,"00")),AJ10,(TEXT(AK10,"v00")),AL10:AM10))) -> Missing input data | BD10: =IF(Y10="","Missing input data",IF(Y10="-","Missing input data",LEN(BC10))) -> Missing input data | BF10: =IF(AA10="","Missing input data",IF(AA10="-","Missing input data",_xlfn.TEXTJOIN(,,C10,E10,I10,AF10,AG10,Z10,AA10,R10:S10,AP10,(TEXT(AQ10,"00")),AJ10,(TEXT(AK10,"v00")),AL10:AM10))) -> Missing input data | BG10: =IF(AA10="","Missing input data",IF(AA10="-","Missing input data",LEN(BF10))) -> Missing input data | BI10: =IF(W10="","Missing input data",IF(W10="-","Missing input data",_xlfn.TEXTJOIN(,,A10:N10,Q10,T10,W10,V10,Y10,AB10,AE10,AH10,(TEXT(AI10,"000000")),AL10:AM10))) -> Missing input data | BJ10: =IF(W10="","Missing input data",IF(W10="-","Missing input data",LEN(BI10))) -> Missing input data | BL10: =IF(W10="","Missing input data",IF(W10="-","Missing input data",_xlfn.TEXTJOIN(,,A10:N10,Q10,T10,W10,V10,Y10,AB10,AE10,AH10,(TEXT(AI10,"000000")),AJ10,(TEXT(AK10,"000"))))) -> Missing input data | BM10: =IF(W10="","Missing input data",IF(W10="-","Missing input data",LEN(BL10))) -> Missing input data
B11: =IF(C11=0,"","-") | D11: =IF(E11=0,"","-") | F11: =IF(G11=0,"","_") | H11: =IF(I11=0,"","_") | J11: =IF(K11=0,"","-") | L11: =IF(M11=0,"","_") | N11: =IF(O11=0,"","_") | P11: =IF(Q11="","","-") | Q11: =IF(O11="","",VLOOKUP(O11,'DOCUMENT TYPE'!$A$2:$D$805,2,)) | R11: =IF(S11="","","-") | S11: =IF(O11="","",VLOOKUP(O11,'DOCUMENT TYPE'!$A$2:$D$805,3,)) | T11: =IF(U11=0,"","_") | V11: =IF(W11="","","-") | W11: =IF(U11="","",VLOOKUP(U11,'ACTIVITY & DISCIPLINE CODE'!$F$3:$I$1862,2,)) | X11: =IF(Y11="","","-") | Y11: =IF(U11="","",VLOOKUP(U11,'ACTIVITY & DISCIPLINE CODE'!$F$3:$I$1862,3,)) | Z11: =IF(AA11="","","_") | AA11: =IF(U11="","",VLOOKUP(U11,'[1]ACTIVITY & DISCIPLINE CODE'!$F$3:$I$1850,4,)) | AB11: =IF(AC11=0,"","_") | AD11: =IF(AE11="","","-") | AE11: =IF(AC11="","",VLOOKUP(AC11,'PROJECT STAGE'!$A$2:$C$100,2,)) | AF11: =IF(AG11="","","_") | AG11: =IF(AC11="","",VLOOKUP(AC11,'PROJECT STAGE'!$A$2:$C$100,3,)) | AH11: =IF(AI11="","","_") | AJ11: =IF(AK11="","","_") | AL11: =IF(AM11="","","_") | AN11: =IF(AO11=0,"","_") | AP11: =IF(AQ11="","","-") | AS11: =IF(A11="RBDTD-LT", "RBDTDLT","Not LT section") -> Not LT section | AT11: =IF(AU11=0,"",".") -> . | AU11: =IF(O11=0,"No input data",INDEX('DOCUMENT TYPE'!D:D,MATCH(Filename!O11,'DOCUMENT TYPE'!A:A,0))) -> No input data | AV11: =IF(AW11=0,"","-") -> - | AW11: =IF(AC11="PD","PP",IF(AC11="MD","TP",IF(AC11="DTD","DP","Check PROJECT STAGE"))) -> Check PROJECT STAGE | AX11: =IF(AY11>"0","-","") | AY11: =IF(AO11=0,"",TEXT(AO11,"00")) | AZ11: =IF(BA11>"0","-","") | BA11: =IF(AQ11=0,"",TEXT(AQ11,"00")) | BC11: =IF(Y11="","Missing input data",IF(Y11="-","Missing input data",_xlfn.TEXTJOIN(,,C11,E11,I11,AF11,AG11,X11,Y11,R11:S11,AP11,(TEXT(AQ11,"00")),AJ11,(TEXT(AK11,"v00")),AL11:AM11))) -> Missing input data | BD11: =IF(Y11="","Missing input data",IF(Y11="-","Missing input data",LEN(BC11))) -> Missing input data | BF11: =IF(AA11="","Missing input data",IF(AA11="-","Missing input data",_xlfn.TEXTJOIN(,,C11,E11,I11,AF11,AG11,Z11,AA11,R11:S11,AP11,(TEXT(AQ11,"00")),AJ11,(TEXT(AK11,"v00")),AL11:AM11))) -> Missing input data | BG11: =IF(AA11="","Missing input data",IF(AA11="-","Missing input data",LEN(BF11))) -> Missing input data | BI11: =IF(W11="","Missing input data",IF(W11="-","Missing input data",_xlfn.TEXTJOIN(,,A11:N11,Q11,T11,W11,V11,Y11,AB11,AE11,AH11,(TEXT(AI11,"000000")),AL11:AM11))) -> Missing input data | BJ11: =IF(W11="","Missing input data",IF(W11="-","Missing input data",LEN(BI11))) -> Missing input data | BL11: =IF(W11="","Missing input data",IF(W11="-","Missing input data",_xlfn.TEXTJOIN(,,A11:N11,Q11,T11,W11,V11,Y11,AB11,AE11,AH11,(TEXT(AI11,"000000")),AJ11,(TEXT(AK11,"000"))))) -> Missing input data | BM11: =IF(W11="","Missing input data",IF(W11="-","Missing input data",LEN(BL11))) -> Missing input data
B12: =IF(C12=0,"","-") | D12: =IF(E12=0,"","-") | F12: =IF(G12=0,"","_") | H12: =IF(I12=0,"","_") | J12: =IF(K12=0,"","-") | L12: =IF(M12=0,"","_") | N12: =IF(O12=0,"","_") | P12: =IF(Q12="","","-") | Q12: =IF(O12="","",VLOOKUP(O12,'DOCUMENT TYPE'!$A$2:$D$805,2,)) | R12: =IF(S12="","","-") | S12: =IF(O12="","",VLOOKUP(O12,'DOCUMENT TYPE'!$A$2:$D$805,3,)) | T12: =IF(U12=0,"","_") | V12: =IF(W12="","","-") | W12: =IF(U12="","",VLOOKUP(U12,'ACTIVITY & DISCIPLINE CODE'!$F$3:$I$1862,2,)) | X12: =IF(Y12="","","-") | Y12: =IF(U12="","",VLOOKUP(U12,'ACTIVITY & DISCIPLINE CODE'!$F$3:$I$1862,3,)) | Z12: =IF(AA12="","","_") | AA12: =IF(U12="","",VLOOKUP(U12,'[1]ACTIVITY & DISCIPLINE CODE'!$F$3:$I$1850,4,)) | AB12: =IF(AC12=0,"","_") | AD12: =IF(AE12="","","-") | AE12: =IF(AC12="","",VLOOKUP(AC12,'PROJECT STAGE'!$A$2:$C$100,2,)) | AF12: =IF(AG12="","","_") | AG12: =IF(AC12="","",VLOOKUP(AC12,'PROJECT STAGE'!$A$2:$C$100,3,)) | AH12: =IF(AI12="","","_") | AJ12: =IF(AK12="","","_") | AL12: =IF(AM12="","","_") | AN12: =IF(AO12=0,"","_") | AP12: =IF(AQ12="","","-") | AS12: =IF(A12="RBDTD-LT", "RBDTDLT","Not LT section") -> Not LT section | AT12: =IF(AU12=0,"",".") -> . | AU12: =IF(O12=0,"No input data",INDEX('DOCUMENT TYPE'!D:D,MATCH(Filename!O12,'DOCUMENT TYPE'!A:A,0))) -> No input data | AV12: =IF(AW12=0,"","-") -> - | AW12: =IF(AC12="PD","PP",IF(AC12="MD","TP",IF(AC12="DTD","DP","Check PROJECT STAGE"))) -> Check PROJECT STAGE | AX12: =IF(AY12>"0","-","") | AY12: =IF(AO12=0,"",TEXT(AO12,"00")) | AZ12: =IF(BA12>"0","-","") | BA12: =IF(AQ12=0,"",TEXT(AQ12,"00")) | BC12: =IF(Y12="","Missing input data",IF(Y12="-","Missing input data",_xlfn.TEXTJOIN(,,C12,E12,I12,AF12,AG12,X12,Y12,R12:S12,AP12,(TEXT(AQ12,"00")),AJ12,(TEXT(AK12,"v00")),AL12:AM12))) -> Missing input data | BD12: =IF(Y12="","Missing input data",IF(Y12="-","Missing input data",LEN(BC12))) -> Missing input data | BF12: =IF(AA12="","Missing input data",IF(AA12="-","Missing input data",_xlfn.TEXTJOIN(,,C12,E12,I12,AF12,AG12,Z12,AA12,R12:S12,AP12,(TEXT(AQ12,"00")),AJ12,(TEXT(AK12,"v00")),AL12:AM12))) -> Missing input data | BG12: =IF(AA12="","Missing input data",IF(AA12="-","Missing input data",LEN(BF12))) -> Missing input data | BI12: =IF(W12="","Missing input data",IF(W12="-","Missing input data",_xlfn.TEXTJOIN(,,A12:N12,Q12,T12,W12,V12,Y12,AB12,AE12,AH12,(TEXT(AI12,"000000")),AL12:AM12))) -> Missing input data | BJ12: =IF(W12="","Missing input data",IF(W12="-","Missing input data",LEN(BI12))) -> Missing input data | BL12: =IF(W12="","Missing input data",IF(W12="-","Missing input data",_xlfn.TEXTJOIN(,,A12:N12,Q12,T12,W12,V12,Y12,AB12,AE12,AH12,(TEXT(AI12,"000000")),AJ12,(TEXT(AK12,"000"))))) -> Missing input data | BM12: =IF(W12="","Missing input data",IF(W12="-","Missing input data",LEN(BL12))) -> Missing input data
B13: =IF(C13=0,"","-") | D13: =IF(E13=0,"","-") | F13: =IF(G13=0,"","_") | H13: =IF(I13=0,"","_") | J13: =IF(K13=0,"","-") | L13: =IF(M13=0,"","_") | N13: =IF(O13=0,"","_") | P13: =IF(Q13="","","-") | Q13: =IF(O13="","",VLOOKUP(O13,'DOCUMENT TYPE'!$A$2:$D$805,2,)) | R13: =IF(S13="","","-") | S13: =IF(O13="","",VLOOKUP(O13,'DOCUMENT TYPE'!$A$2:$D$805,3,)) | T13: =IF(U13=0,"","_") | V13: =IF(W13="","","-") | W13: =IF(U13="","",VLOOKUP(U13,'ACTIVITY & DISCIPLINE CODE'!$F$3:$I$1862,2,)) | X13: =IF(Y13="","","-") | Y13: =IF(U13="","",VLOOKUP(U13,'ACTIVITY & DISCIPLINE CODE'!$F$3:$I$1862,3,)) | Z13: =IF(AA13="","","_") | AA13: =IF(U13="","",VLOOKUP(U13,'[1]ACTIVITY & DISCIPLINE CODE'!$F$3:$I$1850,4,)) | AB13: =IF(AC13=0,"","_") | AD13: =IF(AE13="","","-") | AE13: =IF(AC13="","",VLOOKUP(AC13,'PROJECT STAGE'!$A$2:$C$100,2,)) | AF13: =IF(AG13="","","_") | AG13: =IF(AC13="","",VLOOKUP(AC13,'PROJECT STAGE'!$A$2:$C$100,3,)) | AH13: =IF(AI13="","","_") | AJ13: =IF(AK13="","","_") | AL13: =IF(AM13="","","_") | AN13: =IF(AO13=0,"","_") | AP13: =IF(AQ13="","","-") | AS13: =IF(A13="RBDTD-LT", "RBDTDLT","Not LT section") -> Not LT section | AT13: =IF(AU13=0,"",".") -> . | AU13: =IF(O13=0,"No input data",INDEX('DOCUMENT TYPE'!D:D,MATCH(Filename!O13,'DOCUMENT TYPE'!A:A,0))) -> No input data | AV13: =IF(AW13=0,"","-") -> - | AW13: =IF(AC13="PD","PP",IF(AC13="MD","TP",IF(AC13="DTD","DP","Check PROJECT STAGE"))) -> Check PROJECT STAGE | AX13: =IF(AY13>"0","-","") | AY13: =IF(AO13=0,"",TEXT(AO13,"00")) | AZ13: =IF(BA13>"0","-","") | BA13: =IF(AQ13=0,"",TEXT(AQ13,"00")) | BC13: =IF(Y13="","Missing input data",IF(Y13="-","Missing input data",_xlfn.TEXTJOIN(,,C13,E13,I13,AF13,AG13,X13,Y13,R13:S13,AP13,(TEXT(AQ13,"00")),AJ13,(TEXT(AK13,"v00")),AL13:AM13))) -> Missing input data | BD13: =IF(Y13="","Missing input data",IF(Y13="-","Missing input data",LEN(BC13))) -> Missing input data | BF13: =IF(AA13="","Missing input data",IF(AA13="-","Missing input data",_xlfn.TEXTJOIN(,,C13,E13,I13,AF13,AG13,Z13,AA13,R13:S13,AP13,(TEXT(AQ13,"00")),AJ13,(TEXT(AK13,"v00")),AL13:AM13))) -> Missing input data | BG13: =IF(AA13="","Missing input data",IF(AA13="-","Missing input data",LEN(BF13))) -> Missing input data | BI13: =IF(W13="","Missing input data",IF(W13="-","Missing input data",_xlfn.TEXTJOIN(,,A13:N13,Q13,T13,W13,V13,Y13,AB13,AE13,AH13,(TEXT(AI13,"000000")),AL13:AM13))) -> Missing input data | BJ13: =IF(W13="","Missing input data",IF(W13="-","Missing input data",LEN(BI13))) -> Missing input data | BL13: =IF(W13="","Missing input data",IF(W13="-","Missing input data",_xlfn.TEXTJOIN(,,A13:N13,Q13,T13,W13,V13,Y13,AB13,AE13,AH13,(TEXT(AI13,"000000")),AJ13,(TEXT(AK13,"000"))))) -> Missing input data | BM13: =IF(W13="","Missing input data",IF(W13="-","Missing input data",LEN(BL13))) -> Missing input data
B14: =IF(C14=0,"","-") | D14: =IF(E14=0,"","-") | F14: =IF(G14=0,"","_") | H14: =IF(I14=0,"","_") | J14: =IF(K14=0,"","-") | L14: =IF(M14=0,"","_") | N14: =IF(O14=0,"","_") | P14: =IF(Q14="","","-") | Q14: =IF(O14="","",VLOOKUP(O14,'DOCUMENT TYPE'!$A$2:$D$805,2,)) | R14: =IF(S14="","","-") | S14: =IF(O14="","",VLOOKUP(O14,'DOCUMENT TYPE'!$A$2:$D$805,3,)) | T14: =IF(U14=0,"","_") | V14: =IF(W14="","","-") | W14: =IF(U14="","",VLOOKUP(U14,'ACTIVITY & DISCIPLINE CODE'!$F$3:$I$1862,2,)) | X14: =IF(Y14="","","-") | Y14: =IF(U14="","",VLOOKUP(U14,'ACTIVITY & DISCIPLINE CODE'!$F$3:$I$1862,3,)) | Z14: =IF(AA14="","","_") | AA14: =IF(U14="","",VLOOKUP(U14,'[1]ACTIVITY & DISCIPLINE CODE'!$F$3:$I$1850,4,)) | AB14: =IF(AC14=0,"","_") | AD14: =IF(AE14="","","-") | AE14: =IF(AC14="","",VLOOKUP(AC14,'PROJECT STAGE'!$A$2:$C$100,2,)) | AF14: =IF(AG14="","","_") | AG14: =IF(AC14="","",VLOOKUP(AC14,'PROJECT STAGE'!$A$2:$C$100,3,)) | AH14: =IF(AI14="","","_") | AJ14: =IF(AK14="","","_") | AL14: =IF(AM14="","","_") | AN14: =IF(AO14=0,"","_") | AP14: =IF(AQ14="","","-") | AS14: =IF(A14="RBDTD-LT", "RBDTDLT","Not LT section") -> Not LT section | AT14: =IF(AU14=0,"",".") -> . | AU14: =IF(O14=0,"No input data",INDEX('DOCUMENT TYPE'!D:D,MATCH(Filename!O14,'DOCUMENT TYPE'!A:A,0))) -> No input data | AV14: =IF(AW14=0,"","-") -> - | AW14: =IF(AC14="PD","PP",IF(AC14="MD","TP",IF(AC14="DTD","DP","Check PROJECT STAGE"))) -> Check PROJECT STAGE | AX14: =IF(AY14>"0","-","") | AY14: =IF(AO14=0,"",TEXT(AO14,"00")) | AZ14: =IF(BA14>"0","-","") | BA14: =IF(AQ14=0,"",TEXT(AQ14,"00")) | BC14: =IF(Y14="","Missing input data",IF(Y14="-","Missing input data",_xlfn.TEXTJOIN(,,C14,E14,I14,AF14,AG14,X14,Y14,R14:S14,AP14,(TEXT(AQ14,"00")),AJ14,(TEXT(AK14,"v00")),AL14:AM14))) -> Missing input data | BD14: =IF(Y14="","Missing input data",IF(Y14="-","Missing input data",LEN(BC14))) -> Missing input data | BF14: =IF(AA14="","Missing input data",IF(AA14="-","Missing input data",_xlfn.TEXTJOIN(,,C14,E14,I14,AF14,AG14,Z14,AA14,R14:S14,AP14,(TEXT(AQ14,"00")),AJ14,(TEXT(AK14,"v00")),AL14:AM14))) -> Missing input data | BG14: =IF(AA14="","Missing input data",IF(AA14="-","Missing input data",LEN(BF14))) -> Missing input data | BI14: =IF(W14="","Missing input data",IF(W14="-","Missing input data",_xlfn.TEXTJOIN(,,A14:N14,Q14,T14,W14,V14,Y14,AB14,AE14,AH14,(TEXT(AI14,"000000")),AL14:AM14))) -> Missing input data | BJ14: =IF(W14="","Missing input data",IF(W14="-","Missing input data",LEN(BI14))) -> Missing input data | BL14: =IF(W14="","Missing input data",IF(W14="-","Missing input data",_xlfn.TEXTJOIN(,,A14:N14,Q14,T14,W14,V14,Y14,AB14,AE14,AH14,(TEXT(AI14,"000000")),AJ14,(TEXT(AK14,"000"))))) -> Missing input data | BM14: =IF(W14="","Missing input data",IF(W14="-","Missing input data",LEN(BL14))) -> Missing input data
B15: =IF(C15=0,"","-") | D15: =IF(E15=0,"","-") | F15: =IF(G15=0,"","_") | H15: =IF(I15=0,"","_") | J15: =IF(K15=0,"","-") | L15: =IF(M15=0,"","_") | N15: =IF(O15=0,"","_") | P15: =IF(Q15="","","-") | Q15: =IF(O15="","",VLOOKUP(O15,'DOCUMENT TYPE'!$A$2:$D$805,2,)) | R15: =IF(S15="","","-") | S15: =IF(O15="","",VLOOKUP(O15,'DOCUMENT TYPE'!$A$2:$D$805,3,)) | T15: =IF(U15=0,"","_") | V15: =IF(W15="","","-") | W15: =IF(U15="","",VLOOKUP(U15,'ACTIVITY & DISCIPLINE CODE'!$F$3:$I$1862,2,)) | X15: =IF(Y15="","","-") | Y15: =IF(U15="","",VLOOKUP(U15,'ACTIVITY & DISCIPLINE CODE'!$F$3:$I$1862,3,)) | Z15: =IF(AA15="","","_") | AA15: =IF(U15="","",VLOOKUP(U15,'[1]ACTIVITY & DISCIPLINE CODE'!$F$3:$I$1850,4,)) | AB15: =IF(AC15=0,"","_") | AD15: =IF(AE15="","","-") | AE15: =IF(AC15="","",VLOOKUP(AC15,'PROJECT STAGE'!$A$2:$C$100,2,)) | AF15: =IF(AG15="","","_") | AG15: =IF(AC15="","",VLOOKUP(AC15,'PROJECT STAGE'!$A$2:$C$100,3,)) | AH15: =IF(AI15="","","_") | AJ15: =IF(AK15="","","_") | AL15: =IF(AM15="","","_") | AN15: =IF(AO15=0,"","_") | AP15: =IF(AQ15="","","-") | AS15: =IF(A15="RBDTD-LT", "RBDTDLT","Not LT section") -> Not LT section | AT15: =IF(AU15=0,"",".") -> . | AU15: =IF(O15=0,"No input data",INDEX('DOCUMENT TYPE'!D:D,MATCH(Filename!O15,'DOCUMENT TYPE'!A:A,0))) -> No input data | AV15: =IF(AW15=0,"","-") -> - | AW15: =IF(AC15="PD","PP",IF(AC15="MD","TP",IF(AC15="DTD","DP","Check PROJECT STAGE"))) -> Check PROJECT STAGE | AX15: =IF(AY15>"0","-","") | AY15: =IF(AO15=0,"",TEXT(AO15,"00")) | AZ15: =IF(BA15>"0","-","") | BA15: =IF(AQ15=0,"",TEXT(AQ15,"00")) | BC15: =IF(Y15="","Missing input data",IF(Y15="-","Missing input data",_xlfn.TEXTJOIN(,,C15,E15,I15,AF15,AG15,X15,Y15,R15:S15,AP15,(TEXT(AQ15,"00")),AJ15,(TEXT(AK15,"v00")),AL15:AM15))) -> Missing input data | BD15: =IF(Y15="","Missing input data",IF(Y15="-","Missing input data",LEN(BC15))) -> Missing input data | BF15: =IF(AA15="","Missing input data",IF(AA15="-","Missing input data",_xlfn.TEXTJOIN(,,C15,E15,I15,AF15,AG15,Z15,AA15,R15:S15,AP15,(TEXT(AQ15,"00")),AJ15,(TEXT(AK15,"v00")),AL15:AM15))) -> Missing input data | BG15: =IF(AA15="","Missing input data",IF(AA15="-","Missing input data",LEN(BF15))) -> Missing input data | BI15: =IF(W15="","Missing input data",IF(W15="-","Missing input data",_xlfn.TEXTJOIN(,,A15:N15,Q15,T15,W15,V15,Y15,AB15,AE15,AH15,(TEXT(AI15,"000000")),AL15:AM15))) -> Missing input data | BJ15: =IF(W15="","Missing input data",IF(W15="-","Missing input data",LEN(BI15))) -> Missing input data | BL15: =IF(W15="","Missing input data",IF(W15="-","Missing input data",_xlfn.TEXTJOIN(,,A15:N15,Q15,T15,W15,V15,Y15,AB15,AE15,AH15,(TEXT(AI15,"000000")),AJ15,(TEXT(AK15,"000"))))) -> Missing input data | BM15: =IF(W15="","Missing input data",IF(W15="-","Missing input data",LEN(BL15))) -> Missing input data
B16: =IF(C16=0,"","-") | D16: =IF(E16=0,"","-") | F16: =IF(G16=0,"","_") | H16: =IF(I16=0,"","_") | J16: =IF(K16=0,"","-") | L16: =IF(M16=0,"","_") | N16: =IF(O16=0,"","_") | P16: =IF(Q16="","","-") | Q16: =IF(O16="","",VLOOKUP(O16,'DOCUMENT TYPE'!$A$2:$D$805,2,)) | R16: =IF(S16="","","-") | S16: =IF(O16="","",VLOOKUP(O16,'DOCUMENT TYPE'!$A$2:$D$805,3,)) | T16: =IF(U16=0,"","_") | V16: =IF(W16="","","-") | W16: =IF(U16="","",VLOOKUP(U16,'ACTIVITY & DISCIPLINE CODE'!$F$3:$I$1862,2,)) | X16: =IF(Y16="","","-") | Y16: =IF(U16="","",VLOOKUP(U16,'ACTIVITY & DISCIPLINE CODE'!$F$3:$I$1862,3,)) | Z16: =IF(AA16="","","_") | AA16: =IF(U16="","",VLOOKUP(U16,'[1]ACTIVITY & DISCIPLINE CODE'!$F$3:$I$1850,4,)) | AB16: =IF(AC16=0,"","_") | AD16: =IF(AE16="","","-") | AE16: =IF(AC16="","",VLOOKUP(AC16,'PROJECT STAGE'!$A$2:$C$100,2,)) | AF16: =IF(AG16="","","_") | AG16: =IF(AC16="","",VLOOKUP(AC16,'PROJECT STAGE'!$A$2:$C$100,3,)) | AH16: =IF(AI16="","","_") | AJ16: =IF(AK16="","","_") | AL16: =IF(AM16="","","_") | AN16: =IF(AO16=0,"","_") | AP16: =IF(AQ16="","","-") | AS16: =IF(A16="RBDTD-LT", "RBDTDLT","Not LT section") -> Not LT section | AT16: =IF(AU16=0,"",".") -> . | AU16: =IF(O16=0,"No input data",INDEX('DOCUMENT TYPE'!D:D,MATCH(Filename!O16,'DOCUMENT TYPE'!A:A,0))) -> No input data | AV16: =IF(AW16=0,"","-") -> - | AW16: =IF(AC16="PD","PP",IF(AC16="MD","TP",IF(AC16="DTD","DP","Check PROJECT STAGE"))) -> Check PROJECT STAGE | AX16: =IF(AY16>"0","-","") | AY16: =IF(AO16=0,"",TEXT(AO16,"00")) | AZ16: =IF(BA16>"0","-","") | BA16: =IF(AQ16=0,"",TEXT(AQ16,"00")) | BC16: =IF(Y16="","Missing input data",IF(Y16="-","Missing input data",_xlfn.TEXTJOIN(,,C16,E16,I16,AF16,AG16,X16,Y16,R16:S16,AP16,(TEXT(AQ16,"00")),AJ16,(TEXT(AK16,"v00")),AL16:AM16))) -> Missing input data | BD16: =IF(Y16="","Missing input data",IF(Y16="-","Missing input data",LEN(BC16))) -> Missing input data | BF16: =IF(AA16="","Missing input data",IF(AA16="-","Missing input data",_xlfn.TEXTJOIN(,,C16,E16,I16,AF16,AG16,Z16,AA16,R16:S16,AP16,(TEXT(AQ16,"00")),AJ16,(TEXT(AK16,"v00")),AL16:AM16))) -> Missing input data | BG16: =IF(AA16="","Missing input data",IF(AA16="-","Missing input data",LEN(BF16))) -> Missing input data | BI16: =IF(W16="","Missing input data",IF(W16="-","Missing input data",_xlfn.TEXTJOIN(,,A16:N16,Q16,T16,W16,V16,Y16,AB16,AE16,AH16,(TEXT(AI16,"000000")),AL16:AM16))) -> Missing input data | BJ16: =IF(W16="","Missing input data",IF(W16="-","Missing input data",LEN(BI16))) -> Missing input data | BL16: =IF(W16="","Missing input data",IF(W16="-","Missing input data",_xlfn.TEXTJOIN(,,A16:N16,Q16,T16,W16,V16,Y16,AB16,AE16,AH16,(TEXT(AI16,"000000")),AJ16,(TEXT(AK16,"000"))))) -> Missing input data | BM16: =IF(W16="","Missing input data",IF(W16="-","Missing input data",LEN(BL16))) -> Missing input data
B17: =IF(C17=0,"","-") | D17: =IF(E17=0,"","-") | F17: =IF(G17=0,"","_") | H17: =IF(I17=0,"","_") | J17: =IF(K17=0,"","-") | L17: =IF(M17=0,"","_") | N17: =IF(O17=0,"","_") | P17: =IF(Q17="","","-") | Q17: =IF(O17="","",VLOOKUP(O17,'DOCUMENT TYPE'!$A$2:$D$805,2,)) | R17: =IF(S17="","","-") | S17: =IF(O17="","",VLOOKUP(O17,'DOCUMENT TYPE'!$A$2:$D$805,3,)) | T17: =IF(U17=0,"","_") | V17: =IF(W17="","","-") | W17: =IF(U17="","",VLOOKUP(U17,'ACTIVITY & DISCIPLINE CODE'!$F$3:$I$1862,2,)) | X17: =IF(Y17="","","-") | Y17: =IF(U17="","",VLOOKUP(U17,'ACTIVITY & DISCIPLINE CODE'!$F$3:$I$1862,3,)) | Z17: =IF(AA17="","","_") | AA17: =IF(U17="","",VLOOKUP(U17,'[1]ACTIVITY & DISCIPLINE CODE'!$F$3:$I$1850,4,)) | AB17: =IF(AC17=0,"","_") | AD17: =IF(AE17="","","-") | AE17: =IF(AC17="","",VLOOKUP(AC17,'PROJECT STAGE'!$A$2:$C$100,2,)) | AF17: =IF(AG17="","","_") | AG17: =IF(AC17="","",VLOOKUP(AC17,'PROJECT STAGE'!$A$2:$C$100,3,)) | AH17: =IF(AI17="","","_") | AJ17: =IF(AK17="","","_") | AL17: =IF(AM17="","","_") | AN17: =IF(AO17=0,"","_") | AP17: =IF(AQ17="","","-") | AS17: =IF(A17="RBDTD-LT", "RBDTDLT","Not LT section") -> Not LT section | AT17: =IF(AU17=0,"",".") -> . | AU17: =IF(O17=0,"No input data",INDEX('DOCUMENT TYPE'!D:D,MATCH(Filename!O17,'DOCUMENT TYPE'!A:A,0))) -> No input data | AV17: =IF(AW17=0,"","-") -> - | AW17: =IF(AC17="PD","PP",IF(AC17="MD","TP",IF(AC17="DTD","DP","Check PROJECT STAGE"))) -> Check PROJECT STAGE | AX17: =IF(AY17>"0","-","") | AY17: =IF(AO17=0,"",TEXT(AO17,"00")) | AZ17: =IF(BA17>"0","-","") | BA17: =IF(AQ17=0,"",TEXT(AQ17,"00")) | BC17: =IF(Y17="","Missing input data",IF(Y17="-","Missing input data",_xlfn.TEXTJOIN(,,C17,E17,I17,AF17,AG17,X17,Y17,R17:S17,AP17,(TEXT(AQ17,"00")),AJ17,(TEXT(AK17,"v00")),AL17:AM17))) -> Missing input data | BD17: =IF(Y17="","Missing input data",IF(Y17="-","Missing input data",LEN(BC17))) -> Missing input data | BF17: =IF(AA17="","Missing input data",IF(AA17="-","Missing input data",_xlfn.TEXTJOIN(,,C17,E17,I17,AF17,AG17,Z17,AA17,R17:S17,AP17,(TEXT(AQ17,"00")),AJ17,(TEXT(AK17,"v00")),AL17:AM17))) -> Missing input data | BG17: =IF(AA17="","Missing input data",IF(AA17="-","Missing input data",LEN(BF17))) -> Missing input data | BI17: =IF(W17="","Missing input data",IF(W17="-","Missing input data",_xlfn.TEXTJOIN(,,A17:N17,Q17,T17,W17,V17,Y17,AB17,AE17,AH17,(TEXT(AI17,"000000")),AL17:AM17))) -> Missing input data | BJ17: =IF(W17="","Missing input data",IF(W17="-","Missing input data",LEN(BI17))) -> Missing input data | BL17: =IF(W17="","Missing input data",IF(W17="-","Missing input data",_xlfn.TEXTJOIN(,,A17:N17,Q17,T17,W17,V17,Y17,AB17,AE17,AH17,(TEXT(AI17,"000000")),AJ17,(TEXT(AK17,"000"))))) -> Missing input data | BM17: =IF(W17="","Missing input data",IF(W17="-","Missing input data",LEN(BL17))) -> Missing input data
B18: =IF(C18=0,"","-") | D18: =IF(E18=0,"","-") | F18: =IF(G18=0,"","_") | H18: =IF(I18=0,"","_") | J18: =IF(K18=0,"","-") | L18: =IF(M18=0,"","_") | N18: =IF(O18=0,"","_") | P18: =IF(Q18="","","-") | Q18: =IF(O18="","",VLOOKUP(O18,'DOCUMENT TYPE'!$A$2:$D$805,2,)) | R18: =IF(S18="","","-") | S18: =IF(O18="","",VLOOKUP(O18,'DOCUMENT TYPE'!$A$2:$D$805,3,)) | T18: =IF(U18=0,"","_") | V18: =IF(W18="","","-") | W18: =IF(U18="","",VLOOKUP(U18,'ACTIVITY & DISCIPLINE CODE'!$F$3:$I$1862,2,)) | X18: =IF(Y18="","","-") | Y18: =IF(U18="","",VLOOKUP(U18,'ACTIVITY & DISCIPLINE CODE'!$F$3:$I$1862,3,)) | Z18: =IF(AA18="","","_") | AA18: =IF(U18="","",VLOOKUP(U18,'[1]ACTIVITY & DISCIPLINE CODE'!$F$3:$I$1850,4,)) | AB18: =IF(AC18=0,"","_") | AD18: =IF(AE18="","","-") | AE18: =IF(AC18="","",VLOOKUP(AC18,'PROJECT STAGE'!$A$2:$C$100,2,)) | AF18: =IF(AG18="","","_") | AG18: =IF(AC18="","",VLOOKUP(AC18,'PROJECT STAGE'!$A$2:$C$100,3,)) | AH18: =IF(AI18="","","_") | AJ18: =IF(AK18="","","_") | AL18: =IF(AM18="","","_") | AN18: =IF(AO18=0,"","_") | AP18: =IF(AQ18="","","-") | AS18: =IF(A18="RBDTD-LT", "RBDTDLT","Not LT section") -> Not LT section | AT18: =IF(AU18=0,"",".") -> . | AU18: =IF(O18=0,"No input data",INDEX('DOCUMENT TYPE'!D:D,MATCH(Filename!O18,'DOCUMENT TYPE'!A:A,0))) -> No input data | AV18: =IF(AW18=0,"","-") -> - | AW18: =IF(AC18="PD","PP",IF(AC18="MD","TP",IF(AC18="DTD","DP","Check PROJECT STAGE"))) -> Check PROJECT STAGE | AX18: =IF(AY18>"0","-","") | AY18: =IF(AO18=0,"",TEXT(AO18,"00")) | AZ18: =IF(BA18>"0","-","") | BA18: =IF(AQ18=0,"",TEXT(AQ18,"00")) | BC18: =IF(Y18="","Missing input data",IF(Y18="-","Missing input data",_xlfn.TEXTJOIN(,,C18,E18,I18,AF18,AG18,X18,Y18,R18:S18,AP18,(TEXT(AQ18,"00")),AJ18,(TEXT(AK18,"v00")),AL18:AM18))) -> Missing input data | BD18: =IF(Y18="","Missing input data",IF(Y18="-","Missing input data",LEN(BC18))) -> Missing input data | BF18: =IF(AA18="","Missing input data",IF(AA18="-","Missing input data",_xlfn.TEXTJOIN(,,C18,E18,I18,AF18,AG18,Z18,AA18,R18:S18,AP18,(TEXT(AQ18,"00")),AJ18,(TEXT(AK18,"v00")),AL18:AM18))) -> Missing input data | BG18: =IF(AA18="","Missing input data",IF(AA18="-","Missing input data",LEN(BF18))) -> Missing input data | BI18: =IF(W18="","Missing input data",IF(W18="-","Missing input data",_xlfn.TEXTJOIN(,,A18:N18,Q18,T18,W18,V18,Y18,AB18,AE18,AH18,(TEXT(AI18,"000000")),AL18:AM18))) -> Missing input data | BJ18: =IF(W18="","Missing input data",IF(W18="-","Missing input data",LEN(BI18))) -> Missing input data | BL18: =IF(W18="","Missing input data",IF(W18="-","Missing input data",_xlfn.TEXTJOIN(,,A18:N18,Q18,T18,W18,V18,Y18,AB18,AE18,AH18,(TEXT(AI18,"000000")),AJ18,(TEXT(AK18,"000"))))) -> Missing input data | BM18: =IF(W18="","Missing input data",IF(W18="-","Missing input data",LEN(BL18))) -> Missing input data
B19: =IF(C19=0,"","-") | D19: =IF(E19=0,"","-") | F19: =IF(G19=0,"","_") | H19: =IF(I19=0,"","_") | J19: =IF(K19=0,"","-") | L19: =IF(M19=0,"","_") | N19: =IF(O19=0,"","_") | P19: =IF(Q19="","","-") | Q19: =IF(O19="","",VLOOKUP(O19,'DOCUMENT TYPE'!$A$2:$D$805,2,)) | R19: =IF(S19="","","-") | S19: =IF(O19="","",VLOOKUP(O19,'DOCUMENT TYPE'!$A$2:$D$805,3,)) | T19: =IF(U19=0,"","_") | V19: =IF(W19="","","-") | W19: =IF(U19="","",VLOOKUP(U19,'ACTIVITY & DISCIPLINE CODE'!$F$3:$I$1862,2,)) | X19: =IF(Y19="","","-") | Y19: =IF(U19="","",VLOOKUP(U19,'ACTIVITY & DISCIPLINE CODE'!$F$3:$I$1862,3,)) | Z19: =IF(AA19="","","_") | AA19: =IF(U19="","",VLOOKUP(U19,'[1]ACTIVITY & DISCIPLINE CODE'!$F$3:$I$1850,4,)) | AB19: =IF(AC19=0,"","_") | AD19: =IF(AE19="","","-") | AE19: =IF(AC19="","",VLOOKUP(AC19,'PROJECT STAGE'!$A$2:$C$100,2,)) | AF19: =IF(AG19="","","_") | AG19: =IF(AC19="","",VLOOKUP(AC19,'PROJECT STAGE'!$A$2:$C$100,3,)) | AH19: =IF(AI19="","","_") | AJ19: =IF(AK19="","","_") | AL19: =IF(AM19="","","_") | AN19: =IF(AO19=0,"","_") | AP19: =IF(AQ19="","","-") | AS19: =IF(A19="RBDTD-LT", "RBDTDLT","Not LT section") -> Not LT section | AT19: =IF(AU19=0,"",".") -> . | AU19: =IF(O19=0,"No input data",INDEX('DOCUMENT TYPE'!D:D,MATCH(Filename!O19,'DOCUMENT TYPE'!A:A,0))) -> No input data | AV19: =IF(AW19=0,"","-") -> - | AW19: =IF(AC19="PD","PP",IF(AC19="MD","TP",IF(AC19="DTD","DP","Check PROJECT STAGE"))) -> Check PROJECT STAGE | AX19: =IF(AY19>"0","-","") | AY19: =IF(AO19=0,"",TEXT(AO19,"00")) | AZ19: =IF(BA19>"0","-","") | BA19: =IF(AQ19=0,"",TEXT(AQ19,"00")) | BC19: =IF(Y19="","Missing input data",IF(Y19="-","Missing input data",_xlfn.TEXTJOIN(,,C19,E19,I19,AF19,AG19,X19,Y19,R19:S19,AP19,(TEXT(AQ19,"00")),AJ19,(TEXT(AK19,"v00")),AL19:AM19))) -> Missing input data | BD19: =IF(Y19="","Missing input data",IF(Y19="-","Missing input data",LEN(BC19))) -> Missing input data | BF19: =IF(AA19="","Missing input data",IF(AA19="-","Missing input data",_xlfn.TEXTJOIN(,,C19,E19,I19,AF19,AG19,Z19,AA19,R19:S19,AP19,(TEXT(AQ19,"00")),AJ19,(TEXT(AK19,"v00")),AL19:AM19))) -> Missing input data | BG19: =IF(AA19="","Missing input data",IF(AA19="-","Missing input data",LEN(BF19))) -> Missing input data | BI19: =IF(W19="","Missing input data",IF(W19="-","Missing input data",_xlfn.TEXTJOIN(,,A19:N19,Q19,T19,W19,V19,Y19,AB19,AE19,AH19,(TEXT(AI19,"000000")),AL19:AM19))) -> Missing input data | BJ19: =IF(W19="","Missing input data",IF(W19="-","Missing input data",LEN(BI19))) -> Missing input data | BL19: =IF(W19="","Missing input data",IF(W19="-","Missing input data",_xlfn.TEXTJOIN(,,A19:N19,Q19,T19,W19,V19,Y19,AB19,AE19,AH19,(TEXT(AI19,"000000")),AJ19,(TEXT(AK19,"000"))))) -> Missing input data | BM19: =IF(W19="","Missing input data",IF(W19="-","Missing input data",LEN(BL19))) -> Missing input data
B20: =IF(C20=0,"","-") | D20: =IF(E20=0,"","-") | F20: =IF(G20=0,"","_") | H20: =IF(I20=0,"","_") | J20: =IF(K20=0,"","-") | L20: =IF(M20=0,"","_") | N20: =IF(O20=0,"","_") | P20: =IF(Q20="","","-") | Q20: =IF(O20="","",VLOOKUP(O20,'DOCUMENT TYPE'!$A$2:$D$805,2,)) | R20: =IF(S20="","","-") | S20: =IF(O20="","",VLOOKUP(O20,'DOCUMENT TYPE'!$A$2:$D$805,3,)) | T20: =IF(U20=0,"","_") | V20: =IF(W20="","","-") | W20: =IF(U20="","",VLOOKUP(U20,'ACTIVITY & DISCIPLINE CODE'!$F$3:$I$1862,2,)) | X20: =IF(Y20="","","-") | Y20: =IF(U20="","",VLOOKUP(U20,'ACTIVITY & DISCIPLINE CODE'!$F$3:$I$1862,3,)) | Z20: =IF(AA20="","","_") | AA20: =IF(U20="","",VLOOKUP(U20,'[1]ACTIVITY & DISCIPLINE CODE'!$F$3:$I$1850,4,)) | AB20: =IF(AC20=0,"","_") | AD20: =IF(AE20="","","-") | AE20: =IF(AC20="","",VLOOKUP(AC20,'PROJECT STAGE'!$A$2:$C$100,2,)) | AF20: =IF(AG20="","","_") | AG20: =IF(AC20="","",VLOOKUP(AC20,'PROJECT STAGE'!$A$2:$C$100,3,)) | AH20: =IF(AI20="","","_") | AJ20: =IF(AK20="","","_") | AL20: =IF(AM20="","","_") | AN20: =IF(AO20=0,"","_") | AP20: =IF(AQ20="","","-") | AS20: =IF(A20="RBDTD-LT", "RBDTDLT","Not LT section") -> Not LT section | AT20: =IF(AU20=0,"",".") -> . | AU20: =IF(O20=0,"No input data",INDEX('DOCUMENT TYPE'!D:D,MATCH(Filename!O20,'DOCUMENT TYPE'!A:A,0))) -> No input data | AV20: =IF(AW20=0,"","-") -> - | AW20: =IF(AC20="PD","PP",IF(AC20="MD","TP",IF(AC20="DTD","DP","Check PROJECT STAGE"))) -> Check PROJECT STAGE | AX20: =IF(AY20>"0","-","") | AY20: =IF(AO20=0,"",TEXT(AO20,"00")) | AZ20: =IF(BA20>"0","-","") | BA20: =IF(AQ20=0,"",TEXT(AQ20,"00")) | BC20: =IF(Y20="","Missing input data",IF(Y20="-","Missing input data",_xlfn.TEXTJOIN(,,C20,E20,I20,AF20,AG20,X20,Y20,R20:S20,AP20,(TEXT(AQ20,"00")),AJ20,(TEXT(AK20,"v00")),AL20:AM20))) -> Missing input data | BD20: =IF(Y20="","Missing input data",IF(Y20="-","Missing input data",LEN(BC20))) -> Missing input data | BF20: =IF(AA20="","Missing input data",IF(AA20="-","Missing input data",_xlfn.TEXTJOIN(,,C20,E20,I20,AF20,AG20,Z20,AA20,R20:S20,AP20,(TEXT(AQ20,"00")),AJ20,(TEXT(AK20,"v00")),AL20:AM20))) -> Missing input data | BG20: =IF(AA20="","Missing input data",IF(AA20="-","Missing input data",LEN(BF20))) -> Missing input data | BI20: =IF(W20="","Missing input data",IF(W20="-","Missing input data",_xlfn.TEXTJOIN(,,A20:N20,Q20,T20,W20,V20,Y20,AB20,AE20,AH20,(TEXT(AI20,"000000")),AL20:AM20))) -> Missing input data | BJ20: =IF(W20="","Missing input data",IF(W20="-","Missing input data",LEN(BI20))) -> Missing input data | BL20: =IF(W20="","Missing input data",IF(W20="-","Missing input data",_xlfn.TEXTJOIN(,,A20:N20,Q20,T20,W20,V20,Y20,AB20,AE20,AH20,(TEXT(AI20,"000000")),AJ20,(TEXT(AK20,"000"))))) -> Missing input data | BM20: =IF(W20="","Missing input data",IF(W20="-","Missing input data",LEN(BL20))) -> Missing input data
B21: =IF(C21=0,"","-") | D21: =IF(E21=0,"","-") | F21: =IF(G21=0,"","_") | H21: =IF(I21=0,"","_") | J21: =IF(K21=0,"","-") | L21: =IF(M21=0,"","_") | N21: =IF(O21=0,"","_") | P21: =IF(Q21="","","-") | Q21: =IF(O21="","",VLOOKUP(O21,'DOCUMENT TYPE'!$A$2:$D$805,2,)) | R21: =IF(S21="","","-") | S21: =IF(O21="","",VLOOKUP(O21,'DOCUMENT TYPE'!$A$2:$D$805,3,)) | T21: =IF(U21=0,"","_") | V21: =IF(W21="","","-") | W21: =IF(U21="","",VLOOKUP(U21,'ACTIVITY & DISCIPLINE CODE'!$F$3:$I$1862,2,)) | X21: =IF(Y21="","","-") | Y21: =IF(U21="","",VLOOKUP(U21,'ACTIVITY & DISCIPLINE CODE'!$F$3:$I$1862,3,)) | Z21: =IF(AA21="","","_") | AA21: =IF(U21="","",VLOOKUP(U21,'[1]ACTIVITY & DISCIPLINE CODE'!$F$3:$I$1850,4,)) | AB21: =IF(AC21=0,"","_") | AD21: =IF(AE21="","","-") | AE21: =IF(AC21="","",VLOOKUP(AC21,'PROJECT STAGE'!$A$2:$C$100,2,)) | AF21: =IF(AG21="","","_") | AG21: =IF(AC21="","",VLOOKUP(AC21,'PROJECT STAGE'!$A$2:$C$100,3,)) | AH21: =IF(AI21="","","_") | AJ21: =IF(AK21="","","_") | AL21: =IF(AM21="","","_") | AN21: =IF(AO21=0,"","_") | AP21: =IF(AQ21="","","-") | AS21: =IF(A21="RBDTD-LT", "RBDTDLT","Not LT section") -> Not LT section | AT21: =IF(AU21=0,"",".") -> . | AU21: =IF(O21=0,"No input data",INDEX('DOCUMENT TYPE'!D:D,MATCH(Filename!O21,'DOCUMENT TYPE'!A:A,0))) -> No input data | AV21: =IF(AW21=0,"","-") -> - | AW21: =IF(AC21="PD","PP",IF(AC21="MD","TP",IF(AC21="DTD","DP","Check PROJECT STAGE"))) -> Check PROJECT STAGE | AX21: =IF(AY21>"0","-","") | AY21: =IF(AO21=0,"",TEXT(AO21,"00")) | AZ21: =IF(BA21>"0","-","") | BA21: =IF(AQ21=0,"",TEXT(AQ21,"00")) | BC21: =IF(Y21="","Missing input data",IF(Y21="-","Missing input data",_xlfn.TEXTJOIN(,,C21,E21,I21,AF21,AG21,X21,Y21,R21:S21,AP21,(TEXT(AQ21,"00")),AJ21,(TEXT(AK21,"v00")),AL21:AM21))) -> Missing input data | BD21: =IF(Y21="","Missing input data",IF(Y21="-","Missing input data",LEN(BC21))) -> Missing input data | BF21: =IF(AA21="","Missing input data",IF(AA21="-","Missing input data",_xlfn.TEXTJOIN(,,C21,E21,I21,AF21,AG21,Z21,AA21,R21:S21,AP21,(TEXT(AQ21,"00")),AJ21,(TEXT(AK21,"v00")),AL21:AM21))) -> Missing input data | BG21: =IF(AA21="","Missing input data",IF(AA21="-","Missing input data",LEN(BF21))) -> Missing input data | BI21: =IF(W21="","Missing input data",IF(W21="-","Missing input data",_xlfn.TEXTJOIN(,,A21:N21,Q21,T21,W21,V21,Y21,AB21,AE21,AH21,(TEXT(AI21,"000000")),AL21:AM21))) -> Missing input data | BJ21: =IF(W21="","Missing input data",IF(W21="-","Missing input data",LEN(BI21))) -> Missing input data | BL21: =IF(W21="","Missing input data",IF(W21="-","Missing input data",_xlfn.TEXTJOIN(,,A21:N21,Q21,T21,W21,V21,Y21,AB21,AE21,AH21,(TEXT(AI21,"000000")),AJ21,(TEXT(AK21,"000"))))) -> Missing input data | BM21: =IF(W21="","Missing input data",IF(W21="-","Missing input data",LEN(BL21))) -> Missing input data
B22: =IF(C22=0,"","-") | D22: =IF(E22=0,"","-") | F22: =IF(G22=0,"","_") | H22: =IF(I22=0,"","_") | J22: =IF(K22=0,"","-") | L22: =IF(M22=0,"","_") | N22: =IF(O22=0,"","_") | P22: =IF(Q22="","","-") | Q22: =IF(O22="","",VLOOKUP(O22,'DOCUMENT TYPE'!$A$2:$D$805,2,)) | R22: =IF(S22="","","-") | S22: =IF(O22="","",VLOOKUP(O22,'DOCUMENT TYPE'!$A$2:$D$805,3,)) | T22: =IF(U22=0,"","_") | V22: =IF(W22="","","-") | W22: =IF(U22="","",VLOOKUP(U22,'ACTIVITY & DISCIPLINE CODE'!$F$3:$I$1862,2,)) | X22: =IF(Y22="","","-") | Y22: =IF(U22="","",VLOOKUP(U22,'ACTIVITY & DISCIPLINE CODE'!$F$3:$I$1862,3,)) | Z22: =IF(AA22="","","_") | AA22: =IF(U22="","",VLOOKUP(U22,'[1]ACTIVITY & DISCIPLINE CODE'!$F$3:$I$1850,4,)) | AB22: =IF(AC22=0,"","_") | AD22: =IF(AE22="","","-") | AE22: =IF(AC22="","",VLOOKUP(AC22,'PROJECT STAGE'!$A$2:$C$100,2,)) | AF22: =IF(AG22="","","_") | AG22: =IF(AC22="","",VLOOKUP(AC22,'PROJECT STAGE'!$A$2:$C$100,3,)) | AH22: =IF(AI22="","","_") | AJ22: =IF(AK22="","","_") | AL22: =IF(AM22="","","_") | AN22: =IF(AO22=0,"","_") | AP22: =IF(AQ22="","","-") | AS22: =IF(A22="RBDTD-LT", "RBDTDLT","Not LT section") -> Not LT section | AT22: =IF(AU22=0,"",".") -> . | AU22: =IF(O22=0,"No input data",INDEX('DOCUMENT TYPE'!D:D,MATCH(Filename!O22,'DOCUMENT TYPE'!A:A,0))) -> No input data | AV22: =IF(AW22=0,"","-") -> - | AW22: =IF(AC22="PD","PP",IF(AC22="MD","TP",IF(AC22="DTD","DP","Check PROJECT STAGE"))) -> Check PROJECT STAGE | AX22: =IF(AY22>"0","-","") | AY22: =IF(AO22=0,"",TEXT(AO22,"00")) | AZ22: =IF(BA22>"0","-","") | BA22: =IF(AQ22=0,"",TEXT(AQ22,"00")) | BC22: =IF(Y22="","Missing input data",IF(Y22="-","Missing input data",_xlfn.TEXTJOIN(,,C22,E22,I22,AF22,AG22,X22,Y22,R22:S22,AP22,(TEXT(AQ22,"00")),AJ22,(TEXT(AK22,"v00")),AL22:AM22))) -> Missing input data | BD22: =IF(Y22="","Missing input data",IF(Y22="-","Missing input data",LEN(BC22))) -> Missing input data | BF22: =IF(AA22="","Missing input data",IF(AA22="-","Missing input data",_xlfn.TEXTJOIN(,,C22,E22,I22,AF22,AG22,Z22,AA22,R22:S22,AP22,(TEXT(AQ22,"00")),AJ22,(TEXT(AK22,"v00")),AL22:AM22))) -> Missing input data | BG22: =IF(AA22="","Missing input data",IF(AA22="-","Missing input data",LEN(BF22))) -> Missing input data | BI22: =IF(W22="","Missing input data",IF(W22="-","Missing input data",_xlfn.TEXTJOIN(,,A22:N22,Q22,T22,W22,V22,Y22,AB22,AE22,AH22,(TEXT(AI22,"000000")),AL22:AM22))) -> Missing input data | BJ22: =IF(W22="","Missing input data",IF(W22="-","Missing input data",LEN(BI22))) -> Missing input data | BL22: =IF(W22="","Missing input data",IF(W22="-","Missing input data",_xlfn.TEXTJOIN(,,A22:N22,Q22,T22,W22,V22,Y22,AB22,AE22,AH22,(TEXT(AI22,"000000")),AJ22,(TEXT(AK22,"000"))))) -> Missing input data | BM22: =IF(W22="","Missing input data",IF(W22="-","Missing input data",LEN(BL22))) -> Missing input data
... B1000: =IF(C1000=0,"","-") | D1000: =IF(E1000=0,"","-") | F1000: =IF(G1000=0,"","_") | H1000: =IF(I1000=0,"","_") | J1000: =IF(K1000=0,"","-") | L1000: =IF(M1000=0,"","_") | N1000: =IF(O1000=0,"","_") | P1000: =IF(Q1000="","","-") | Q1000: =IF(O1000="","",VLOOKUP(O1000,'DOCUMENT TYPE'!$A$2:$D$805,2,)) | R1000: =IF(S1000="","","-") | S1000: =IF(O1000="","",VLOOKUP(O1000,'DOCUMENT TYPE'!$A$2:$D$805,3,)) | T1000: =IF(U1000=0,"","_") | V1000: =IF(W1000="","","-") | W1000: =IF(U1000="","",VLOOKUP(U1000,'ACTIVITY & DISCIPLINE CODE'!$F$3:$I$1862,2,)) | X1000: =IF(Y1000="","","-") | Y1000: =IF(U1000="","",VLOOKUP(U1000,'ACTIVITY & DISCIPLINE CODE'!$F$3:$I$1862,3,)) | Z1000: =IF(AA1000="","","_") | AA1000: =IF(U1000="","",VLOOKUP(U1000,'[1]ACTIVITY & DISCIPLINE CODE'!$F$3:$I$1850,4,)) | AB1000: =IF(AC1000=0,"","_") | AD1000: =IF(AE1000="","","-") | AE1000: =IF(AC1000="","",VLOOKUP(AC1000,'PROJECT STAGE'!$A$2:$C$100,2,)) | AF1000: =IF(AG1000="","","_") | AG1000: =IF(AC1000="","",VLOOKUP(AC1000,'PROJECT STAGE'!$A$2:$C$100,3,)) | AH1000: =IF(AI1000="","","_") | AJ1000: =IF(AK1000="","","_") | AL1000: =IF(AM1000="","","_") | AN1000: =IF(AO1000=0,"","_") | AP1000: =IF(AQ1000="","","-") | AS1000: =IF(A1000="RBDTD-LT", "RBDTDLT","Not LT section") -> Not LT section | AT1000: =IF(AU1000=0,"",".") -> . | AU1000: =IF(O1000=0,"No input data",INDEX('DOCUMENT TYPE'!D:D,MATCH(Filename!O1000,'DOCUMENT TYPE'!A:A,0))) -> No input data | AV1000: =IF(AW1000=0,"","-") -> - | AW1000: =IF(AC1000="PD","PP",IF(AC1000="MD","TP",IF(AC1000="DTD","DP","Check PROJECT STAGE"))) -> Check PROJECT STAGE | AX1000: =IF(AY1000>"0","-","") | AY1000: =IF(AO1000=0,"",TEXT(AO1000,"00")) | AZ1000: =IF(BA1000>"0","-","") | BA1000: =IF(AQ1000=0,"",TEXT(AQ1000,"00")) | BC1000: =IF(Y1000="","Missing input data",IF(Y1000="-","Missing input data",_xlfn.TEXTJOIN(,,C1000,E1000,I1000,AF1000,AG1000,X1000,Y1000,R1000:S1000,AP1000,(TEXT(AQ1000,"00")),AJ1000,(TEXT(AK1000,"v00")),AL1000:AM1000))) -> Missing input data | BD1000: =IF(Y1000="","Missing input data",IF(Y1000="-","Missing input data",LEN(BC1000))) -> Missing input data | BF1000: =IF(AA1000="","Missing input data",IF(AA1000="-","Missing input data",_xlfn.TEXTJOIN(,,C1000,E1000,I1000,AF1000,AG1000,Z1000,AA1000,R1000:S1000,AP1000,(TEXT(AQ1000,"00")),AJ1000,(TEXT(AK1000,"v00")),AL1000:AM1000))) -> Missing input data | BG1000: =IF(AA1000="","Missing input data",IF(AA1000="-","Missing input data",LEN(BF1000))) -> Missing input data | BI1000: =IF(W1000="","Missing input data",IF(W1000="-","Missing input data",_xlfn.TEXTJOIN(,,A1000:N1000,Q1000,T1000,W1000,V1000,Y1000,AB1000,AE1000,AH1000,(TEXT(AI1000,"000000")),AL1000:AM1000))) -> Missing input data | BJ1000: =IF(W1000="","Missing input data",IF(W1000="-","Missing input data",LEN(BI1000))) -> Missing input data | BL1000: =IF(W1000="","Missing input data",IF(W1000="-","Missing input data",_xlfn.TEXTJOIN(,,A1000:N1000,Q1000,T1000,W1000,V1000,Y1000,AB1000,AE1000,AH1000,(TEXT(AI1000,"000000")),AJ1000,(TEXT(AK1000,"000"))))) -> Missing input data | BM1000: =IF(W1000="","Missing input data",IF(W1000="-","Missing input data",LEN(BL1000))) -> Missing input data
D1001: =IF(E1001=0,"","-")
D1002: =IF(E1002=0,"","-")
D1003: =IF(E1003=0,"","-")
D1004: =IF(E1004=0,"","-")
D1005: =IF(E1005=0,"","-")
D1006: =IF(E1006=0,"","-")
D1007: =IF(E1007=0,"","-")
D1008: =IF(E1008=0,"","-")
D1009: =IF(E1009=0,"","-")
D1010: =IF(E1010=0,"","-")
D1011: =IF(E1011=0,"","-")
D1012: =IF(E1012=0,"","-")
... D1292: =IF(E1292=0,"","-")

Sheet PROJECT ID
A1: CODE | B1: DESCTIPTION
A2: RBDTD-EE | B2: Design section in Estonia

Sheet SECTION ID
A1: CODE | B1: DESCTIPTION
A2: ZZ | B2: No section
A3: DS2 | B3: Design section No.2
A4: SS | B4: Signaling subsystem section
A5: ES | B5: Energy subsystem section
B6: To be continued if required. Any code and description shall be agreed with the Client.

Sheet SUB-SECTION ID
A1: CODE | B1: DESCTIPTION
A2: ZZ | B2: No sub-section
A3: DPS1 | B3: Design Priority section No.1
A4: DPS2 | B4: Design Priority section No.2
A5: DPS3 | B5: Design Priority section No.3
B6: To be continued if required. Any code and description shall be agreed with the Client.

Sheet ORIGINATOR_SUPPLIER
A1: CODE | B1: NAME
A2: AFR | B2: Afry
A3: ALL | B3: Allspark
A4: ARD | B4: Ardanuy
A5: ATE | B5: Atemo OÜ
A6: ENS | B6: Enersense AS
A7: GRK | B7: GRK infra AS
A8: HPT | B8: Hepta Group Energy OÜ
A9: INF | B9: INF INFRA OÜ
A10: KKP | B10: Keskkonnaprojekt AS
A11: KMG | B11: KMG Inseneriehituse AS
A12: KPR | B12: K-Projekt (ET)
... A31: YIT | B31: AS YIT Eesti
B32: To be continued if required. Any code and description shall be agreed with the Client.

Sheet VOLUME_SYSTEM
A1: IN FORCE CODE | B1: MD CODE | C1: DTD | D1: RBR-Functional classification | E1: NAME / TYPE | F1: COUNTRY | G1: PD code | H1: PD Section | I1: Municipality | J1: WGS84 Long X Coordinate | K1: WGS84 Lat Y Coordinate | L1: Characteristics of Crossing / Road / Utility | M1: Affected party | N1: PD_km | O1: Type of data | P1: Date | Q1: Order | R1: Order with roads | U1: Archive | V1: New
A2: 000000 | B2: 000000 | E2: No Volume applicable | F2: EE | Q2: 1 | R2: 1
A3: BR0020 | B3: BR0020 | D3: CV-BR-RWBG-00 | E3: Bridge-Railway | F3: EE | H3: 3 | J3: 59.229465 | K3: 24.726774 | L3: Construction Object 01 - Railway Bridge - Kroodi stream RB (09-BR13, BR0020) | N3: 1+450 | O3: Bridge | Q3: 2 | R3: 2
A4: BR0022 | B4: BR0022 | D4: CV-BR-RWBG-00 | E4: Bridge-Railway | F4: EE | H4: 3 | J4: 59.465616 | K4: 24.979142 | L4: Construction Object 02 - Railway Bridge - Kroodi stream 1520 (BR0022) | N4: 1+450 | O4: Bridge | Q4: 3 | R4: 3
A5: BR0030 | B5: BR0030 | D5: CV-TU-TUNL-00 | E5: Tunnel | F5: EE | H5: 3 | J5: 59.452745 | K5: 24.980197 | L5: Construction Object 01 - Railway Tunnel Maardu (09-BR11, BR0030) | N5: 2+300 - 3+300 | O5: Tunnel | Q5: 4 | R5: 4
A6: BR0040 | B6: BR0040 | D6: CV-BR-UPSS-RD | E6: Underpass-Road | F6: EE | H6: 3 | J6: 59.446618 | K6: 24.925558 | L6: Construction Object 01 - Railway Bridge - T1 Tallinn-Narva Road (09-BR10, BR0040)/ Peterburi tee underpass | N6: 5+940 - 6+120 | O6: Underpass | Q6: 5 | R6: 5
A7: BR0050 | B7: BR0050 | D7: CV-BR-RWBG-00 | E7: Bridge-Railway | F7: EE | H7: 3 | J7: 59.213138 | K7: 24.740657 | L7: Construction Object 01 - Railway Bridge - Pirita River (09-BR08, BR0050) | N7: 7+390 - 7+500 | O7: Bridge | Q7: 6 | R7: 6
A8: BR0051 | B8: BR0051 | C8: BR0051 | D8: CV-BR-UPSS-PD | E8: Underpass-Pedestrian | F8: EE | H8: 1 | J8: 59.423326 | K8: 24.791768 | L8: Tunnel nr 5 | N8: -1+845 | O8: Underpass | Q8: 7 | R8: 7
A9: BR0053 | B9: BR0053 | D9: CV-BR-RWBG-00 | E9: Bridge-Railway | F9: EE | H9: 3 | J9: 59.435588 | K9: 24.926448 | L9: 1520 Pirita river bridge reconstruction | N9: 7+380 | O9: Bridge | P9: 25.07.2025 | Q9: 8 | R9: 8
A10: BR0055 | B10: BR0055 | D10: CV-BR-OPSS-RD | E10: Overpass-Road | F10: EE | H10: 1 | J10: 59.421277 | K10: 24.84155 | L10: Smuuli overpass | N10: 0+993 | O10: Overpass | Q10: 9 | R10: 9
A11: BR0060 | B11: BR0060 | D11: CV-TU-TUNL-00 | E11: Tunnel | F11: EE | H11: 1 | J11: 59.409778 | K11: 24.910953 | L11: Construction Object 01 - Railway Tunnel - 1520 Tracks & 11290 Tallinn-Lagedi Road (09-BR04, BR0060) | N11: 10+200 - 11+595 | O11: Tunnel | Q11: 10 | R11: 10
A12: BR0070 | B12: BR0070 | D12: CV-BR-OPSS-RD | E12: Overpass-Road | F12: EE | H12: 1 | J12: 59.465595 | K12: 24.978824 | L12: Overpass 11290 Tallinn-Lagedi | N12: 5+054 | O12: Overpass | Q12: 11 | R12: 11
A13: BR0075 | B13: BR0075 | D13: CV-BR-RWBG-00 | E13: Bridge-Railway | F13: EE | H13: 1 | J13: 59.465616 | K13: 24.979142 | L13: Vaskjala Ülemiste water channel bridge | N13: 8+624 | O13: Bridge | Q13: 12 | R13: 12
A14: BR0130 | B14: BR0130 | D14: CV-BR-RWBG-00 | E14: Bridge-Railway | F14: EE | H14: 1 | J14: 59.362144 | K14: 24.788934 | L14: Railway Bridge Kurnaoja Road & Kurna stream | M14: Noise barrier asociated to road | N14: 15+494 | O14: Bridge | Q14: 13 | R14: 13
A15: BR0143 | C15: BR0143 | D15: CV-BR-OPSS-RW | E15: Overpass-Railway | F15: EE | H15: 2 | J15: 59.268391 | K15: 24.693406 | L15: Männiku Pileslab 1 | N15: 2+042-3+132 | O15: Overpass | Q15: 14 | R15: 14
A16: BR0146 | C16: BR0146 | D16: CV-BR-OPSS-RW | E16: Overpass-Railway | F16: EE | H16: 2 | J16: 59.25627 | K16: 24.699371 | L16: Männiku Pileslab 2 | N16: 4+250-6+042 | O16: Overpass | Q16: 15 | R16: 15
A17: BR0150 | C17: BR0150 | D17: CV-BR-OPSS-RD | E17: Overpass-Road | F17: EE | H17: 2 | J17: 59.312248 | K17: 24.736272 | L17: Saustinõmme overpass | N17: 6+265 | O17: Overpass | Q17: 16 | R17: 16
A18: BR0160 | B18: BR0160 | D18: CV-BR-RWBG-00 | E18: Bridge-Railway | F18: EE | H18: 2 | J18: 59.435373 | K18: 24.927118 | L18: New Vääna River Bridge | N18: 9+446 | O18: Bridge | Q18: 17 | R18: 17
A19: BR0165 | B19: BR0165 | D19: CV-BR-RWBG-00 | E19: Bridge-Railway | F19: EE | H19: 2 | J19: 59.423326 | K19: 24.791768 | L19: Old Vääna River Bridge | N19: 9+811 | O19: Bridge | Q19: 18 | R19: 18
A20: BR0170 | B20: BR0170 | D20: CV-BR-UPSS-RD | E20: Underpass-Road | F20: EE | H20: 2 | J20: 59.287252 | K20: 24.69577 | L20: Railway Bridge Soo Road | N20: 9+943 | O20: Bridge | Q20: 19 | R20: 19
A21: BR0230 | B21: BR0230 | D21: CV-BR-OPSS-RD | E21: Overpass-Road | F21: EE | H21: 3 | J21: 59.229896 | K21: 24.727629 | L21: Construction Object 02 - Road Bridge - Altmetsa Road (BR0230) | N21: 1+120 | O21: Overpass | Q21: 20 | R21: 20
A22: BR0235 | B22: BR0235 | D22: CV-BR-OPSS-RD | E22: Overpass-Road | F22: EE | H22: 3 | J22: 59.455088 | K22: 24.980685 | L22: Kroodi I overpass | N22: 2+496 | O22: Overpass | Q22: 21 | R22: 21
A23: BR0240 | B23: BR0240 | D23: CV-BR-UPSS-PD | E23: Underpass-Pedestrian | F23: EE | H23: 3 | J23: 59.215059 | K23: 24.736166 | L23: Construction Object 02 - Road Underpass - Nehatu Road (08-BR09, BR0240) | N23: 6+420 | O23: Underpass | Q23: 22 | R23: 22
A24: BR0250 | B24: BR0250 | D24: CV-BR-OPSS-RD | E24: Overpass-Road | F24: EE | H24: 3 | J24: 59.425401 | K24: 24.920653 | L24: Väo overpass | N24: 8+613 | O24: Overpass | Q24: 23 | R24: 23
A25: BR0256 | B25: BR0256 | D25: CV-BR-OPSS-RD | E25: Overpass-Road | F25: EE | H25: 3 | J25: 59.481312 | K25: 24.973026 | L25: Construction Object 02 - Veneküla overpass - (09-BR05, BR0256) | N25: 9+500 | O25: Overpass | Q25: 24 | R25: 24
A26: BR0258 | B26: BR0258 | D26: CV-BR-OPSS-RD | E26: Overpass-Road | F26: EE | H26: 3 | J26: 59.414407 | K26: 24.90819 | L26: Varivere Road over 1520 Railway Line | N26: 2+260 | O26: Overpass | Q26: 25 | R26: 25
A27: BR0260 | B27: BR0260 | D27: CV-BR-OPSS-RD | E27: Overpass-Road | F27: EE | H27: 3 | J27: 59.214532 | K27: 24.735149 | L27: Construction Object 02 - Road overpass - Varivere Road (09-BR05, BR0260) /Lepiku overpass | N27: 10+080 | O27: Overpass | Q27: 26 | R27: 26
A28: BR0280 | B28: BR0280 | C28: BR0280 | D28: CV-BR-OPSS-RD | E28: Overpass-Road | F28: EE | H28: 1 | J28: 59.377591 | K28: 24.894526 | L28: Overpass 11113 Assaku_Jüri | N28: 9+154 | O28: Overpass | Q28: 27 | R28: 27
A29: BR0290 | B29: BR0290 | D29: CV-BR-OPSS-RD | E29: Overpass-Road | F29: EE | H29: 1 | J29: 59.341171 | K29: 24.762322 | L29: Overpass 11330 Järveküla-Jüri | N29: 11+236 | O29: Overpass | Q29: 28 | R29: 28
A30: BR0300 | B30: BR0300 | D30: CV-BR-OPSS-RD | E30: Overpass-Road | F30: EE | H30: 1 | J30: 59.288346 | K30: 24.696555 | L30: Overpass T2 Tallinn-Tartu-Võru-Luhamaa | N30: 11+483 | O30: Overpass | Q30: 29 | R30: 29
A31: BR0310 | B31: BR0310 | D31: CV-BR-OPSS-RD | E31: Overpass-Road | F31: EE | H31: 1 | J31: 59.455088 | K31: 24.980685 | L31: Overpass Rukki Local Road | N31: 11+665 | O31: Overpass | Q31: 30 | R31: 30
A32: BR0320 | B32: BR0320 | D32: CV-BR-OPSS-RD | E32: Overpass-Road | F32: EE | H32: 1 | J32: 59.443397 | K32: 24.92445 | L32: Uuesalu Overpass / Põdra Local Road | N32: 13+650 | O32: Overpass | Q32: 31 | R32: 31
A33: BR0345 | B33: BR0345 | D33: CV-BR-OPSS-RD | E33: Overpass-Road | F33: EE | H33: 2 | J33: 59.425401 | K33: 24.920653 | L33: Overpass T15 Tallinn-Rapla-Türi (08-BR11c) | M33: ON HOLD | N33: 0+742 | O33: Overpass | Q33: 32 | R33: 32
A34: BR0347 | C34: BR0347 | D34: CV-BR-OPSS-RD | E34: Overpass-Road | F34: EE | H34: 2 | J34: 59.357542 | K34: 24.768641 | L34: Raudalu overpass | M34: BR0350 | N34: 0+863 | O34: Overpass | Q34: 33 | R34: 33
A35: BR0350 | B35: BR0350 | D35: CV-BR-OPSS-RD | E35: Overpass-Road | F35: EE | H35: 2 | J35: 59.419025 | K35: 24.912046 | L35: Overpass T15 Tallinn-Rapla-Türi (08-BR11a) | N35: 1+496 | O35: Overpass | Q35: 34 | R35: 34
A36: BR0360 | B36: BR0360 | D36: CV-BR-OPSS-RD | E36: Overpass-Road | F36: EE | H36: 2 | J36: 59.414407 | K36: 24.90819 | L36: Overpass 11342 Saku-Tõdva | N36: 11+462 | O36: Overpass | Q36: 35 | R36: 35
A37: BR0370 | B37: BR0370 | D37: CV-BR-OPSS-RD | E37: Overpass-Road | F37: EE | H37: 2 | J37: 59.369927 | K37: 24.856713 | L37: Overpass 11240 Tõdva-Hageri | N37: 13+518 | O37: Overpass | Q37: 36 | R37: 36
A38: BR0380 | B38: BR0380 | D38: CV-BR-OPSS-RD | E38: Overpass-Road | F38: EE | H38: 2 | J38: 59.367668 | K38: 24.819121 | L38: Overpass 11152 Kirdalu-Kiisa | N38: 16+244 | O38: Overpass | Q38: 37 | R38: 37
A39: BR0390 | B39: BR0390 | D39: CV-BR-OPSS-RD | E39: Overpass-Road | F39: EE | H39: 2 | J39: 59.357542 | K39: 24.768641 | L39: Overpass 11154 Tagadi-Kurtna | N39: 16+986 | O39: Overpass | Q39: 38 | R39: 38
A40: BR0543 | B40: BR0543 | D40: CV-BR-OPSS-PD | E40: Overpass-Pedestrian | F40: EE | H40: 2 | J40: 59.421028 | K40: 24.842346 | L40: Overpass Pedestrian crossing (08-BR11b) | N40: 1+020 | O40: Overpass | Q40: 39 | R40: 39
A41: BR0545 | B41: BR0545 | D41: CV-BR-OPSS-PD | E41: Overpass-Pedestrian | F41: EE | H41: 2 | J41: 59.34821 | K41: 24.766495 | L41: Overpass Pedestrian crossing (08-BR10) | N41: 1+760 | O41: Overpass | Q41: 40 | R41: 40
A42: BR0547 | B42: BR0547 | D42: CV-BR-UPSS-PD | E42: Underpass-Pedestrian | F42: EE | H42: 2 | J42: 59.234395 | K42: 24.72237 | L42: Pedestrian Underpass | M42: This underpass is associated to the pedestrian path above (VD-001). | N42: 1+677 | O42: Underpass | Q42: 41 | R42: 41
A43: BR0550 | B43: BR0550 | D43: CV-BR-OPSS-PD | E43: Overpass-Pedestrian | F43: EE | H43: 2 | J43: 59.335756 | K43: 24.761048 | L43: Overpass between Luige Station platforms | N43: 3+205 | O43: Overpass | Q43: 42 | R43: 42 | T43: x | U43: x
A44: BR0560 | B44: BR0560 | D44: CV-BR-OPSS-PD | E44: Overpass-Pedestrian | F44: EE | H44: 2 | J44: 59.309268 | K44: 24.729427 | L44: Overpass Jäätmehoidla pedestrian crossing | N44: 6+800 | O44: Overpass | Q44: 43 | R44: 43
A45: BR0570 | B45: BR0570 | D45: CV-BR-UPSS-PD | E45: Underpass-Pedestrian | F45: EE | H45: 2 | J45: 59.298231 | K45: 24.707092 | L45: Underpass Viimsi Metskond pedestrian crossing | N45: 8+550 | O45: Underpass | Q45: 44 | R45: 44
A46: BR0585 | B46: BR0585 | D46: CV-BR-UPSS-PD | E46: Underpass-Pedestrian | F46: EE | H46: 2 | J46: 59.232394 | K46: 24.724191 | L46: Underpass between Kurtna Station platforms | N46: 16+493 | O46: Underpass | Q46: 45 | R46: 45 | T46: x | U46: x
A47: BR0590 | B47: BR0590 | D47: CV-BR-UPSS-PD | E47: Underpass-Pedestrian | F47: EE | H47: 2 | J47: 59.229899 | K47: 24.726494 | L47: Underpass Koosi pedestrian crossing | N47: 16+796 | O47: Underpass | Q47: 46 | R47: 46
A48: BR0685 | B48: BR0685 | D48: CV-BR-OPSS-WL | E48: Overpass-Wildlife | F48: EE | H48: 1 | J48: 59.373557 | K48: 24.879981 | L48: Rae Green bridge NEW | N48: 10+100 | O48: Ecoduct | Q48: 47 | R48: 47
A49: BR0750 | B49: BR0750 | D49: CV-BR-OPSS-WL | E49: Overpass-Wildlife | F49: EE | H49: 2 | J49: 59.298238 | K49: 24.707092 | L49: Saustinõmme Ecoduct | N49: 7+500 | O49: Ecoduct | Q49: 48 | R49: 48
A50: BR0760 | B50: BR0760 | D50: CV-BR-OPSS-WL | E50: Overpass-Wildlife | F50: EE | H50: 2 | J50: 59.373543 | K50: 24.879981 | L50: Kiisa Ecoduct | N50: 14+639 | O50: Ecoduct | Q50: 49 | R50: 49
A51: BR0790 | B51: BR0790 | D51: CV-BR-OPSS-WL | E51: Overpass-Wildlife | F51: EE | H51: 2 | J51: 59.305119 | K51: 24.719848 | L51: Tagadi Ecoduct | N51: 18+385 | O51: Ecoduct | Q51: 50 | R51: 50
A52: BR0880 | B52: BR0880 | D52: CV-BR-OPSS-UT | E52: Overpass-Utilities | F52: EE | H52: 1 | J52: 59.370577 | K52: 24.861379 | L52: Elveso Water System Overpass km 11+250 | N52: 11+208 | O52: Overpass | Q52: 51 | R52: 51
A53: BR0900 | B53: BR0900 | D53: CV-BR-OPSS-UT | E53: Overpass-Utilities | F53: EE | H53: 1 | J53: 59.369507 | K53: 24.853897 | L53: Water System Overpass km 11+650 | N53: 11+650 | O53: Overpass | Q53: 52 | R53: 52
A54: BR0920 | B54: BR0920 | D54: CV-BR-OPSS-UT | E54: Overpass-Utilities | F54: EE | H54: 1 | J54: 59.367478 | K54: 24.815609 | L54: Water System Overpass km 13+849 | N54: 13+850 | O54: Overpass | Q54: 53 | R54: 53
A55: CU0010 | B55: CU0010 | D55: CV-DR-CULV-W1 | E55: Culvert-Railway-Small Animals-water | F55: EE | H55: 3 | J55: 59.470291 | K55: 24.973799 | L55: Culvert 09-CU14 | N55: 0+737 | O55: Culvert | Q55: 54 | R55: 54
A56: CU003001 | B56: CU003001 | D56: CV-DR-CULV-RD | E56: Culvert-Road | F56: EE | H56: 3 | J56: 59.452995 | K56: 24.982836 | L56: Kroodi stream road culvert | N56: 2+720 | O56: Culvert | P56: 25.07.2025 | Q56: 55 | R56: 55
A57: CU007002 | C57: CU007002 | D57: CV-DR-CULV-RD | E57: Culvert-Road | F57: EE | H57: 1 | J57: 59.409612 | K57: 24.908691 | L57: Culvert | M57: OR007016 | N57: 4+900 | O57: Culvert | Q57: 56 | R57: 56
A58: CU007003 | B58: CU007003 | D58: CV-DR-CULV-RD | E58: Culvert-Road | F58: EE | H58: 1 | J58: 59.408886 | K58: 24.911588 | L58: Culvert - d1000 | M58: OR007001 | N58: 5+358 | O58: Culvert | Q58: 57 | R58: 57
A59: CU007004 | B59: CU007004 | D59: CV-DR-CULV-RD | E59: Culvert-Road | F59: EE | H59: 1 | J59: 59.413479 | K59: 24.903056 | L59: Culvert - d1000 | M59: OR007002 | N59: 4+666 | O59: Culvert | Q59: 58 | R59: 58
A60: CU007006 | B60: CU007006 | D60: CV-DR-CULV-RD | E60: Culvert-Road | F60: EE | H60: 1 | J60: 59.413307 | K60: 24.903422 | L60: Road culvert | M60: OR007006 | N60: 4+696 | O60: Culvert | Q60: 59 | R60: 59
A61: CU007008 | C61: CU007008 | D61: CV-DR-CULV-RD | E61: Culvert-Road | F61: EE | H61: 1 | J61: 59.40982 | K61: 24.908655 | L61: Culvert | M61: OR007012 | N61: 5+200 | O61: Culvert | Q61: 60 | R61: 60
A62: CU007010 | B62: CU007010 | D62: CV-DR-CULV-RD | E62: Culvert-Road | F62: EE | H62: 1 | J62: 59.35777 | K62: 24.771323 | L62: Culvert | M62: OR007010 | N62: 4+250 | O62: Culvert | Q62: 61 | R62: 61
A63: CU007012 | C63: CU007012 | D63: CV-DR-CULV-RD | E63: Culvert-Road | F63: EE | H63: 1 | J63: 59.408693 | K63: 24.909812 | L63: Road culvert | M63: OR007016 | N63: 5+345 | O63: Culvert | Q63: 62 | R63: 62 | T63: x | U63: x
A64: CU007013 | C64: CU007013 | D64: CV-DR-CULV-RD | E64: Culvert-Road | F64: EE | J64: 59.385743 | K64: 24.927617 | L64: Road culvert | N64: 7+600 | O64: Culvert | Q64: 63 | R64: 63
A65: CU007014 | C65: CU007014 | D65: CV-DR-CULV-RD | E65: Culvert-Road | F65: EE | H65: 1 | J65: 59.403248 | K65: 24.911122 | L65: Road culvert | M65: OR007016 | N65: 5+964 | O65: Culvert | Q65: 64 | R65: 64 | T65: x | U65: x
A66: CU017001 | C66: CU017001 | D66: CV-DR-CULV-00 | E66: Culvert-Drainage | F66: EE | H66: 2 | J66: 59.285255 | K66: 24.695298 | L66: Culvert | M66: ME0766 | N66: 10+163 | O66: Culvert | Q66: 65 | R66: 65
A67: CU017002 | C67: CU017002 | D67: CV-DR-CULV-00 | E67: Culvert-Drainage | F67: EE | H67: 2 | J67: 59.285416 | K67: 24.694108 | L67: Culvert | M67: ME0766 | N67: 10+164 | O67: Culvert | Q67: 66 | R67: 66
A68: CU017003 | C68: CU017003 | D68: CV-DR-CULV-00 | E68: Culvert-Drainage | F68: EE | H68: 2 | J68: 59.287034 | K68: 24.696531 | L68: Culvert | M68: OR017002 | N68: 9+950 | O68: Culvert | Q68: 67 | R68: 67
A69: CU017004 | C69: CU017004 | D69: CV-DR-CULV-00 | E69: Culvert-Drainage | F69: EE | H69: 2 | J69: 59.287522 | K69: 24.693528 | L69: Culvert | M69: OR017004 | N69: 9+952 | O69: Culvert | Q69: 68 | R69: 68
A70: CU017005 | C70: CU017005 | D70: CV-DR-CULV-RD | E70: Culvert-Road | F70: EE | H70: 2 | J70: 59.287191 | K70: 24.696156 | L70: Road culvert | M70: OR0170 | N70: 9+941 | O70: Culvert | Q70: 69 | R70: 69
A71: CU017006 | C71: CU017006 | D71: CV-DR-CULV-RD | E71: Culvert-Road | F71: EE | H71: 2 | J71: 59.287312 | K71: 24.695463 | L71: Road culvert | M71: OR0170 | N71: 9+941 | O71: Culvert | Q71: 70 | R71: 70
A72: CU024001 | B72: CU024001 | D72: CV-DR-CULV-W1 | E72: Culvert-Railway-Small Animals-water | F72: EE | H72: 3 | J72: 59.435962 | K72: 24.92798 | L72: Animal culvert | N72: 7+320 | O72: Culvert | P72: 25.07.2025 | Q72: 71 | R72: 71
A73: CU0260 | B73: CU0260 | D73: CV-DR-CULV-W1 | E73: Culvert-Railway-Small Animals-water | F73: EE | H73: 3 | J73: 59.425583 | K73: 24.920946 | L73: Culvert - Box 1,50 x 1,50 | N73: 8+586 | O73: Culvert | Q73: 72 | R73: 72
A74: CU0270 | B74: CU0270 | D74: CV-DR-CULV-W1 | E74: Culvert-Railway-Small Animals-water | F74: EE | H74: 3 | J74: 59.424007 | K74: 24.918401 | L74: Culvert - Box 1,50 x 1,50 | N74: 8+813 | O74: Culvert | Q74: 73 | R74: 73
A75: CU028001 | C75: CU028001 | D75: CV-DR-CULV-RD | E75: Culvert-Road | F75: EE | H75: 1 | J75: 59.375882 | K75: 24.900555 | L75: Road culvert | M75: OR0280 | N75: 9+024 | O75: Culvert | Q75: 74 | R75: 74
A76: CU028002 | C76: CU028002 | D76: CV-DR-CULV-RD | E76: Culvert-Road | F76: EE | H76: 1 | J76: 59.377982 | K76: 24.893904 | L76: Road culvert | M76: OR0280 | N76: 9+155 | O76: Culvert | Q76: 75 | R76: 75
A77: CU028003 | C77: CU028003 | D77: CV-DR-CULV-RD | E77: Culvert-Road | F77: EE | H77: 1 | J77: 59.37583 | K77: 24.90024 | L77: Road culvert | M77: OR028003 | N77: 9+036 | O77: Culvert | Q77: 76 | R77: 76
A78: CU028004 | C78: CU028004 | D78: CV-DR-CULV-RD | E78: Culvert-Road | F78: EE | H78: 1 | J78: 59.377768 | K78: 24.893423 | L78: Road culvert | M78: OR028010 | N78: 9+192 | O78: Culvert | P78: 11.07.2025 | Q78: 77 | R78: 77
A79: CU029001 | C79: CU029001 | D79: CV-DR-CULV-00 | E79: Culvert-Drainage | F79: EE | H79: 1 | J79: 59.371243 | K79: 24.860736 | L79: minor culvert | M79: OR029007 | N79: 11+222 | O79: Culvert | Q79: 78 | R79: 78
A80: CU029002 | C80: CU029002 | D80: CV-DR-CULV-RD | E80: Culvert-Road | F80: EE | H80: 1 | J80: 59.371503 | K80: 24.862604 | L80: Culvert | M80: OR029008 | N80: 11+112 | O80: Culvert | Q80: 79 | R80: 79
A81: CU029003 | C81: CU029003 | D81: CV-DR-CULV-RD | E81: Culvert-Road | F81: EE | H81: 1 | J81: 59.369762 | K81: 24.863423 | L81: Culvert | M81: OR029013 | N81: 11+163 | O81: Culvert | Q81: 80 | R81: 80
A82: CU029004 | C82: CU029004 | D82: CV-DR-CULV-RD | E82: Culvert-Road | F82: EE | H82: 1 | J82: 59.372005 | K82: 24.861354 | L82: Culvert | M82: OR029008 | N82: 11+163 | O82: Culvert | Q82: 81 | R82: 81
A83: CU029006 | C83: CU029006 | D83: CV-DR-CULV-RD | E83: Culvert-Road | F83: EE | H83: 1 | J83: 59.371933 | K83: 24.86131 | L83: Road culvert | M83: OR029014 | N83: 11+168 | O83: Culvert | Q83: 82 | R83: 82
A84: CU029008 | C84: CU029008 | D84: CV-DR-CULV-RD | E84: Culvert-Road | F84: EE | H84: 1 | J84: 59.371244 | K84: 24.860924 | L84: Road culvert | M84: OR029014 | N84: 11+211 | O84: Culvert | Q84: 83 | R84: 83
A85: CU030001 | C85: CU030001 | D85: CV-DR-CULV-RD | E85: Culvert-Road | F85: EE | H85: 1 | J85: 59.369506 | K85: 24.857293 | L85: Road culvert | M85: OR0300 | N85: 11+465 | O85: Culvert | Q85: 84 | R85: 84
A86: CU031001 | B86: CU031001 | D86: CV-DR-CULV-RD | E86: Culvert-Road | F86: EE | H86: 1 | J86: 59.369007 | K86: 24.854623 | L86: Culvert | M86: OR0310 | N86: 11+630 (left) | O86: Culvert | Q86: 85 | R86: 85
A87: CU031002 | B87: CU031002 | D87: CV-DR-CULV-RD | E87: Culvert-Road | F87: EE | H87: 1 | J87: 59.470291 | K87: 24.973799 | L87: Culvert | M87: OR031006 | N87: 11+690(right) | O87: Culvert | Q87: 86 | R87: 86
A88: CU031003 | B88: CU031003 | D88: CV-DR-CULV-RD | E88: Culvert-Road | F88: EE | H88: 1 | J88: 59.409612 | K88: 24.908691 | L88: Culvert | M88: OR031001 | N88: 11+600 (left) | O88: Culvert | Q88: 87 | R88: 87
A89: CU031005 | C89: CU031005 | D89: CV-DR-CULV-RD | E89: Culvert-Road | F89: EE | H89: 1 | J89: 59.368164 | K89: 24.85588 | L89: Road culvert | M89: OR031007 | N89: 11+585 | O89: Culvert | Q89: 88 | R89: 88
A90: CU031007 | C90: CU031007 | D90: CV-DR-CULV-RD | E90: Culvert-Road | F90: EE | H90: 1 | J90: 59.367632 | K90: 24.854443 | L90: Road culvert | M90: OR031013 | N90: 11+681 | O90: Culvert | Q90: 89 | R90: 89
A91: CU031009 | C91: CU031009 | D91: CV-DR-CULV-RD | E91: Culvert-Road | F91: EE | H91: 1 | J91: 59.367647 | K91: 24.853885 | L91: Road culvert | M91: OR031009 | N91: 11+710 | O91: Culvert | Q91: 90 | R91: 90
A92: CU031011 | C92: CU031011 | D92: CV-DR-CULV-RD | E92: Culvert-Road | F92: EE | H92: 1 | J92: 59.368627 | K92: 24.852692 | L92: Road culvert | M92: OR031005 | N92: 11+744 | O92: Culvert | Q92: 91 | R92: 91
A93: CU031013 | C93: CU031013 | D93: CV-DR-CULV-RD | E93: Culvert-Road | F93: EE | H93: 1 | J93: 59.367706 | K93: 24.846678 | L93: Road culvert | M93: OR031005 | N93: 12+094 | O93: Culvert | Q93: 92 | R93: 92
A94: CU031015 | C94: CU031015 | D94: CV-DR-CULV-RD | E94: Culvert-Road | F94: EE | H94: 1 | J94: 59.367522 | K94: 24.842651 | L94: Road culvert | M94: OR031003 | N94: 12+319 | O94: Culvert | Q94: 93 | R94: 93
A95: CU032001 | C95: CU032001 | D95: CV-DR-CULV-RD | E95: Culvert-Road | F95: EE | H95: 1 | J95: 59.365798 | K95: 24.824022 | L95: Culvert | M95: OR032005 | N95: 13+373 | O95: Culvert | Q95: 94 | R95: 94
A96: CU032002 | C96: CU032002 | D96: CV-DR-CULV-RD | E96: Culvert-Road | F96: EE | H96: 1 | J96: 59.368315 | K96: 24.824956 | L96: Road culvert | M96: OR032004 | N96: 13+318 | O96: Culvert | Q96: 95 | R96: 95
A97: CU032003 | C97: CU032003 | D97: CV-DR-CULV-RD | E97: Culvert-Road | F97: EE | H97: 1 | J97: 59.365605 | K97: 24.81946 | L97: Culvert | M97: OR032005 | N97: 13+650 | O97: Culvert | Q97: 96 | R97: 96
A98: CU032004 | C98: CU032004 | D98: CV-DR-CULV-RD | E98: Culvert-Road | F98: EE | H98: 1 | J98: 59.369086 | K98: 24.820378 | L98: Road culvert | M98: OR032002 | N98: 13+567 | O98: Culvert | Q98: 97 | R98: 97
A99: CU032005 | C99: CU032005 | D99: CV-DR-CULV-RD | E99: Culvert-Road | F99: EE | H99: 1 | J99: 59.365705 | K99: 24.818575 | L99: Road culvert | M99: OR032003 | N99: 13+703 | O99: Culvert | Q99: 98 | R99: 98
A100: CU032006 | C100: CU032006 | D100: CV-DR-CULV-RD | E100: Culvert-Road | F100: EE | H100: 1 | J100: 59.368896 | K100: 24.819931 | L100: Road culvert | M100: OR032003 | N100: 13+594 | O100: Culvert | Q100: 99 | R100: 99
...

Sheet ZONE
A1: CODE | B1: NAME
A2: ZZ | B2: Whole Zone
A3: 00 | B3: No Zone applicable
A4: SB | B4: Substructure | C4: Not in use
A5: SP | B5: Superstructure | C5: Not in use
A6: EN | B6: Entrances | C6: Not in use
A7: AG | B7: Above Ground | C7: Not in use
B8: To be continued if required. Any code and description shall be agreed with the Client.

Sheet LOCATION
A1: CODE | B1: CHAINAGE KM
A2: 0000 | B2: No location applicable
A3: ZZZZ | B3: Multiple Locations applicable | F3: NOTES:
A4: 0001 | B4: 0 | C4: - | D4: =B5 -> 1000 | F4: Chainage and codes are relative for each desing priority section (DPS) starting from 0+000
A5: 0002 | B5: =B4+1000 -> 1000 | C5: =C4 -> - | D5: =B6 -> 2000 | F5: Absolute chainage shall be introduced after all design sections are finalized in MD stage
A6: 0003 | B6: =B5+1000 -> 2000 | C6: =C5 -> - | D6: =B7 -> 3000
A7: 0004 | B7: =B6+1000 -> 3000 | C7: =C6 -> - | D7: =B8 -> 4000
A8: 0005 | B8: =B7+1000 -> 4000 | C8: =C7 -> - | D8: =B9 -> 5000
A9: 0006 | B9: =B8+1000 -> 5000 | C9: =C8 -> - | D9: =B10 -> 6000
A10: 0007 | B10: =B9+1000 -> 6000 | C10: =C9 -> - | D10: =B11 -> 7000
A11: 0008 | B11: =B10+1000 -> 7000 | C11: =C10 -> - | D11: =B12 -> 8000
A12: 0009 | B12: =B11+1000 -> 8000 | C12: =C11 -> - | D12: =B13 -> 9000
A13: 0010 | B13: =B12+1000 -> 9000 | C13: =C12 -> - | D13: =B14 -> 10000
A14: 0011 | B14: =B13+1000 -> 10000 | C14: =C13 -> - | D14: =B15 -> 11000
A15: 0012 | B15: =B14+1000 -> 11000 | C15: =C14 -> - | D15: =B16 -> 12000
A16: 0013 | B16: =B15+1000 -> 12000 | C16: =C15 -> - | D16: =B17 -> 13000
A17: 0014 | B17: =B16+1000 -> 13000 | C17: =C16 -> - | D17: =B18 -> 14000
... A22: 0019 | B22: =B21+1000 -> 18000 | C22: =C21 -> - | D22: =B23 -> 19000
A23: 0020 | B23: =B22+1000 -> 19000 | C23: =C22 -> -
B24: To be continued if required. Any code and description shall be agreed with the Client.

Sheet DOCUMENT TYPE
A1: DOCUMENT TYPE DESCRIPTION | B1: RBR CODE | C1: EE file name relevant | D1: LT file name relevant
A2: Animation File | B2: AF | C2: 9 | F2: FOR INFORMATION
A3: Application | B3: AP | C3: 9 | G3: EE document types
A4: BIM model native format | B4: BM | C4: 9 | F4: 0 | G4: Ülddokumendid (tiitelleht, sisukord, dokumentide nimekiri jms) | H4: General documents (title page, table of contents, list of documents, etc.)
A5: Bill of Quantity (general) | B5: BQ | C5: 8 | D5: SŽ | F5: 1 | G5: Lähtedokumendid (projekteerimistingimused, tehnilised tingimused jms) | H5: Reference documents (design specifications, technical conditions, etc.)
A6: Bill of Quantity for Eqiupment (Placement of equipment) | B6: BQ | C6: 8 | D6: IŽ | F6: 2 | G6: Kooskõlastused (kooskõlastuste koondtabel, kooskõlastuslehed jms | H6: Coordinations (summary table of coordination, coordination letters, etc.)
A7: Bill of Quantity for Construction Products | B7: BQ | C7: 8 | D7: SPŽ | F7: 3 | G7: Seletuskirjad | H7: Explanatory notes
A8: Bill of Quantity for Construction works | B8: BQ | C8: 8 | D8: SDŽ | F8: 4 | G8: Asendiplaani joonised (välisosa plaanijoonised) | H8: Drawings of the position plan (external plane layouts)
A9: BIM element/object | B9: BE | C9: 9 | F9: 5 | G9: Ehitise üldised plaanijoonised (horisontaalsed üldjoonised, sh üldskeemid) | H9: General layout of the building (horizontal general drawings, including general layouts)
A10: Calculations (general) | B10: CA | C10: 9 | D10: S | F10: 6 | G10: Ehitise üldised vaated, lõiked, pikiprofiilid (vertikaalsed üldjoonised) | H10: General views, cuts, longitudinal profiles of the building (vertical drawings)
A11: Engineering calculations | B11: CA | C11: 9 | D11: IS | F11: 7 | G11: Muud joonised (sõlmed, detailid jms) | H11: Other drawings (nodes, details, etc.)
A12: Economic calculations | B12: CA | C12: 9 | D12: ES | F12: 8 | G12: Spetsifikatsioonid, mahtude loetelud jms | H12: Specifications, volumes, etc.
A13: Clash detection model native file | B13: CC | C13: 9 | F13: 9 | G13: Lisad (kõik muud lisatavad dokumendid) | H13: Extras (all other documents to be added)
A14: Contract | B14: CD | C14: 1
A15: Comment | B15: CE | C15: 9
A16: Change Request Notice | B16: CH | C16: 9 | G16: LT document types
A17: Point Cloud model | B17: CL | C17: 9 | F17: AR | G17: Aiškinamasis raštas | H17: Explanatory note
A18: Combined Model | B18: CM | C18: 9 | F18: BAR | G18: Bendrasis aiškinamasis raštas | H18: General explanatory note
A19: Consent | B19: CN | C19: 0 | F19: B | G19: Brėžiniai | H19: Drawings
A20: Correspondence | B20: CO | C20: 0 | F20: S… | G20: Skaičiavimai (skaičiavimų rezultatai) | H20: Calculations (results of calculations)
A21: Cost Plan | B21: CP | C21: 8 | F21: IS | G21: Inžineriniai skaičiavimai | H21: Engineering calculations
A22: Cost estimation calculations | B22: CE | C22: 8 | D22: KS | F22: KS | G22: Kainos skaičiavimas | H22: Cost estimation
A23: Clash Report | B23: CR | C23: 9 | F23: ES | G23: Ekonominiai skaičiavimai | H23: Economic calculations
A24: Calculation Sheet | B24: CS | C24: 9 | D24: S, IS, KS, ES | F24: TS | G24: Techninės specifikacijos | H24: Technical specifications
A25: Certificate | B25: CT | C25: 9 | F25: BTS | G25: Bendroji techninė specifikacija | H25: General technical specification
A26: Asset Data Dictionary | B26: AD | C26: 9 | F26: Ž… | G26: Žiniaraštis | H26: Bill of ….
A27: Asset Data Dictionary Defi Documents (AD4s) | B27: DA | C27: 9 | F27: PSŽ | G27: Projekto sudėties žiniaraštis | H27: Project Composition Sheet
A28: Database | B28: DB | C28: 9 | F28: BSŽ | G28: Bylos (segtuvų) sudėties žiniaraštis | H28: File (binder) composition chart
A29: Data Drop from BIM Model | B29: DD | C29: 9 | F29: SDŽ | G29: Sustambintų darbų žiniaraštis
A30: Drawings of the position plan (external plane layouts), Site plan drawings | B30: D1 | C30: 4 | D30: B | F30: ŠŽ… | G30: Sąnaudų kiekių žiniaraštis (statybos produktu, įrenginių ir statybos darbų) | H30: BoQ (construction products, equipment and construction works)
A31: General layout of the building (horizontal general drawings, including general layouts), GA drawings | B31: D2 | C31: 5 | D31: B | F31: IŽ | G31: Įrenginių žiniaraštis | H31: Bill of eqiupment (Placement of equipment)
A32: General views, cuts, longitudinal profiles of the building (vertical drawings) | B32: D3 | C32: 6 | D32: B | F32: SPŽ | G32: Statybos produktų žiniaraštis | H32: Construction Products Sheet
A33: Other drawings (nodes, details, etc.) | B33: D4 | C33: 7 | D33: B | F33: SDŽ | G33: Statybos darbų žiniaraštis | H33: Construction works sheet
A34: Detailed equipment or space data | B34: DS | C34: 7
A35: Existing Information | B35: EI | C35: 1
A36: Financial Document | B36: FD | C36: 0
A37: Forms | B37: FM | C37: 0
A38: File Note | B38: FN | C38: 0
A39: Ground Investigation | B39: GI | C39: 1
A40: GIS dataset | B40: GS | C40: 1
A41: Health and Safety | B41: HS | C41: 0
A42: Information Exchange File | B42: IE | C42: 9
A43: BIM Model IFC format | B43: IF | C43: 9
A44: Image | B44: IM | C44: 9
A45: Invoice | B45: IN | C45: 0
... A70: Report | B70: RP | C70: 0
A71: Explanatory reports | B71: RP | C71: 3 | F71: 44375 | G71: Added (Eike Alunurm; RBE)
A72: Schedule of Accommodation | B72: SA | C72: 9
A73: Schedules | B73: SH | C73: 9
A74: Sketch | B74: SK | C74: 7
A75: Snagging List | B75: SN | C75: 0
A76: Specification | B76: SP | C76: 8 | D76: BTS
A77: Specification | B77: SP | C77: 8 | D77: TS
A78: Standard | B78: ST | C78: 1
A79: Survey | B79: SU | C79: 1
A80: Template | B80: TE | C80: 1
A81: Terms of reference | B81: TO | C81: 1 | F81: 27.08.2021 | G81: Changed number (Eike Alunurm; RBE)
A82: Technical Query | B82: TQ | C82: 0
A83: Transmittal | B83: TR | C83: 0
A84: Visualisation | B84: VS | C84: 9
A85: Other Document Type | B85: XX | C85: 9
A86: Coordinations | B86: CO | C86: 2 | F86: 44375 | G86: Added (Eike Alunurm; RBE)
A87: To be continued if required. Any code and description shall be agreed with the Client.

Sheet ACTIVITY & DISCIPLINE CODE
B1: Folder number | C1: Activity/Discipline code description | D1: Volsys. Code | E1: Folder number | F1: Activity/Discipline description RBR | G1: Activity/Discipline code | J1: Activity/Discipline description EHR | K1: Activity/Discipline description MNT | L1: Rev date | M1: Rev by
G2: RBR | H2: EHR | I2: MNT
A3: Overall (0-OV) | B3: 000 | C3: Model | E3: 01 | F3: landXML | G3: MO | H3: AA | I3: -
E4: 02 | F4: IFC | G4: MO | H4: AA | I4: -
E5: 03 | F5: RVT | G5: MO | H5: AA | I5: -
E6: 04 | F6: NWD | G6: MO | H6: AA | I6: -
E7: ... | F7: ... | G7: MO | H7: AA | I7: -
B8: 001 | C8: Minutes of Meeting | F8: Minutes of Meeting | G8: MOM | H8: AA | I8: -
B9: 002 | C9: General | D9: VOLSYS. CODE | E9: 01 | F9: General | G9: GE | H9: AA | I9: - | J9: Üldosa | K9: Üldosa
E10: 02 | F10: Conditions for Design | G10: GE | H10: AA | I10: PT | J10: Üldosa | K10: projekteerimistingimused
E11: 03 | F11: Terms of Reference | G11: GE | H11: AA | I11: LY | J11: Üldosa | K11: lähteülesanne
E12: 04 | F12: Technical Conditions | G12: GE | H12: AA | I12: TT | J12: Üldosa | K12: tehnilised tingimused
E13: 05 | F13: Initial Data | G13: GE | H13: AA | I13: AD | J13: Üldosa | K13: lähteandmed
E14: 06 | F14: Approvals | G14: GE | H14: AA | I14: KK | J14: Üldosa | K14: kooskõlastused
E15: 07 | F15: Road Safety Audit | G15: GE | H15: AA | I15: LA | J15: Üldosa | K15: liiklusohutuse audit
E16: 08 | F16: Appraisal | G16: GE | H16: AA | I16: EK | J16: Üldosa | K16: ekspertiis
E17: 09 | F17: Agreement with landowners | G17: GE | H17: AA | I17: MO | J17: Üldosa | K17: kokkulepped maaomanikega
E18: 10 | F18: Building Permit | G18: GE | H18: AA | I18: BP | J18: Üldosa | K18: ehitusluba
E19: 11 | F19: Road pavement calculation | G19: GE | H19: AA | I19: KA | J19: Üldosa | K19: kattendiarvutus
E20: 12 | F20: Cost List | G20: GE | H20: AA | I20: CL | J20: Üldosa | K20: kululoend
E21: 13 | F21: Application for Funding | G21: GE | H21: AA | I21: RK | J21: Üldosa | K21: rahastustaotlus
E22: 14 | F22: Land allocation Plan | G22: GE | H22: AA | I22: KY | J22: Üldosa | K22: ümberkruntimiskava (krundijaotuskava)
E23: 15 | F23: General technical solutions | G23: GE | H23: AA | I23: KY | J23: Üldosa
B24: 003 | C24: Investigations, Surveys and Studies | E24: 01 | F24: Geological Investigations | G24: IS | H24: AA | I24: GL | J24: Üldosa | K24: geoloogiline uuring
E25: 02 | F25: Traffic Survey | G25: IS | H25: AA | I25: LU | J25: Üldosa | K25: liiklusuuring
E26: 03 | F26: Flora/Fauna Survey | G26: IS | H26: AA | I26: FU | J26: Üldosa | K26: taimsetiku/loomastiku uuring
E27: 04 | F27: Archeological Survey | G27: IS | H27: AA | I27: AU | J27: Üldosa | K27: arheoloogiline uuring
E28: 05 | F28: Topographic Survey | G28: IS | H28: AA | I28: GD | J28: Üldosa | K28: topogeodeesia
E29: 06 | F29: Noise Survey | G29: IS | H29: AA | I29: MU | J29: Üldosa | K29: müra uuring
E30: 07 | F30: Enviormental screening | G30: IS | H30: AA | I30: KE | J30: Üldosa | K30: keskkonnamõju eelhinnang
E31: 08 | F31: EIA | G31: IS | H31: AA | I31: KH | J31: Üldosa | K31: keskkonnamõju hinnang (KMH või KSH)
E32: 09 | F32: Feasibilty study | G32: IS | H32: AA | I32: TU | J32: Üldosa | K32: teostatavusuuring
E33: 10 | F33: Other | G33: IS | H33: AA | I33: ZZ | J33: Üldosa | K33: muu
B34: 004 | C34: Demolition | E34: 01 | F34: Architecture, Building structures & Service (Demolition) | G34: DE | H34: AA | I34: - | J34: Üldosa
E35: 02 | F35: Civil & Structures (Demolition) | G35: DE | H35: AA | I35: - | J35: Üldosa
E36: 03 | F36: Electrical (Demolition) | G36: DE | H36: AA | I36: - | J36: Üldosa
E37: 04 | F37: Fleet (Demolition) | G37: DE | H37: AA | I37: - | J37: Üldosa
E38: 05 | F38: Property (Demolition) | G38: DE | H38: AA | I38: - | J38: Üldosa
E39: 06 | F39: Signalling & Control Systems (Demolition) | G39: DE | H39: AA | I39: - | J39: Üldosa
E40: 07 | F40: Information Technology & Telecommunications System (Demolition) | G40: DE | H40: AA | I40: - | J40: Üldosa
E41: 08 | F41: Track (Demolition) | G41: DE | H41: AA | I41: - | J41: Üldosa
E42: 09 | F42: Fire safety systems (Demolition) | G42: DE | H42: AA | I42: - | J42: Üldosa
E43: 10 | F43: General demolition design (Demolition) | G43: DE | H43: AA | I43: - | J43: Üldosa
E44: 11 | F44: Other (Demolition) | G44: DE | H44: AA | I44: - | J44: Üldosa
B45: 005 | C45: Construction documentation | E45: 01 | F45: AsBuiltDoc | G45: GE | H45: AA | I45: - | J45: Üldosa | K45: Tööde aktid, Teostusmõõdistused, protokollid, katsetused
E46: 02 | F46: Maintenance Sheet | G46: GE | H46: AA | I46: - | J46: Üldosa | K46: Hooldusjuhend
E47: 03 | F47: Manufacturer Sheet | G47: GE | H47: AA | I47: - | J47: Üldosa | K47: Tooteleht, paigaldusjuhend
E48: 04 | F48: Delivery note | G48: GE | H48: AA | I48: - | J48: Üldosa | K48: Saatelehed
E49: 05 | F49: Site Diary | G49: GE | H49: AA | I49: - | J49: Üldosa | K49: Ehitustööde päevik
E50: 06 | F50: Photos | G50: GE | H50: AA | I50: - | J50: Üldosa | K50: Üldfotod
E51: 07 | F51: Personnel | G51: GE | H51: AA | I51: - | J51: Üldosa | K51: Personal ja nende nõuded
E52: 08 | F52: Quality management | G52: GE | H52: AA | I52: - | J52: Üldosa | K52: Keskkonnakavad, kvaliteedi tagamiseplaanid
E53: 09 | H53: - | I53: -
E54: 10 | H54: - | I54: -
E55: 11 | H55: - | I55: -
A56: Architecture, Building structures & Services (1-AR) | B56: 101 | C56: Master Plan | D56: VOLSYS. CODE | F56: Position Plan | G56: MP | H56: AS | I56: - | J56: Asendiplaan
B57: 102 | C57: Urban Design & Landscaping | E57: 01 | F57: Landscaping | G57: UD | H57: MA | I57: MA | J57: Maastik | K57: Maastik
E58: 02 | F58: Paving | G58: UD | H58: MA | I58: - | J58: Maastik | K58: Maastik
B59: 103 | C59: Car Parks | E59: 01 | F59: Car Park-At Grade Commuter | G59: PK | H59: TL | I59: TL | K59: Tee
E60: 02 | F60: Car Park-Multi Storey Commuter | G60: PK | H60: TL | I60: TL | K60: Tee
E61: 03 | F61: Kiss and Ride Bay | G61: PK | H61: TL | I61: TL | K61: Tee
E62: 04 | F62: Taxi Rank | G62: PK | H62: TL | I62: TL | K62: Tee
B63: 104 | C63: Architecture | F63: Architecture | G63: AR | H63: AR | I63: - | J63: Arhitektuur
B64: 105 | C64: Interior Architecture | E64: 01 | F64: Office Equipment | G64: IA | H64: SA | I64: - | J64: Sisearhitektuur
E65: 02 | F65: Furniture & Fixtures | G65: IA | H65: SA | I65: - | J65: Sisearhitektuur
B66: 106 | C66: Art | E66: 01 | F66: Paintings | G66: OA | H66: AR | I66: - | J66: Kunst
E67: 02 | F67: Sculptures | G67: OA | H67: AR | I67: - | J67: Kunst
B68: 107 | C68: Structural | E68: 01 | F68: Construction Structures | G68: STR | H68: EK | I68: - | J68: Konstruktsioon
E69: 02 | F69: Access Platform | G69: STR | H69: EK | I69: - | J69: Konstruktsioon
E70: 03 | F70: Access Ramp | G70: STR | H70: EK | I70: - | J70: Konstruktsioon
E71: 04 | F71: Building-Permanent | G71: STR | H71: EK | I71: - | J71: Konstruktsioon
E72: 05 | F72: Platform | G72: STR | H72: EK | I72: - | J72: Konstruktsioon
B73: 108 | C73: Acoustics | F73: Acoustics | G73: AC | H73: AK | I73: - | J73: Akustika
B74: 109 | C74: Mechanical Systems (HVAC) | F74: Mechanical Systems (HVAC) | G74: ME | H74: KV | J74: Küte, ventilatsioon ja jahutus
B75: 110 | C75: Heating and Cooling Engineering and Networks (HECL) | E75: 01 | F75: Heating Engineering and Networks | G75: HE | H75: SV | I75: TV | J75: Soojusvarustus
E76: 02 | F76: Cooling Engineering and Networks | G76: CL | H76: KVJ | J76: Jahutusvarustus | L76: 45706 | M76: Taavo Tinno (EHR tähis)
B77: 111 | C77: Water Supply and Sewerage, external | F77: Water Supply and Sewerage, external | G77: WE | H77: VKV | I77: TV | J77: Veevarustuse ja kanalisatsiooni välisosa | K77: Tehnovõrgud
B78: 112 | C78: Water Supply and Sewerage, interior | F78: Water Supply and Sewerage, interior | G78: IW | H78: VKS | I78: - | J78: Veevarustuse ja kanalisatsiooni siseosa
B79: 113 | C79: Gas supply, external network | F79: Gas supply, external network | G79: EG | H79: GVV | I79: TV | J79: Gaasivarustuse välisvõrk | K79: Tehnovõrgud | L79: 45706 | M79: Taavo Tinno (EHR tähis)
B80: 114 | C80: Gas supply, internal network | F80: Gas supply, internal network | G80: IG | H80: GVS | I80: - | J80: Gaasivarustuse siseosa | L80: 45706 | M80: Taavo Tinno (EHR tähis)
B81: 115 | C81: Technology Part | E81: 01 | F81: Compressed Air Systems | G81: TP | H81: TE | I81: - | J81: Tehnoloogia
E82: 02 | F82: Other systems | G82: TP | H82: TE | I82: TV | J82: Tehnoloogia | K82: Tehnovõrgud
E83: 03 | F83: Fuel & Oil Systems | G83: TP | H83: TE | I83: TV | J83: Tehnoloogia | K83: Tehnovõrgud
E84: 04 | F84: Door locking systems | G84: TP | H84: TE | I84: TV | J84: Tehnoloogia
B85: 116 | C85: Vertical Transportation Systems | E85: 01 | F85: Escalator | G85: VT | H85: TE | I85: - | J85: Tehnoloogia
E86: 02 | F86: Lift | G86: VT | H86: TE | I86: - | J86: Tehnoloogia
B87: 117 | C87: Energy | F87: Energy Efficency | G87: EN | H87: EE | I87: - | J87: Energiamärgis
A88: Civil & Structures (2-CV) | B88: 201 | C88: Roads | D88: VOLSYS. CODE | F88: Road | G88: RO | H88: TL | I88: TL | J88: Teed ja liikluskorraldus (va. raudteed, veetranspordirajatised ja sillad-viaduktid) | K88: Tee
B89: 202 | C89: Bridges | E89: 01 | F89: Overpass | G89: BR | H89: TS | I89: TS | J89: Sillad, viaduktid, estakaadid ja tunnelid | K89: Konstruktsioonid
E90: 02 | F90: Bridge-Road | G90: BR | H90: TS | I90: TS | J90: Sillad, viaduktid, estakaadid ja tunnelid | K90: Konstruktsioonid
E91: 03 | F91: Bridge-Railway | G91: BR | H91: TS | I91: TS | J91: Sillad, viaduktid, estakaadid ja tunnelid | K91: Konstruktsioonid
E92: 04 | F92: Underpass | G92: BR | H92: TS | I92: TS | J92: Sillad, viaduktid, estakaadid ja tunnelid | K92: Konstruktsioonid
E93: 05 | F93: Viaduct-Road | G93: BR | H93: TS | I93: TS | J93: Sillad, viaduktid, estakaadid ja tunnelid | K93: Konstruktsioonid
B94: 203 | C94: Tunnels | F94: Tunnel | G94: TU | H94: TS | I94: MR | J94: Sillad, viaduktid, estakaadid ja tunnelid | K94: Muud rajatised
B95: 204 | C95: Retaining Wall | F95: Retaining Wall | G95: RS | H95: TS | I95: TS | J95: Sillad, viaduktid, estakaadid ja tunnelid | K95: Konstruktsioonid
B96: 205 | C96: Earthworks & Geotech | E96: 01 | F96: Earthworks-Cutting | G96: EW | H96: TS | I96: MR | J96: Sillad, viaduktid, estakaadid ja tunnelid | K96: Muud rajatised
E97: 02 | F97: Earthworks-Embankment | G97: EW | H97: TS | I97: MR | J97: Sillad, viaduktid, estakaadid ja tunnelid | K97: Muud rajatised
B98: 206 | C98: Misc Structures | F98: Fauna Crossing | G98: MS | H98: TS | I98: MR | J98: Sillad, viaduktid, estakaadid ja tunnelid | K98: Muud rajatised
B99: 207 | C99: Overhead & Gantry Structures | F99: Overhead Loading Structure | G99: OS | H99: TS | I99: MR | J99: Sillad, viaduktid, estakaadid ja tunnelid | K99: Muud rajatised
B100: 208 | C100: Tower Structures | E100: 01 | F100: Communications Tower | G100: TW | H100: TS | I100: MR | J100: Sillad, viaduktid, estakaadid ja tunnelid | K100: Muud rajatised
...

Sheet PROJECT STAGE
A1: STAGE DESCRIPTION | B1: RBR CODE | C1: EE CODE | D1: Staadium
A2: STAGE DESCRIPTION | B2: RBR CODE | C2: EE CODE | D2: Staadium
A3: Site Investigations | B3: SI | C3: UP | D3: Uuringud
A4: Value Engineering | B4: VE | C4: VE | D4: Väärtuspõhine alternatiivide võrdlus
A5: Preliminary design | B5: PD | C5: EP | D5: Eelprojekt
A6: Master Design | B6: MD | C6: PP | D6: Põhiprojekt
A7: Detailed Technical Design | B7: DTD | C7: TP | D7: Tööprojekt
A8: Construction | B8: CO | C8: TJ | D8: Teostusprojekt
A9: Operation | B9: OP | C9: OP | D9: Opereerimine
A10: Demolition | B10: DE | C10: LP | D10: Lammutusprojekt
A12: Techinis darbu projektas - LST 1516:2015 | B12: TDP
A13: Būvprojekts minimālā sastāvā - LBN 202-15 | B13: MBP
B14: To be continued if required. Any code and description shall be agreed with the Client.

Sheet ASSET CLASSIFICATION
A1: ASSET CLASSIFICATION | P1: v.2020-11-22 | Q1: All updates and modifications should be agreed with BIM Team
R2: Object Description Translation
A3: Discipline | B3: Discipline description | C3: Asset Class | D3: Asset Class description | E3: Function | F3: Asset Function description | G3: Type | H3: Asset Type description | I3: ISO 12006 mapping | J3: Category | K3: Asset group | L3: Capitalise | M3: Asset Class (Financial) | N3: Technical Object code | O3: Technical Object description | P3: RBR-Functional classification | Q3: Object description | R3: Estonian | S3: Latvian | T3: Lithuanian | U3: Aux | V3: Calculated for AM comparison | W3: v202002 | X3: RB team | Y3: RB when added | Z3: comments | AA3: value | AB3: order
A4: AR | B4: Architecture & Services | C4: BD | D4: Buildings & Access | E4: APLT | F4: Access Platform | G4: EW | H4: Elevated Work | I4: Entity | J4: Non Linear | L4: Yes | M4: Buildings | P4: =A4&"-"&U4 -> AR-BD-APLT-EW | Q4: Fxd Elev Work Plat | U4: =C4& "-" &E4 & IF(G4<>"","-" &G4,"-00") -> BD-APLT-EW | V4: =C4& "-" &E4 & IF(G4<>"","-" &G4,"") -> BD-APLT-EW | W4: =VLOOKUP(V4,'[2]Asset Classifications'!$M$12:$M$1690,1,FALSE) -> BD-APLT-EW | Y4: from_v202002 | AA4: BD-APLT-EW | AB4: 1
A5: AR | B5: Architecture & Services | C5: BD | D5: Buildings & Access | E5: APLT | F5: Access Platform | G5: YD | H5: Yard | I5: Entity | J5: Non Linear | L5: Yes | M5: Buildings | P5: =A5&"-"&U5 -> AR-BD-APLT-YD | Q5: Fxd Yard Access Plat | U5: =C5& "-" &E5 & IF(G5<>"","-" &G5,"-00") -> BD-APLT-YD | V5: =C5& "-" &E5 & IF(G5<>"","-" &G5,"") -> BD-APLT-YD | W5: =VLOOKUP(V5,'[2]Asset Classifications'!$M$12:$M$1690,1,FALSE) -> BD-APLT-YD | Y5: from_v202002 | AA5: BD-APLT-YD | AB5: 2
A6: AR | B6: Architecture & Services | C6: BD | D6: Buildings & Access | E6: ARMP | F6: Access Ramp | I6: Entity | J6: Non Linear | L6: Yes | M6: Buildings | P6: =A6&"-"&U6 -> AR-BD-ARMP-00 | Q6: Access Ramp | U6: =C6& "-" &E6 & IF(G6<>"","-" &G6,"-00") -> BD-ARMP-00 | V6: =C6& "-" &E6 & IF(G6<>"","-" &G6,"") -> BD-ARMP | W6: =VLOOKUP(V6,'[2]Asset Classifications'!$M$12:$M$1690,1,FALSE) -> BD-ARMP | AA6: BD-ARMP | AB6: 3
A7: AR | B7: Architecture & Services | C7: BD | D7: Buildings & Access | E7: BKES | F7: Bicycle Shed | I7: Entity | J7: Non Linear | L7: Yes | M7: Buildings | P7: =A7&"-"&U7 -> AR-BD-BKES-00 | Q7: Bicycle Shed | U7: =C7& "-" &E7 & IF(G7<>"","-" &G7,"-00") -> BD-BKES-00 | V7: =C7& "-" &E7 & IF(G7<>"","-" &G7,"") -> BD-BKES | W7: =VLOOKUP(V7,'[2]Asset Classifications'!$M$12:$M$1690,1,FALSE) -> BD-BKES | AA7: BD-BKES | AB7: 4
A8: AR | B8: Architecture & Services | C8: BD | D8: Buildings & Access | E8: BLDG | F8: Building-Permanent | G8: AM | H8: Amenities | I8: Entity | J8: Non Linear | L8: Yes | M8: Buildings | P8: =A8&"-"&U8 -> AR-BD-BLDG-AM | Q8: Amenities Building | U8: =C8& "-" &E8 & IF(G8<>"","-" &G8,"-00") -> BD-BLDG-AM | V8: =C8& "-" &E8 & IF(G8<>"","-" &G8,"") -> BD-BLDG-AM | W8: =VLOOKUP(V8,'[2]Asset Classifications'!$M$12:$M$1690,1,FALSE) -> BD-BLDG-AM | AA8: BD-BLDG-AM | AB8: 5
A9: AR | B9: Architecture & Services | C9: BD | D9: Buildings & Access | E9: BLDG | F9: Building-Permanent | G9: CO | H9: Communications | I9: Entity | J9: Non Linear | L9: Yes | M9: Buildings | P9: =A9&"-"&U9 -> AR-BD-BLDG-CO | Q9: Communications Building | U9: =C9& "-" &E9 & IF(G9<>"","-" &G9,"-00") -> BD-BLDG-CO | V9: =C9& "-" &E9 & IF(G9<>"","-" &G9,"") -> BD-BLDG-CO | W9: =VLOOKUP(V9,'[2]Asset Classifications'!$M$12:$M$1690,1,FALSE) -> BD-BLDG-CO | AA9: BD-BLDG-CO | AB9: 6
A10: AR | B10: Architecture & Services | C10: BD | D10: Buildings & Access | E10: BLDG | F10: Building-Permanent | G10: DP | H10: Depot | I10: Entity | J10: Non Linear | L10: Yes | M10: Buildings | P10: =A10&"-"&U10 -> AR-BD-BLDG-DP | Q10: Depot Building | U10: =C10& "-" &E10 & IF(G10<>"","-" &G10,"-00") -> BD-BLDG-DP | V10: =C10& "-" &E10 & IF(G10<>"","-" &G10,"") -> BD-BLDG-DP | W10: =VLOOKUP(V10,'[2]Asset Classifications'!$M$12:$M$1690,1,FALSE) -> BD-BLDG-DP | X10: Ops | AA10: BD-BLDG-DP | AB10: 7
A11: AR | B11: Architecture & Services | C11: BD | D11: Buildings & Access | E11: BLDG | F11: Building-Permanent | G11: FD | H11: Fuel Shed | I11: Entity | J11: Non Linear | L11: Yes | M11: Buildings | P11: =A11&"-"&U11 -> AR-BD-BLDG-FD | Q11: Fuel Shed Building | U11: =C11& "-" &E11 & IF(G11<>"","-" &G11,"-00") -> BD-BLDG-FD | V11: =C11& "-" &E11 & IF(G11<>"","-" &G11,"") -> BD-BLDG-FD | W11: =VLOOKUP(V11,'[2]Asset Classifications'!$M$12:$M$1690,1,FALSE) -> BD-BLDG-FD | AA11: BD-BLDG-FD | AB11: 8
A12: AR | B12: Architecture & Services | C12: BD | D12: Buildings & Access | E12: BLDG | F12: Building-Permanent | G12: GA | H12: Garage | I12: Entity | J12: Non Linear | L12: Yes | M12: Buildings | P12: =A12&"-"&U12 -> AR-BD-BLDG-GA | Q12: Garage Building | U12: =C12& "-" &E12 & IF(G12<>"","-" &G12,"-00") -> BD-BLDG-GA | V12: =C12& "-" &E12 & IF(G12<>"","-" &G12,"") -> BD-BLDG-GA | W12: =VLOOKUP(V12,'[2]Asset Classifications'!$M$12:$M$1690,1,FALSE) -> BD-BLDG-GA | AA12: BD-BLDG-GA | AB12: 9
A13: AR | B13: Architecture & Services | C13: BD | D13: Buildings & Access | E13: BLDG | F13: Building-Permanent | G13: LA | H13: Laboratory | I13: Entity | J13: Non Linear | L13: Yes | M13: Buildings | P13: =A13&"-"&U13 -> AR-BD-BLDG-LA | Q13: Laboratory Building | U13: =C13& "-" &E13 & IF(G13<>"","-" &G13,"-00") -> BD-BLDG-LA | V13: =C13& "-" &E13 & IF(G13<>"","-" &G13,"") -> BD-BLDG-LA | W13: =VLOOKUP(V13,'[2]Asset Classifications'!$M$12:$M$1690,1,FALSE) -> BD-BLDG-LA | AA13: BD-BLDG-LA | AB13: 10
A14: AR | B14: Architecture & Services | C14: BD | D14: Buildings & Access | E14: BLDG | F14: Building-Permanent | G14: OF | H14: Office/Admin | I14: Entity | J14: Non Linear | L14: Yes | M14: Buildings | P14: =A14&"-"&U14 -> AR-BD-BLDG-OF | Q14: Office/Admin Bldg | U14: =C14& "-" &E14 & IF(G14<>"","-" &G14,"-00") -> BD-BLDG-OF | V14: =C14& "-" &E14 & IF(G14<>"","-" &G14,"") -> BD-BLDG-OF | W14: =VLOOKUP(V14,'[2]Asset Classifications'!$M$12:$M$1690,1,FALSE) -> BD-BLDG-OF | AA14: BD-BLDG-OF | AB14: 11
A15: AR | B15: Architecture & Services | C15: BD | D15: Buildings & Access | E15: BLDG | F15: Building-Permanent | G15: OP | H15: Operations | I15: Entity | J15: Non Linear | L15: Yes | M15: Buildings | P15: =A15&"-"&U15 -> AR-BD-BLDG-OP | Q15: Operations Building | U15: =C15& "-" &E15 & IF(G15<>"","-" &G15,"-00") -> BD-BLDG-OP | V15: =C15& "-" &E15 & IF(G15<>"","-" &G15,"") -> BD-BLDG-OP | W15: =VLOOKUP(V15,'[2]Asset Classifications'!$M$12:$M$1690,1,FALSE) -> BD-BLDG-OP | AA15: BD-BLDG-OP | AB15: 12
A16: AR | B16: Architecture & Services | C16: BD | D16: Buildings & Access | E16: BLDG | F16: Building-Permanent | G16: RE | H16: Retail | I16: Entity | J16: Non Linear | L16: Yes | M16: Buildings | P16: =A16&"-"&U16 -> AR-BD-BLDG-RE | Q16: Retail Building | U16: =C16& "-" &E16 & IF(G16<>"","-" &G16,"-00") -> BD-BLDG-RE | V16: =C16& "-" &E16 & IF(G16<>"","-" &G16,"") -> BD-BLDG-RE | W16: =VLOOKUP(V16,'[2]Asset Classifications'!$M$12:$M$1690,1,FALSE) -> BD-BLDG-RE | AA16: BD-BLDG-RE | AB16: 13
A17: AR | B17: Architecture & Services | C17: BD | D17: Buildings & Access | E17: BLDG | F17: Building-Permanent | G17: RS | H17: Residential | I17: Entity | J17: Non Linear | L17: Yes | M17: Buildings | P17: =A17&"-"&U17 -> AR-BD-BLDG-RS | Q17: Residential Building | U17: =C17& "-" &E17 & IF(G17<>"","-" &G17,"-00") -> BD-BLDG-RS | V17: =C17& "-" &E17 & IF(G17<>"","-" &G17,"") -> BD-BLDG-RS | W17: =VLOOKUP(V17,'[2]Asset Classifications'!$M$12:$M$1690,1,FALSE) -> BD-BLDG-RS | AA17: BD-BLDG-RS | AB17: 14
A18: AR | B18: Architecture & Services | C18: BD | D18: Buildings & Access | E18: BLDG | F18: Building-Permanent | G18: SB | H18: Signal Box | I18: Entity | J18: Non Linear | L18: Yes | M18: Buildings | P18: =A18&"-"&U18 -> AR-BD-BLDG-SB | Q18: Signal Box Building | U18: =C18& "-" &E18 & IF(G18<>"","-" &G18,"-00") -> BD-BLDG-SB | V18: =C18& "-" &E18 & IF(G18<>"","-" &G18,"") -> BD-BLDG-SB | W18: =VLOOKUP(V18,'[2]Asset Classifications'!$M$12:$M$1690,1,FALSE) -> BD-BLDG-SB | AA18: BD-BLDG-SB | AB18: 15
A19: AR | B19: Architecture & Services | C19: BD | D19: Buildings & Access | E19: BLDG | F19: Building-Permanent | G19: SD | H19: Storage Shed | I19: Entity | J19: Non Linear | L19: Yes | M19: Buildings | P19: =A19&"-"&U19 -> AR-BD-BLDG-SD | Q19: Storage Shed Bldg | U19: =C19& "-" &E19 & IF(G19<>"","-" &G19,"-00") -> BD-BLDG-SD | V19: =C19& "-" &E19 & IF(G19<>"","-" &G19,"") -> BD-BLDG-SD | W19: =VLOOKUP(V19,'[2]Asset Classifications'!$M$12:$M$1690,1,FALSE) -> BD-BLDG-SD | AA19: BD-BLDG-SD | AB19: 16
A20: AR | B20: Architecture & Services | C20: BD | D20: Buildings & Access | E20: BLDG | F20: Building-Permanent | G20: SH | H20: Section Hut | I20: Entity | J20: Non Linear | L20: Yes | M20: Buildings | P20: =A20&"-"&U20 -> AR-BD-BLDG-SH | Q20: Section Hut Building | U20: =C20& "-" &E20 & IF(G20<>"","-" &G20,"-00") -> BD-BLDG-SH | V20: =C20& "-" &E20 & IF(G20<>"","-" &G20,"") -> BD-BLDG-SH | W20: =VLOOKUP(V20,'[2]Asset Classifications'!$M$12:$M$1690,1,FALSE) -> BD-BLDG-SH | AA20: BD-BLDG-SH | AB20: 17
A21: AR | B21: Architecture & Services | C21: BD | D21: Buildings & Access | E21: BLDG | F21: Building-Permanent | G21: SN | H21: Station | I21: Entity | J21: Non Linear | L21: Yes | M21: Buildings | P21: =A21&"-"&U21 -> AR-BD-BLDG-SN | Q21: Station Building | U21: =C21& "-" &E21 & IF(G21<>"","-" &G21,"-00") -> BD-BLDG-SN | V21: =C21& "-" &E21 & IF(G21<>"","-" &G21,"") -> BD-BLDG-SN | W21: =VLOOKUP(V21,'[2]Asset Classifications'!$M$12:$M$1690,1,FALSE) -> BD-BLDG-SN | X21: Ops | AA21: BD-BLDG-SN | AB21: 18
A22: AR | B22: Architecture & Services | C22: BD | D22: Buildings & Access | E22: BLDG | F22: Building-Permanent | G22: SS | H22: Substation | I22: Entity | J22: Non Linear | L22: Yes | M22: Buildings | P22: =A22&"-"&U22 -> AR-BD-BLDG-SS | Q22: Substation Building | U22: =C22& "-" &E22 & IF(G22<>"","-" &G22,"-00") -> BD-BLDG-SS | V22: =C22& "-" &E22 & IF(G22<>"","-" &G22,"") -> BD-BLDG-SS | W22: =VLOOKUP(V22,'[2]Asset Classifications'!$M$12:$M$1690,1,FALSE) -> BD-BLDG-SS | AA22: BD-BLDG-SS | AB22: 19
A23: AR | B23: Architecture & Services | C23: BD | D23: Buildings & Access | E23: BLDG | F23: Building-Permanent | G23: SV | H23: Services | I23: Entity | J23: Non Linear | L23: Yes | M23: Buildings | P23: =A23&"-"&U23 -> AR-BD-BLDG-SV | Q23: Services Building | U23: =C23& "-" &E23 & IF(G23<>"","-" &G23,"-00") -> BD-BLDG-SV | V23: =C23& "-" &E23 & IF(G23<>"","-" &G23,"") -> BD-BLDG-SV | W23: =VLOOKUP(V23,'[2]Asset Classifications'!$M$12:$M$1690,1,FALSE) -> BD-BLDG-SV | X23: Ops | AA23: BD-BLDG-SV | AB23: 20
A24: AR | B24: Architecture & Services | C24: BD | D24: Buildings & Access | E24: BLDG | F24: Building-Permanent | G24: TR | H24: Training | I24: Entity | J24: Non Linear | L24: Yes | M24: Buildings | P24: =A24&"-"&U24 -> AR-BD-BLDG-TR | Q24: Training Building | U24: =C24& "-" &E24 & IF(G24<>"","-" &G24,"-00") -> BD-BLDG-TR | V24: =C24& "-" &E24 & IF(G24<>"","-" &G24,"") -> BD-BLDG-TR | W24: =VLOOKUP(V24,'[2]Asset Classifications'!$M$12:$M$1690,1,FALSE) -> BD-BLDG-TR | AA24: BD-BLDG-TR | AB24: 21
A25: AR | B25: Architecture & Services | C25: BD | D25: Buildings & Access | E25: BLDG | F25: Building-Permanent | G25: TS | H25: Tunnel Services | I25: Entity | J25: Non Linear | L25: Yes | M25: Infrastructure | P25: =A25&"-"&U25 -> AR-BD-BLDG-TS | Q25: Tunnel Services Bldg | U25: =C25& "-" &E25 & IF(G25<>"","-" &G25,"-00") -> BD-BLDG-TS | V25: =C25& "-" &E25 & IF(G25<>"","-" &G25,"") -> BD-BLDG-TS | W25: =VLOOKUP(V25,'[2]Asset Classifications'!$M$12:$M$1690,1,FALSE) -> BD-BLDG-TS | AA25: BD-BLDG-TS | AB25: 22
A26: AR | B26: Architecture & Services | C26: BD | D26: Buildings & Access | E26: BLDG | F26: Building-Permanent | G26: WA | H26: Wash/Presentation | I26: Entity | J26: Non Linear | L26: Yes | M26: Buildings | P26: =A26&"-"&U26 -> AR-BD-BLDG-WA | Q26: Wash/Presentatn Bldg | U26: =C26& "-" &E26 & IF(G26<>"","-" &G26,"-00") -> BD-BLDG-WA | V26: =C26& "-" &E26 & IF(G26<>"","-" &G26,"") -> BD-BLDG-WA | W26: =VLOOKUP(V26,'[2]Asset Classifications'!$M$12:$M$1690,1,FALSE) -> BD-BLDG-WA | AA26: BD-BLDG-WA | AB26: 23
A27: AR | B27: Architecture & Services | C27: BD | D27: Buildings & Access | E27: BLDG | F27: Building-Permanent | G27: WH | H27: Warehouse | I27: Entity | J27: Non Linear | L27: Yes | M27: Buildings | P27: =A27&"-"&U27 -> AR-BD-BLDG-WH | Q27: Warehouse Building | U27: =C27& "-" &E27 & IF(G27<>"","-" &G27,"-00") -> BD-BLDG-WH | V27: =C27& "-" &E27 & IF(G27<>"","-" &G27,"") -> BD-BLDG-WH | W27: =VLOOKUP(V27,'[2]Asset Classifications'!$M$12:$M$1690,1,FALSE) -> BD-BLDG-WH | AA27: BD-BLDG-WH | AB27: 24
A28: AR | B28: Architecture & Services | C28: BD | D28: Buildings & Access | E28: BLDG | F28: Building-Permanent | G28: WO | H28: Workshop | I28: Entity | J28: Non Linear | L28: Yes | M28: Buildings | P28: =A28&"-"&U28 -> AR-BD-BLDG-WO | Q28: Workshop Building | U28: =C28& "-" &E28 & IF(G28<>"","-" &G28,"-00") -> BD-BLDG-WO | V28: =C28& "-" &E28 & IF(G28<>"","-" &G28,"") -> BD-BLDG-WO | W28: =VLOOKUP(V28,'[2]Asset Classifications'!$M$12:$M$1690,1,FALSE) -> BD-BLDG-WO | AA28: BD-BLDG-WO | AB28: 25
A29: AR | B29: Architecture & Services | C29: BD | D29: Buildings & Access | E29: BLDP | F29: Building-Portable | I29: Entity | J29: Non Linear | L29: Yes | M29: Buildings | P29: =A29&"-"&U29 -> AR-BD-BLDP-00 | Q29: Portable Building | U29: =C29& "-" &E29 & IF(G29<>"","-" &G29,"-00") -> BD-BLDP-00 | V29: =C29& "-" &E29 & IF(G29<>"","-" &G29,"") -> BD-BLDP | W29: =VLOOKUP(V29,'[2]Asset Classifications'!$M$12:$M$1690,1,FALSE) -> BD-BLDP | AA29: BD-BLDP | AB29: 26
A30: AR | B30: Architecture & Services | C30: BD | D30: Buildings & Access | E30: BRMP | F30: Boat Ramp | I30: Entity | J30: Non Linear | L30: Yes | M30: Buildings | P30: =A30&"-"&U30 -> AR-BD-BRMP-00 | Q30: Boat Ramp | U30: =C30& "-" &E30 & IF(G30<>"","-" &G30,"-00") -> BD-BRMP-00 | V30: =C30& "-" &E30 & IF(G30<>"","-" &G30,"") -> BD-BRMP | W30: =VLOOKUP(V30,'[2]Asset Classifications'!$M$12:$M$1690,1,FALSE) -> #N/A | AA30: BD-BRMP | AB30: 27
A31: AR | B31: Architecture & Services | C31: BD | D31: Buildings & Access | E31: CNPY | F31: Canopy | G31: BI | H31: Bicycle | I31: Entity | J31: Non Linear | L31: Yes | M31: Buildings | P31: =A31&"-"&U31 -> AR-BD-CNPY-BI | Q31: Canopy-Bicycle | U31: =C31& "-" &E31 & IF(G31<>"","-" &G31,"-00") -> BD-CNPY-BI | V31: =C31& "-" &E31 & IF(G31<>"","-" &G31,"") -> BD-CNPY-BI | W31: =VLOOKUP(V31,'[2]Asset Classifications'!$M$12:$M$1690,1,FALSE) -> BD-CNPY-BI | Y31: from_v202002 | AA31: BD-CNPY-BI | AB31: 28
A32: AR | B32: Architecture & Services | C32: BD | D32: Buildings & Access | E32: CNPY | F32: Canopy | G32: BU | H32: Bus Stop | I32: Entity | J32: Non Linear | L32: Yes | M32: Buildings | P32: =A32&"-"&U32 -> AR-BD-CNPY-BU | Q32: Canopy-Bus Stop | U32: =C32& "-" &E32 & IF(G32<>"","-" &G32,"-00") -> BD-CNPY-BU | V32: =C32& "-" &E32 & IF(G32<>"","-" &G32,"") -> BD-CNPY-BU | W32: =VLOOKUP(V32,'[2]Asset Classifications'!$M$12:$M$1690,1,FALSE) -> BD-CNPY-BU | AA32: BD-CNPY-BU | AB32: 29
A33: AR | B33: Architecture & Services | C33: BD | D33: Buildings & Access | E33: CNPY | F33: Canopy | G33: DP | H33: Depot | I33: Entity | J33: Non Linear | L33: Yes | M33: Buildings | P33: =A33&"-"&U33 -> AR-BD-CNPY-DP | Q33: Canopy-Depot | U33: =C33& "-" &E33 & IF(G33<>"","-" &G33,"-00") -> BD-CNPY-DP | V33: =C33& "-" &E33 & IF(G33<>"","-" &G33,"") -> BD-CNPY-DP | W33: =VLOOKUP(V33,'[2]Asset Classifications'!$M$12:$M$1690,1,FALSE) -> BD-CNPY-DP | AA33: BD-CNPY-DP | AB33: 30
A34: AR | B34: Architecture & Services | C34: BD | D34: Buildings & Access | E34: CNPY | F34: Canopy | G34: KR | H34: Kiss and Ride Bay | I34: Entity | J34: Non Linear | L34: Yes | M34: Buildings | P34: =A34&"-"&U34 -> AR-BD-CNPY-KR | Q34: Canopy-Kiss and Ride | U34: =C34& "-" &E34 & IF(G34<>"","-" &G34,"-00") -> BD-CNPY-KR | V34: =C34& "-" &E34 & IF(G34<>"","-" &G34,"") -> BD-CNPY-KR | W34: =VLOOKUP(V34,'[2]Asset Classifications'!$M$12:$M$1690,1,FALSE) -> BD-CNPY-KR | Y34: from_v202002 | AA34: BD-CNPY-KR | AB34: 31
A35: AR | B35: Architecture & Services | C35: BD | D35: Buildings & Access | E35: CNPY | F35: Canopy | G35: LR | H35: Tram Stop | I35: Entity | J35: Non Linear | L35: Yes | M35: Buildings | P35: =A35&"-"&U35 -> AR-BD-CNPY-LR | Q35: Canopy-Tram Stop | U35: =C35& "-" &E35 & IF(G35<>"","-" &G35,"-00") -> BD-CNPY-LR | V35: =C35& "-" &E35 & IF(G35<>"","-" &G35,"") -> BD-CNPY-LR | W35: =VLOOKUP(V35,'[2]Asset Classifications'!$M$12:$M$1690,1,FALSE) -> BD-CNPY-LR | AA35: BD-CNPY-LR | AB35: 32
A36: AR | B36: Architecture & Services | C36: BD | D36: Buildings & Access | E36: CNPY | F36: Canopy | G36: TA | H36: Taxi Rank | I36: Entity | J36: Non Linear | L36: Yes | M36: Buildings | P36: =A36&"-"&U36 -> AR-BD-CNPY-TA | Q36: Canopy-Taxi Rank | U36: =C36& "-" &E36 & IF(G36<>"","-" &G36,"-00") -> BD-CNPY-TA | V36: =C36& "-" &E36 & IF(G36<>"","-" &G36,"") -> BD-CNPY-TA | W36: =VLOOKUP(V36,'[2]Asset Classifications'!$M$12:$M$1690,1,FALSE) -> BD-CNPY-TA | Y36: from_v202002 | AA36: BD-CNPY-TA | AB36: 33
A37: AR | B37: Architecture & Services | C37: BD | D37: Buildings & Access | E37: CNPY | F37: Canopy | G37: TR | H37: Train Station | I37: Entity | J37: Non Linear | L37: Yes | M37: Buildings | P37: =A37&"-"&U37 -> AR-BD-CNPY-TR | Q37: Canopy-Train Station | U37: =C37& "-" &E37 & IF(G37<>"","-" &G37,"-00") -> BD-CNPY-TR | V37: =C37& "-" &E37 & IF(G37<>"","-" &G37,"") -> BD-CNPY-TR | W37: =VLOOKUP(V37,'[2]Asset Classifications'!$M$12:$M$1690,1,FALSE) -> BD-CNPY-TR | AA37: BD-CNPY-TR | AB37: 34
A38: AR | B38: Architecture & Services | C38: BD | D38: Buildings & Access | E38: CNPY | F38: Canopy | G38: WH | H38: Wharf | I38: Entity | J38: Non Linear | L38: Yes | M38: Buildings | P38: =A38&"-"&U38 -> AR-BD-CNPY-WH | Q38: Canopy-Wharf | U38: =C38& "-" &E38 & IF(G38<>"","-" &G38,"-00") -> BD-CNPY-WH | V38: =C38& "-" &E38 & IF(G38<>"","-" &G38,"") -> BD-CNPY-WH | W38: =VLOOKUP(V38,'[2]Asset Classifications'!$M$12:$M$1690,1,FALSE) -> BD-CNPY-WH | AA38: BD-CNPY-WH | AB38: 35
A39: AR | B39: Architecture & Services | C39: BD | D39: Buildings & Access | E39: CONC | F39: Concourse | I39: Entity | J39: Non Linear | L39: Yes | M39: Buildings | P39: =A39&"-"&U39 -> AR-BD-CONC-00 | Q39: Concourse | U39: =C39& "-" &E39 & IF(G39<>"","-" &G39,"-00") -> BD-CONC-00 | V39: =C39& "-" &E39 & IF(G39<>"","-" &G39,"") -> BD-CONC | W39: =VLOOKUP(V39,'[2]Asset Classifications'!$M$12:$M$1690,1,FALSE) -> BD-CONC | AA39: BD-CONC | AB39: 36
A40: AR | B40: Architecture & Services | C40: BD | D40: Buildings & Access | E40: DOLP | F40: Dolphin Structure | I40: Entity | J40: Non Linear | K40: I | L40: Yes | M40: Buildings | N40: BD-DOLP | O40: Dolphin Structure | P40: =A40&"-"&U40 -> AR-BD-DOLP-00 | Q40: Dolphin Structure | U40: =C40& "-" &E40 & IF(G40<>"","-" &G40,"-00") -> BD-DOLP-00 | V40: =C40& "-" &E40 & IF(G40<>"","-" &G40,"") -> BD-DOLP | Y40: v153
A41: AR | B41: Architecture & Services | C41: BD | D41: Buildings & Access | E41: DOOR | F41: Door | G41: EN | H41: Egress-Non Fire Rated | I41: Product | J41: Non Linear | K41: I | L41: No, with parent | N41: BD-DOOR-EN | O41: Door-Egress-Non Fire | P41: =A41&"-"&U41 -> AR-BD-DOOR-EN | Q41: Door-Egress-Non Fire | U41: =C41& "-" &E41 & IF(G41<>"","-" &G41,"-00") -> BD-DOOR-EN | V41: =C41& "-" &E41 & IF(G41<>"","-" &G41,"") -> BD-DOOR-EN | Y41: v153
A42: AR | B42: Architecture & Services | C42: BD | D42: Buildings & Access | E42: DOOR | F42: Door | G42: HB | H42: Hinged bi-fold | I42: Product | J42: Non Linear | L42: Yes | M42: Buildings | P42: =A42&"-"&U42 -> AR-BD-DOOR-HB | Q42: Door-Hinged bi-fold | U42: =C42& "-" &E42 & IF(G42<>"","-" &G42,"-00") -> BD-DOOR-HB | V42: =C42& "-" &E42 & IF(G42<>"","-" &G42,"") -> BD-DOOR-HB | W42: =VLOOKUP(V42,'[2]Asset Classifications'!$M$12:$M$1690,1,FALSE) -> BD-DOOR-HB | Y42: from_v202002 | AA42: BD-DOOR-HB | AB42: 37
A43: AR | B43: Architecture & Services | C43: BD | D43: Buildings & Access | E43: DOOR | F43: Door | G43: HS | H43: Hinged single | I43: Product | J43: Non Linear | L43: Yes | M43: Buildings | P43: =A43&"-"&U43 -> AR-BD-DOOR-HS | Q43: Door-Hinged single | U43: =C43& "-" &E43 & IF(G43<>"","-" &G43,"-00") -> BD-DOOR-HS | V43: =C43& "-" &E43 & IF(G43<>"","-" &G43,"") -> BD-DOOR-HS | W43: =VLOOKUP(V43,'[2]Asset Classifications'!$M$12:$M$1690,1,FALSE) -> BD-DOOR-HS | Y43: from_v202002 | AA43: BD-DOOR-HS | AB43: 38
A44: AR | B44: Architecture & Services | C44: BD | D44: Buildings & Access | E44: DOOR | F44: Door | G44: PS | H44: Panel Section | I44: Product | J44: Non Linear | L44: Yes | M44: Buildings | P44: =A44&"-"&U44 -> AR-BD-DOOR-PS | Q44: Door-Panel Section | U44: =C44& "-" &E44 & IF(G44<>"","-" &G44,"-00") -> BD-DOOR-PS | V44: =C44& "-" &E44 & IF(G44<>"","-" &G44,"") -> BD-DOOR-PS | W44: =VLOOKUP(V44,'[2]Asset Classifications'!$M$12:$M$1690,1,FALSE) -> BD-DOOR-PS | Y44: from_v202002 | AA44: BD-DOOR-PS | AB44: 39
A45: AR | B45: Architecture & Services | C45: BD | D45: Buildings & Access | E45: DOOR | F45: Door | G45: RO | H45: Rollup | I45: Product | J45: Non Linear | L45: Yes | M45: Buildings | P45: =A45&"-"&U45 -> AR-BD-DOOR-RO | Q45: Door-Rollup | U45: =C45& "-" &E45 & IF(G45<>"","-" &G45,"-00") -> BD-DOOR-RO | V45: =C45& "-" &E45 & IF(G45<>"","-" &G45,"") -> BD-DOOR-RO | W45: =VLOOKUP(V45,'[2]Asset Classifications'!$M$12:$M$1690,1,FALSE) -> BD-DOOR-RO | Y45: from_v202002 | AA45: BD-DOOR-RO | AB45: 40
A46: AR | B46: Architecture & Services | C46: BD | D46: Buildings & Access | E46: DOOR | F46: Door | G46: SL | H46: Sliding | I46: Product | J46: Non Linear | L46: Yes | M46: Buildings | P46: =A46&"-"&U46 -> AR-BD-DOOR-SL | Q46: Door-Sliding | U46: =C46& "-" &E46 & IF(G46<>"","-" &G46,"-00") -> BD-DOOR-SL | V46: =C46& "-" &E46 & IF(G46<>"","-" &G46,"") -> BD-DOOR-SL | W46: =VLOOKUP(V46,'[2]Asset Classifications'!$M$12:$M$1690,1,FALSE) -> BD-DOOR-SL | Y46: from_v202002 | AA46: BD-DOOR-SL | AB46: 41
A47: AR | B47: Architecture & Services | C47: BD | D47: Buildings & Access | E47: DOOR | F47: Door | G47: TC | H47: Tilt-up canopy | I47: Product | J47: Non Linear | L47: Yes | M47: Buildings | P47: =A47&"-"&U47 -> AR-BD-DOOR-TC | Q47: Door-Tilt-up canopy | U47: =C47& "-" &E47 & IF(G47<>"","-" &G47,"-00") -> BD-DOOR-TC | V47: =C47& "-" &E47 & IF(G47<>"","-" &G47,"") -> BD-DOOR-TC | W47: =VLOOKUP(V47,'[2]Asset Classifications'!$M$12:$M$1690,1,FALSE) -> BD-DOOR-TC | Y47: from_v202002 | AA47: BD-DOOR-TC | AB47: 42
A48: AR | B48: Architecture & Services | C48: BD | D48: Buildings & Access | E48: DOOR | F48: Door | G48: TR | H48: Tilt-up retractable | I48: Product | J48: Non Linear | L48: Yes | M48: Buildings | P48: =A48&"-"&U48 -> AR-BD-DOOR-TR | Q48: Door-Tilt-up retract | U48: =C48& "-" &E48 & IF(G48<>"","-" &G48,"-00") -> BD-DOOR-TR | V48: =C48& "-" &E48 & IF(G48<>"","-" &G48,"") -> BD-DOOR-TR | W48: =VLOOKUP(V48,'[2]Asset Classifications'!$M$12:$M$1690,1,FALSE) -> BD-DOOR-TR | Y48: from_v202002 | AA48: BD-DOOR-TR | AB48: 43
A49: AR | B49: Architecture & Services | C49: BD | D49: Buildings & Access | E49: EXPB | F49: Expandable Barrier | I49: Product | J49: Non Linear | L49: Yes | M49: Plant & Equipment | P49: =A49&"-"&U49 -> AR-BD-EXPB-00 | Q49: Expandable Barrier | U49: =C49& "-" &E49 & IF(G49<>"","-" &G49,"-00") -> BD-EXPB-00 | V49: =C49& "-" &E49 & IF(G49<>"","-" &G49,"") -> BD-EXPB | W49: =VLOOKUP(V49,'[2]Asset Classifications'!$M$12:$M$1690,1,FALSE) -> BD-EXPB | Y49: from_v202002 | AA49: BD-EXPB | AB49: 44
A50: AR | B50: Architecture & Services | C50: BD | D50: Buildings & Access | E50: GWAY | F50: Gangway | I50: Entity | J50: Non Linear | L50: Yes | M50: Buildings | P50: =A50&"-"&U50 -> AR-BD-GWAY-00 | Q50: Gangway | U50: =C50& "-" &E50 & IF(G50<>"","-" &G50,"-00") -> BD-GWAY-00 | V50: =C50& "-" &E50 & IF(G50<>"","-" &G50,"") -> BD-GWAY | W50: =VLOOKUP(V50,'[2]Asset Classifications'!$M$12:$M$1690,1,FALSE) -> BD-GWAY | AA50: BD-GWAY | AB50: 45
A51: AR | B51: Architecture & Services | C51: BD | D51: Buildings & Access | E51: HSRE | F51: Height Safety Restraint | I51: Product | J51: Non Linear | L51: Yes | M51: Buildings | P51: =A51&"-"&U51 -> AR-BD-HSRE-00 | Q51: Hgt Safety Restraint | U51: =C51& "-" &E51 & IF(G51<>"","-" &G51,"-00") -> BD-HSRE-00 | V51: =C51& "-" &E51 & IF(G51<>"","-" &G51,"") -> BD-HSRE | W51: =VLOOKUP(V51,'[2]Asset Classifications'!$M$12:$M$1690,1,FALSE) -> BD-HSRE | Y51: from_v202002 | AA51: BD-HSRE | AB51: 46
A52: AR | B52: Architecture & Services | C52: BD | D52: Buildings & Access | E52: HSTD | F52: Hardstand | I52: Entity | J52: Non Linear | L52: Yes | M52: Buildings | P52: =A52&"-"&U52 -> AR-BD-HSTD-00 | Q52: Hardstand | U52: =C52& "-" &E52 & IF(G52<>"","-" &G52,"-00") -> BD-HSTD-00 | V52: =C52& "-" &E52 & IF(G52<>"","-" &G52,"") -> BD-HSTD | W52: =VLOOKUP(V52,'[2]Asset Classifications'!$M$12:$M$1690,1,FALSE) -> #N/A | AA52: BD-HSTD | AB52: 47
A53: AR | B53: Architecture & Services | C53: BD | D53: Buildings & Access | E53: ISCA | F53: Integrated Services Cabinet | I53: Product | J53: Non Linear | L53: Yes | M53: Buildings | P53: =A53&"-"&U53 -> AR-BD-ISCA-00 | Q53: Int Services Cabinet | U53: =C53& "-" &E53 & IF(G53<>"","-" &G53,"-00") -> BD-ISCA-00 | V53: =C53& "-" &E53 & IF(G53<>"","-" &G53,"") -> BD-ISCA | W53: =VLOOKUP(V53,'[2]Asset Classifications'!$M$12:$M$1690,1,FALSE) -> BD-ISCA | Y53: from_v202002 | AA53: BD-ISCA | AB53: 48
A54: AR | B54: Architecture & Services | C54: BD | D54: Buildings & Access | E54: JETY | F54: Jetty | I54: Entity | J54: Non Linear | L54: Yes | M54: Buildings | P54: =A54&"-"&U54 -> AR-BD-JETY-00 | Q54: Jetty | U54: =C54& "-" &E54 & IF(G54<>"","-" &G54,"-00") -> BD-JETY-00 | V54: =C54& "-" &E54 & IF(G54<>"","-" &G54,"") -> BD-JETY | W54: =VLOOKUP(V54,'[2]Asset Classifications'!$M$12:$M$1690,1,FALSE) -> BD-JETY | AA54: BD-JETY | AB54: 49
A55: AR | B55: Architecture & Services | C55: BD | D55: Buildings & Access | E55: LADR | F55: Ladder | I55: Product | J55: Non Linear | L55: Yes | M55: Buildings | P55: =A55&"-"&U55 -> AR-BD-LADR-00 | Q55: Ladder | U55: =C55& "-" &E55 & IF(G55<>"","-" &G55,"-00") -> BD-LADR-00 | V55: =C55& "-" &E55 & IF(G55<>"","-" &G55,"") -> BD-LADR | W55: =VLOOKUP(V55,'[2]Asset Classifications'!$M$12:$M$1690,1,FALSE) -> BD-LADR | AA55: BD-LADR | AB55: 50
A56: AR | B56: Architecture & Services | C56: BD | D56: Buildings & Access | E56: LFTT | F56: Lift Tower | I56: Entity | J56: Non Linear | L56: Yes | M56: Buildings | P56: =A56&"-"&U56 -> AR-BD-LFTT-00 | Q56: Lift Tower | U56: =C56& "-" &E56 & IF(G56<>"","-" &G56,"-00") -> BD-LFTT-00 | V56: =C56& "-" &E56 & IF(G56<>"","-" &G56,"") -> BD-LFTT | W56: =VLOOKUP(V56,'[2]Asset Classifications'!$M$12:$M$1690,1,FALSE) -> BD-LFTT | AA56: BD-LFTT | AB56: 51
A57: AR | B57: Architecture & Services | C57: BD | D57: Buildings & Access | E57: MRMP | F57: Movable Access Ramp | I57: Entity | J57: Non Linear | K57: I | L57: Yes | M57: Buildings | N57: BD-MRMP | O57: Movable Access Ramp | P57: =A57&"-"&U57 -> AR-BD-MRMP-00 | Q57: Movable Access Ramp | U57: =C57& "-" &E57 & IF(G57<>"","-" &G57,"-00") -> BD-MRMP-00 | V57: =C57& "-" &E57 & IF(G57<>"","-" &G57,"") -> BD-MRMP | Y57: v153
A58: AR | B58: Architecture & Services | C58: BD | D58: Buildings & Access | E58: PIER | F58: Pier | I58: Entity | J58: Non Linear | L58: Yes | M58: Buildings | P58: =A58&"-"&U58 -> AR-BD-PIER-00 | Q58: Pier | U58: =C58& "-" &E58 & IF(G58<>"","-" &G58,"-00") -> BD-PIER-00 | V58: =C58& "-" &E58 & IF(G58<>"","-" &G58,"") -> BD-PIER | W58: =VLOOKUP(V58,'[2]Asset Classifications'!$M$12:$M$1690,1,FALSE) -> BD-PIER | AA58: BD-PIER | AB58: 52
A59: AR | B59: Architecture & Services | C59: BD | D59: Buildings & Access | E59: PILE | F59: Pile | I59: Product | J59: Non Linear | K59: I | L59: No, with parent | N59: BD-PILE | O59: Pile | P59: =A59&"-"&U59 -> AR-BD-PILE-00 | Q59: Pile | U59: =C59& "-" &E59 & IF(G59<>"","-" &G59,"-00") -> BD-PILE-00 | V59: =C59& "-" &E59 & IF(G59<>"","-" &G59,"") -> BD-PILE | Y59: v153
A60: AR | B60: Architecture & Services | C60: BD | D60: Buildings & Access | E60: PLAT | F60: Platform | G60: LR | H60: Tram Stop | I60: Entity | J60: Linear | L60: Yes | M60: Buildings | P60: =A60&"-"&U60 -> AR-BD-PLAT-LR | Q60: Platform-Tram Stop | U60: =C60& "-" &E60 & IF(G60<>"","-" &G60,"-00") -> BD-PLAT-LR | V60: =C60& "-" &E60 & IF(G60<>"","-" &G60,"") -> BD-PLAT-LR | W60: =VLOOKUP(V60,'[2]Asset Classifications'!$M$12:$M$1690,1,FALSE) -> BD-PLAT-LR | AA60: BD-PLAT-LR | AB60: 53
A61: AR | B61: Architecture & Services | C61: BD | D61: Buildings & Access | E61: PLAT | F61: Platform | G61: TR | H61: Train Station | I61: Entity | J61: Linear | L61: Yes | M61: Buildings | P61: =A61&"-"&U61 -> AR-BD-PLAT-TR | Q61: Platform-Train Stn | U61: =C61& "-" &E61 & IF(G61<>"","-" &G61,"-00") -> BD-PLAT-TR | V61: =C61& "-" &E61 & IF(G61<>"","-" &G61,"") -> BD-PLAT-TR | W61: =VLOOKUP(V61,'[2]Asset Classifications'!$M$12:$M$1690,1,FALSE) -> BD-PLAT-TR | X61: Road | AA61: BD-PLAT-TR | AB61: 54
A62: AR | B62: Architecture & Services | C62: BD | D62: Buildings & Access | E62: PLAT | F62: Platform | G62: WH | H62: Wharf | I62: Entity | J62: Non Linear | K62: I | L62: Yes | M62: Buildings | N62: BD-PLAT-WH | O62: Platform-Wharf | P62: =A62&"-"&U62 -> AR-BD-PLAT-WH | Q62: Platform-Wharf | U62: =C62& "-" &E62 & IF(G62<>"","-" &G62,"-00") -> BD-PLAT-WH | V62: =C62& "-" &E62 & IF(G62<>"","-" &G62,"") -> BD-PLAT-WH | Y62: v153
A63: AR | B63: Architecture & Services | C63: BD | D63: Buildings & Access | E63: PLTD | F63: Platform Door | G63: ED | H63: Edge Door | I63: Product | J63: Non Linear | K63: I | L63: No, with platform | N63: BD-PLTD-ED | O63: Platform Edge Door | P63: =A63&"-"&U63 -> AR-BD-PLTD-ED | Q63: Platform Edge Door | U63: =C63& "-" &E63 & IF(G63<>"","-" &G63,"-00") -> BD-PLTD-ED | V63: =C63& "-" &E63 & IF(G63<>"","-" &G63,"") -> BD-PLTD-ED | Y63: v153
A64: AR | B64: Architecture & Services | C64: BD | D64: Buildings & Access | E64: PLTD | F64: Platform Door | G64: SD | H64: Full Screen Door | I64: Product | J64: Non Linear | K64: I | L64: No, with platform | N64: BD-PLTD-SD | O64: Platform Screen Door | P64: =A64&"-"&U64 -> AR-BD-PLTD-SD | Q64: Platform Screen Door | U64: =C64& "-" &E64 & IF(G64<>"","-" &G64,"-00") -> BD-PLTD-SD | V64: =C64& "-" &E64 & IF(G64<>"","-" &G64,"") -> BD-PLTD-SD | Y64: v153
A65: AR | B65: Architecture & Services | C65: BD | D65: Buildings & Access | E65: PLTH | F65: Plinth | I65: Entity | J65: Non Linear | L65: Yes | M65: Buildings | P65: =A65&"-"&U65 -> AR-BD-PLTH-00 | Q65: Plinth | U65: =C65& "-" &E65 & IF(G65<>"","-" &G65,"-00") -> BD-PLTH-00 | V65: =C65& "-" &E65 & IF(G65<>"","-" &G65,"") -> BD-PLTH | W65: =VLOOKUP(V65,'[2]Asset Classifications'!$M$12:$M$1690,1,FALSE) -> #N/A | AA65: BD-PLTH | AB65: 55
A66: AR | B66: Architecture & Services | C66: BD | D66: Buildings & Access | E66: PMGF | F66: Platform Mechanical Gap Filler | I66: Product | J66: Non Linear | K66: I | L66: No, with platform | N66: BD-PMGF | O66: Plat Mech Gap Filler | P66: =A66&"-"&U66 -> AR-BD-PMGF-00 | Q66: Plat Mech Gap Filler | U66: =C66& "-" &E66 & IF(G66<>"","-" &G66,"-00") -> BD-PMGF-00 | V66: =C66& "-" &E66 & IF(G66<>"","-" &G66,"") -> BD-PMGF | Y66: v153
A67: AR | B67: Architecture & Services | C67: BD | D67: Buildings & Access | E67: PONT | F67: Pontoon | G67: FU | H67: Fuel | I67: Entity | J67: Non Linear | K67: I | L67: Yes | M67: Buildings | N67: BD-PONT-FU | O67: Pontoon-Fuel | P67: =A67&"-"&U67 -> AR-BD-PONT-FU | Q67: Pontoon-Fuel | U67: =C67& "-" &E67 & IF(G67<>"","-" &G67,"-00") -> BD-PONT-FU | V67: =C67& "-" &E67 & IF(G67<>"","-" &G67,"") -> BD-PONT-FU | Y67: v153
A68: AR | B68: Architecture & Services | C68: BD | D68: Buildings & Access | E68: PONT | F68: Pontoon | G68: WH | H68: Wharf | I68: Entity | J68: Non Linear | K68: I | L68: Yes | M68: Buildings | N68: BD-PONT-WH | O68: Pontoon-Wharf | P68: =A68&"-"&U68 -> AR-BD-PONT-WH | Q68: Pontoon-Wharf | U68: =C68& "-" &E68 & IF(G68<>"","-" &G68,"-00") -> BD-PONT-WH | V68: =C68& "-" &E68 & IF(G68<>"","-" &G68,"") -> BD-PONT-WH | Y68: v153
A69: AR | B69: Architecture & Services | C69: BD | D69: Buildings & Access | E69: PONT | F69: Pontoon | I69: Entity | J69: Non Linear | L69: Yes | M69: Buildings | P69: =A69&"-"&U69 -> AR-BD-PONT-00 | Q69: Pontoon | U69: =C69& "-" &E69 & IF(G69<>"","-" &G69,"-00") -> BD-PONT-00 | V69: =C69& "-" &E69 & IF(G69<>"","-" &G69,"") -> BD-PONT | W69: =VLOOKUP(V69,'[2]Asset Classifications'!$M$12:$M$1690,1,FALSE) -> BD-PONT | AA69: BD-PONT | AB69: 56
A70: AR | B70: Architecture & Services | C70: BD | D70: Buildings & Access | E70: STRS | F70: Stairs | G70: AC | H70: Access | I70: Entity | J70: Non Linear | L70: Yes | M70: Buildings | P70: =A70&"-"&U70 -> AR-BD-STRS-AC | Q70: Stairs-Bldg Access | U70: =C70& "-" &E70 & IF(G70<>"","-" &G70,"-00") -> BD-STRS-AC | V70: =C70& "-" &E70 & IF(G70<>"","-" &G70,"") -> BD-STRS-AC | W70: =VLOOKUP(V70,'[2]Asset Classifications'!$M$12:$M$1690,1,FALSE) -> BD-STRS-AC | AA70: BD-STRS-AC | AB70: 57
A71: AR | B71: Architecture & Services | C71: BD | D71: Buildings & Access | E71: STRS | F71: Stairs | G71: FI | H71: Fire | I71: Entity | J71: Non Linear | L71: Yes | M71: Buildings | P71: =A71&"-"&U71 -> AR-BD-STRS-FI | Q71: Stairs-Fire | U71: =C71& "-" &E71 & IF(G71<>"","-" &G71,"-00") -> BD-STRS-FI | V71: =C71& "-" &E71 & IF(G71<>"","-" &G71,"") -> BD-STRS-FI | W71: =VLOOKUP(V71,'[2]Asset Classifications'!$M$12:$M$1690,1,FALSE) -> BD-STRS-FI | AA71: BD-STRS-FI | AB71: 58
A72: AR | B72: Architecture & Services | C72: BD | D72: Buildings & Access | E72: STRS | F72: Stairs | G72: TP | H72: Track to Platform | I72: Product | J72: Non Linear | L72: Yes | M72: Plant & Equipment | P72: =A72&"-"&U72 -> AR-BD-STRS-TP | Q72: Stairs-Trk to Platfm | U72: =C72& "-" &E72 & IF(G72<>"","-" &G72,"-00") -> BD-STRS-TP | V72: =C72& "-" &E72 & IF(G72<>"","-" &G72,"") -> BD-STRS-TP | W72: =VLOOKUP(V72,'[2]Asset Classifications'!$M$12:$M$1690,1,FALSE) -> BD-STRS-TP | AA72: BD-STRS-TP | AB72: 59
A73: AR | B73: Architecture & Services | C73: BD | D73: Buildings & Access | E73: STRS | F73: Stairs | G73: TT | H73: Train to Track | I73: Product | J73: Non Linear | L73: Yes | M73: Plant & Equipment | P73: =A73&"-"&U73 -> AR-BD-STRS-TT | Q73: Stairs-Train to Trk | U73: =C73& "-" &E73 & IF(G73<>"","-" &G73,"-00") -> BD-STRS-TT | V73: =C73& "-" &E73 & IF(G73<>"","-" &G73,"") -> BD-STRS-TT | W73: =VLOOKUP(V73,'[2]Asset Classifications'!$M$12:$M$1690,1,FALSE) -> BD-STRS-TT | AA73: BD-STRS-TT | AB73: 60
A74: AR | B74: Architecture & Services | C74: BD | D74: Buildings & Access | E74: SUTE | F74: Suite | I74: Space | J74: Non Linear | L74: No | P74: =A74&"-"&U74 -> AR-BD-SUTE-00 | Q74: Suite | U74: =C74& "-" &E74 & IF(G74<>"","-" &G74,"-00") -> BD-SUTE-00 | V74: =C74& "-" &E74 & IF(G74<>"","-" &G74,"") -> BD-SUTE | W74: =VLOOKUP(V74,'[2]Asset Classifications'!$M$12:$M$1690,1,FALSE) -> BD-SUTE | Y74: from_v202002 | AA74: BD-SUTE | AB74: 61
A75: AR | B75: Architecture & Services | C75: BD | D75: Buildings & Access | E75: VRMP | F75: Vehicular Ramp | I75: Entity | J75: Non Linear | K75: I | L75: No, with parent | N75: BD-VRMP | O75: Vehicular Ramp | P75: =A75&"-"&U75 -> AR-BD-VRMP-00 | Q75: Vehicular Ramp | U75: =C75& "-" &E75 & IF(G75<>"","-" &G75,"-00") -> BD-VRMP-00 | V75: =C75& "-" &E75 & IF(G75<>"","-" &G75,"") -> BD-VRMP | Y75: v153
A76: AR | B76: Architecture & Services | C76: BD | D76: Buildings & Access | E76: WALK | F76: Walkway | I76: Entity | J76: Non Linear | L76: Yes | M76: Buildings | P76: =A76&"-"&U76 -> AR-BD-WALK-00 | Q76: Walkway-Bldg Access | U76: =C76& "-" &E76 & IF(G76<>"","-" &G76,"-00") -> BD-WALK-00 | V76: =C76& "-" &E76 & IF(G76<>"","-" &G76,"") -> BD-WALK | W76: =VLOOKUP(V76,'[2]Asset Classifications'!$M$12:$M$1690,1,FALSE) -> BD-WALK | AA76: BD-WALK | AB76: 62
A77: AR | B77: Architecture & Services | C77: CA | D77: Compressed Air Systems | E77: AIRD | F77: Air Dryer | I77: Product | J77: Non Linear | L77: No, with parent system | P77: =A77&"-"&U77 -> AR-CA-AIRD-00 | Q77: Air Sup-Air Dryer | U77: =C77& "-" &E77 & IF(G77<>"","-" &G77,"-00") -> CA-AIRD-00 | V77: =C77& "-" &E77 & IF(G77<>"","-" &G77,"") -> CA-AIRD | W77: =VLOOKUP(V77,'[2]Asset Classifications'!$M$12:$M$1690,1,FALSE) -> CA-AIRD | AA77: CA-AIRD | AB77: 63
A78: AR | B78: Architecture & Services | C78: CA | D78: Compressed Air Systems | E78: AIRM | F78: Air Main | I78: Product | J78: Linear | L78: No, with parent system | P78: =A78&"-"&U78 -> AR-CA-AIRM-00 | Q78: Air Sup-Main | U78: =C78& "-" &E78 & IF(G78<>"","-" &G78,"-00") -> CA-AIRM-00 | V78: =C78& "-" &E78 & IF(G78<>"","-" &G78,"") -> CA-AIRM | W78: =VLOOKUP(V78,'[2]Asset Classifications'!$M$12:$M$1690,1,FALSE) -> CA-AIRM | AA78: CA-AIRM | AB78: 64
A79: AR | B79: Architecture & Services | C79: CA | D79: Compressed Air Systems | E79: AIRR | F79: Air Receiver | I79: Product | J79: Non Linear | L79: No, with parent system | P79: =A79&"-"&U79 -> AR-CA-AIRR-00 | Q79: Air Sup-Air Receiver | U79: =C79& "-" &E79 & IF(G79<>"","-" &G79,"-00") -> CA-AIRR-00 | V79: =C79& "-" &E79 & IF(G79<>"","-" &G79,"") -> CA-AIRR | W79: =VLOOKUP(V79,'[2]Asset Classifications'!$M$12:$M$1690,1,FALSE) -> CA-AIRR | AA79: CA-AIRR | AB79: 65
A80: AR | B80: Architecture & Services | C80: CA | D80: Compressed Air Systems | E80: AIRS | F80: Air Supply System | G80: DP | H80: Depot | I80: System | J80: Non Linear | L80: Yes, each system | M80: Buildings | P80: =A80&"-"&U80 -> AR-CA-AIRS-DP | Q80: Air Supply Sys-Depot | U80: =C80& "-" &E80 & IF(G80<>"","-" &G80,"-00") -> CA-AIRS-DP | V80: =C80& "-" &E80 & IF(G80<>"","-" &G80,"") -> CA-AIRS-DP | W80: =VLOOKUP(V80,'[2]Asset Classifications'!$M$12:$M$1690,1,FALSE) -> CA-AIRS-DP | AA80: CA-AIRS-DP | AB80: 66
A81: AR | B81: Architecture & Services | C81: CA | D81: Compressed Air Systems | E81: AIRS | F81: Air Supply System | G81: SI | H81: Signalling | I81: System | J81: Non Linear | L81: Yes, each system | M81: Infrastructure | P81: =A81&"-"&U81 -> AR-CA-AIRS-SI | Q81: Air Supply Sys-Signl | U81: =C81& "-" &E81 & IF(G81<>"","-" &G81,"-00") -> CA-AIRS-SI | V81: =C81& "-" &E81 & IF(G81<>"","-" &G81,"") -> CA-AIRS-SI | W81: =VLOOKUP(V81,'[2]Asset Classifications'!$M$12:$M$1690,1,FALSE) -> CA-AIRS-SI | AA81: CA-AIRS-SI | AB81: 67
A82: AR | B82: Architecture & Services | C82: CA | D82: Compressed Air Systems | E82: AIRS | F82: Air Supply System | G82: SS | H82: Substation | I82: System | J82: Non Linear | L82: Yes, each system | M82: Infrastructure | P82: =A82&"-"&U82 -> AR-CA-AIRS-SS | Q82: Air Supply Sys-Subs | U82: =C82& "-" &E82 & IF(G82<>"","-" &G82,"-00") -> CA-AIRS-SS | V82: =C82& "-" &E82 & IF(G82<>"","-" &G82,"") -> CA-AIRS-SS | W82: =VLOOKUP(V82,'[2]Asset Classifications'!$M$12:$M$1690,1,FALSE) -> CA-AIRS-SS | AA82: CA-AIRS-SS | AB82: 68
A83: AR | B83: Architecture & Services | C83: CA | D83: Compressed Air Systems | E83: AUTO | F83: Auto Drain | I83: Product | J83: Non Linear | L83: No, with parent system | P83: =A83&"-"&U83 -> AR-CA-AUTO-00 | Q83: Air Sup-Auto Drain | U83: =C83& "-" &E83 & IF(G83<>"","-" &G83,"-00") -> CA-AUTO-00 | V83: =C83& "-" &E83 & IF(G83<>"","-" &G83,"") -> CA-AUTO | W83: =VLOOKUP(V83,'[2]Asset Classifications'!$M$12:$M$1690,1,FALSE) -> CA-AUTO | AA83: CA-AUTO | AB83: 69
A84: AR | B84: Architecture & Services | C84: CA | D84: Compressed Air Systems | E84: COMP | F84: Compressor | I84: Product | J84: Non Linear | L84: No, with parent system | P84: =A84&"-"&U84 -> AR-CA-COMP-00 | Q84: Compressor (Fxd) | U84: =C84& "-" &E84 & IF(G84<>"","-" &G84,"-00") -> CA-COMP-00 | V84: =C84& "-" &E84 & IF(G84<>"","-" &G84,"") -> CA-COMP | W84: =VLOOKUP(V84,'[2]Asset Classifications'!$M$12:$M$1690,1,FALSE) -> CA-COMP | AA84: CA-COMP | AB84: 70
A85: AR | B85: Architecture & Services | C85: CA | D85: Compressed Air Systems | E85: EXPJ | F85: Expansion Joint | I85: Product | J85: Non Linear | L85: No, with parent system | P85: =A85&"-"&U85 -> AR-CA-EXPJ-00 | Q85: Air Sup-Expansn Jnt | U85: =C85& "-" &E85 & IF(G85<>"","-" &G85,"-00") -> CA-EXPJ-00 | V85: =C85& "-" &E85 & IF(G85<>"","-" &G85,"") -> CA-EXPJ | W85: =VLOOKUP(V85,'[2]Asset Classifications'!$M$12:$M$1690,1,FALSE) -> CA-EXPJ | AA85: CA-EXPJ | AB85: 71
A86: AR | B86: Architecture & Services | C86: CA | D86: Compressed Air Systems | E86: MANI | F86: Air Manifold | I86: Product | J86: Non Linear | L86: No, with parent system | P86: =A86&"-"&U86 -> AR-CA-MANI-00 | Q86: Air Sup-Air Manifold | U86: =C86& "-" &E86 & IF(G86<>"","-" &G86,"-00") -> CA-MANI-00 | V86: =C86& "-" &E86 & IF(G86<>"","-" &G86,"") -> CA-MANI | W86: =VLOOKUP(V86,'[2]Asset Classifications'!$M$12:$M$1690,1,FALSE) -> CA-MANI | AA86: CA-MANI | AB86: 72
A87: AR | B87: Architecture & Services | C87: CA | D87: Compressed Air Systems | E87: PRTX | F87: Pressure Transmitter | I87: Product | J87: Non Linear | L87: No, with parent system | P87: =A87&"-"&U87 -> AR-CA-PRTX-00 | Q87: Air Sup-Pressure Tx | U87: =C87& "-" &E87 & IF(G87<>"","-" &G87,"-00") -> CA-PRTX-00 | V87: =C87& "-" &E87 & IF(G87<>"","-" &G87,"") -> CA-PRTX | W87: =VLOOKUP(V87,'[2]Asset Classifications'!$M$12:$M$1690,1,FALSE) -> CA-PRTX | AA87: CA-PRTX | AB87: 73
A88: AR | B88: Architecture & Services | C88: ES | D88: LV Reticulation & Lighting Systems | E88: ATSW | F88: Automatic Transfer Switch | I88: Product | J88: Non Linear | L88: No, with parent system | P88: =A88&"-"&U88 -> AR-ES-ATSW-00 | Q88: Auto Transfer Switch | U88: =C88& "-" &E88 & IF(G88<>"","-" &G88,"-00") -> ES-ATSW-00 | V88: =C88& "-" &E88 & IF(G88<>"","-" &G88,"") -> ES-ATSW | W88: =VLOOKUP(V88,'[2]Asset Classifications'!$M$12:$M$1690,1,FALSE) -> ES-ATSW | AA88: ES-ATSW | AB88: 74
A89: AR | B89: Architecture & Services | C89: ES | D89: LV Reticulation & Lighting Systems | E89: BATT | F89: Battery | I89: Product | J89: Non Linear | L89: No, with parent system | P89: =A89&"-"&U89 -> AR-ES-BATT-00 | Q89: LV BU Battery | U89: =C89& "-" &E89 & IF(G89<>"","-" &G89,"-00") -> ES-BATT-00 | V89: =C89& "-" &E89 & IF(G89<>"","-" &G89,"") -> ES-BATT | W89: =VLOOKUP(V89,'[2]Asset Classifications'!$M$12:$M$1690,1,FALSE) -> ES-BATT | AA89: ES-BATT | AB89: 75
A90: AR | B90: Architecture & Services | C90: ES | D90: LV Reticulation & Lighting Systems | E90: CHGO | F90: Changeover Panel | I90: Product | J90: Non Linear | L90: No, with parent system | P90: =A90&"-"&U90 -> AR-ES-CHGO-00 | Q90: LV Changeover Panel | U90: =C90& "-" &E90 & IF(G90<>"","-" &G90,"-00") -> ES-CHGO-00 | V90: =C90& "-" &E90 & IF(G90<>"","-" &G90,"") -> ES-CHGO | W90: =VLOOKUP(V90,'[2]Asset Classifications'!$M$12:$M$1690,1,FALSE) -> ES-CHGO | Y90: from_v202002 | AA90: ES-CHGO | AB90: 76
A91: AR | B91: Architecture & Services | C91: ES | D91: LV Reticulation & Lighting Systems | E91: DBRD | F91: Distribution Board | G91: EM | H91: Emergency | I91: Product | J91: Non Linear | L91: No, with parent system | P91: =A91&"-"&U91 -> AR-ES-DBRD-EM | Q91: Elec DB-Emergency | U91: =C91& "-" &E91 & IF(G91<>"","-" &G91,"-00") -> ES-DBRD-EM | V91: =C91& "-" &E91 & IF(G91<>"","-" &G91,"") -> ES-DBRD-EM | W91: =VLOOKUP(V91,'[2]Asset Classifications'!$M$12:$M$1690,1,FALSE) -> ES-DBRD-EM | Y91: from_v202002 | AA91: ES-DBRD-EM | AB91: 77
A92: AR | B92: Architecture & Services | C92: ES | D92: LV Reticulation & Lighting Systems | E92: DBRD | F92: Distribution Board | G92: ES | H92: Essential | I92: Product | J92: Non Linear | L92: No, with parent system | P92: =A92&"-"&U92 -> AR-ES-DBRD-ES | Q92: Elec DB-Essential | U92: =C92& "-" &E92 & IF(G92<>"","-" &G92,"-00") -> ES-DBRD-ES | V92: =C92& "-" &E92 & IF(G92<>"","-" &G92,"") -> ES-DBRD-ES | W92: =VLOOKUP(V92,'[2]Asset Classifications'!$M$12:$M$1690,1,FALSE) -> ES-DBRD-ES | Y92: from_v202002 | AA92: ES-DBRD-ES | AB92: 78
A93: AR | B93: Architecture & Services | C93: ES | D93: LV Reticulation & Lighting Systems | E93: DBRD | F93: Distribution Board | G93: LS | H93: Life Safety | I93: Product | J93: Non Linear | L93: No, with parent system | P93: =A93&"-"&U93 -> AR-ES-DBRD-LS | Q93: Elec DB-Life Safety | U93: =C93& "-" &E93 & IF(G93<>"","-" &G93,"-00") -> ES-DBRD-LS | V93: =C93& "-" &E93 & IF(G93<>"","-" &G93,"") -> ES-DBRD-LS | W93: =VLOOKUP(V93,'[2]Asset Classifications'!$M$12:$M$1690,1,FALSE) -> ES-DBRD-LS | Y93: from_v202002 | AA93: ES-DBRD-LS | AB93: 79
A94: AR | B94: Architecture & Services | C94: ES | D94: LV Reticulation & Lighting Systems | E94: DBRD | F94: Distribution Board | G94: MN | H94: Main | I94: Product | J94: Non Linear | L94: No, with parent system | P94: =A94&"-"&U94 -> AR-ES-DBRD-MN | Q94: Fclty Elec DB-Main | U94: =C94& "-" &E94 & IF(G94<>"","-" &G94,"-00") -> ES-DBRD-MN | V94: =C94& "-" &E94 & IF(G94<>"","-" &G94,"") -> ES-DBRD-MN | W94: =VLOOKUP(V94,'[2]Asset Classifications'!$M$12:$M$1690,1,FALSE) -> #N/A | AA94: ES-DBRD-MN | AB94: 80
A95: AR | B95: Architecture & Services | C95: ES | D95: LV Reticulation & Lighting Systems | E95: DBRD | F95: Distribution Board | G95: NO | H95: Normal | I95: Product | J95: Non Linear | L95: No, with parent system | P95: =A95&"-"&U95 -> AR-ES-DBRD-NO | Q95: Elec DB-Normal | U95: =C95& "-" &E95 & IF(G95<>"","-" &G95,"-00") -> ES-DBRD-NO | V95: =C95& "-" &E95 & IF(G95<>"","-" &G95,"") -> ES-DBRD-NO | W95: =VLOOKUP(V95,'[2]Asset Classifications'!$M$12:$M$1690,1,FALSE) -> ES-DBRD-NO | Y95: from_v202002 | AA95: ES-DBRD-NO | AB95: 81
A96: AR | B96: Architecture & Services | C96: ES | D96: LV Reticulation & Lighting Systems | E96: DBRD | F96: Distribution Board | G96: SU | H96: Sub | I96: Product | J96: Non Linear | L96: No, with parent system | P96: =A96&"-"&U96 -> AR-ES-DBRD-SU | Q96: Fclty Elec DB-Sub | U96: =C96& "-" &E96 & IF(G96<>"","-" &G96,"-00") -> ES-DBRD-SU | V96: =C96& "-" &E96 & IF(G96<>"","-" &G96,"") -> ES-DBRD-SU | W96: =VLOOKUP(V96,'[2]Asset Classifications'!$M$12:$M$1690,1,FALSE) -> #N/A | AA96: ES-DBRD-SU | AB96: 82
A97: AR | B97: Architecture & Services | C97: ES | D97: LV Reticulation & Lighting Systems | E97: DBRD | F97: Distribution Board | G97: UP | H97: UPS | I97: Product | J97: Non Linear | L97: No, with parent system | P97: =A97&"-"&U97 -> AR-ES-DBRD-UP | Q97: Elec DB-UPS | U97: =C97& "-" &E97 & IF(G97<>"","-" &G97,"-00") -> ES-DBRD-UP | V97: =C97& "-" &E97 & IF(G97<>"","-" &G97,"") -> ES-DBRD-UP | W97: =VLOOKUP(V97,'[2]Asset Classifications'!$M$12:$M$1690,1,FALSE) -> ES-DBRD-UP | Y97: from_v202002 | AA97: ES-DBRD-UP | AB97: 83
A98: AR | B98: Architecture & Services | C98: ES | D98: LV Reticulation & Lighting Systems | E98: ELEC | F98: LV Reticulation System | G98: BD | H98: Building | I98: System | J98: Non Linear | L98: Yes, each system | M98: Buildings | P98: =A98&"-"&U98 -> AR-ES-ELEC-BD | Q98: LV Reticulation-Bldg | U98: =C98& "-" &E98 & IF(G98<>"","-" &G98,"-00") -> ES-ELEC-BD | V98: =C98& "-" &E98 & IF(G98<>"","-" &G98,"") -> ES-ELEC-BD | W98: =VLOOKUP(V98,'[2]Asset Classifications'!$M$12:$M$1690,1,FALSE) -> ES-ELEC-BD | AA98: ES-ELEC-BD | AB98: 84
A99: AR | B99: Architecture & Services | C99: ES | D99: LV Reticulation & Lighting Systems | E99: ELEC | F99: LV Reticulation System | G99: TU | H99: Tunnel | I99: System | J99: Non Linear | L99: Yes, each system | M99: Infrastructure | P99: =A99&"-"&U99 -> AR-ES-ELEC-TU | Q99: LV Reticulation-Tunl | U99: =C99& "-" &E99 & IF(G99<>"","-" &G99,"-00") -> ES-ELEC-TU | V99: =C99& "-" &E99 & IF(G99<>"","-" &G99,"") -> ES-ELEC-TU | W99: =VLOOKUP(V99,'[2]Asset Classifications'!$M$12:$M$1690,1,FALSE) -> ES-ELEC-TU | AA99: ES-ELEC-TU | AB99: 85
A100: AR | B100: Architecture & Services | C100: ES | D100: LV Reticulation & Lighting Systems | E100: ERTH | F100: Earthing | I100: Product | J100: Non Linear | L100: No, with parent system | P100: =A100&"-"&U100 -> AR-ES-ERTH-00 | Q100: Fclty Earthing | U100: =C100& "-" &E100 & IF(G100<>"","-" &G100,"-00") -> ES-ERTH-00 | V100: =C100& "-" &E100 & IF(G100<>"","-" &G100,"") -> ES-ERTH | W100: =VLOOKUP(V100,'[2]Asset Classifications'!$M$12:$M$1690,1,FALSE) -> ES-ERTH | AA100: ES-ERTH | AB100: 86
...
